Workbook

Sheet Executive_Summary
B2: Meridian Manufacturing Co. — Inventory Health Executive Summary
B3: 40-SKU catalog | 12 months of sales & inventory history | All figures below are live formulas
B5: Total SKUs Analyzed | E5: SKUs at Stockout Risk | H5: SKUs Overstocked | K5: Excess-Risk SKUs (Overstocked + Erratic)
B6: =COUNTA(Inventory_Planning_Model!A9:A48) -> 40 | E6: =COUNTIF(Inventory_Planning_Model!R9:R48,"Stockout Risk") -> 20 | H6: =COUNTIF(Inventory_Planning_Model!R9:R48,"Overstock") -> 5 | K6: =COUNTIF(Inventory_Planning_Model!V9:V48,"Yes") -> 4
B9: Total Avg. Inventory Value | E9: Value Tied Up in Excess-Risk SKUs | H9: Catalog Inventory Turnover | K9: Forecast Accuracy (WAPE)
B10: =SUM(Inventory_Planning_Model!W9:W48) -> 233844.07 | E10: =SUMIF(Inventory_Planning_Model!V9:V48,"Yes",Inventory_Planning_Model!W9:W48) -> 111068.74 | H10: =SUMPRODUCT(Inventory_Planning_Model!K9:K48,Inventory_Planning_Model!E9:E48)/SUM(Inventory_Planning_Model!W9:W48) -> 7.6970035 | K10: =Forecast_MAPE_Summary!F6 -> 0.28053708
B13: ABC x XYZ Matrix — SKU Count
C15: X (Steady) | D15: Y (Moderate) | E15: Z (Erratic)
B16: A (Top 80% revenue) | C16: =COUNTIFS(ABC_XYZ_Classification!$H$6:$H$45,"A",ABC_XYZ_Classification!$L$6:$L$45,"X") -> 6 | D16: =COUNTIFS(ABC_XYZ_Classification!$H$6:$H$45,"A",ABC_XYZ_Classification!$L$6:$L$45,"Y") -> 5 | E16: =COUNTIFS(ABC_XYZ_Classification!$H$6:$H$45,"A",ABC_XYZ_Classification!$L$6:$L$45,"Z") -> 4
B17: B (Next 15%) | C17: =COUNTIFS(ABC_XYZ_Classification!$H$6:$H$45,"B",ABC_XYZ_Classification!$L$6:$L$45,"X") -> 5 | D17: =COUNTIFS(ABC_XYZ_Classification!$H$6:$H$45,"B",ABC_XYZ_Classification!$L$6:$L$45,"Y") -> 4 | E17: =COUNTIFS(ABC_XYZ_Classification!$H$6:$H$45,"B",ABC_XYZ_Classification!$L$6:$L$45,"Z") -> 1
B18: C (Bottom 5%) | C18: =COUNTIFS(ABC_XYZ_Classification!$H$6:$H$45,"C",ABC_XYZ_Classification!$L$6:$L$45,"X") -> 11 | D18: =COUNTIFS(ABC_XYZ_Classification!$H$6:$H$45,"C",ABC_XYZ_Classification!$L$6:$L$45,"Y") -> 2 | E18: =COUNTIFS(ABC_XYZ_Classification!$H$6:$H$45,"C",ABC_XYZ_Classification!$L$6:$L$45,"Z") -> 2
B20: AZ (top-revenue + erratic-demand) is the highest-attention cell: valuable, unpredictable, and expensive to get wrong either way.
B23: Excess-Risk SKUs (Overstocked + Erratic Demand)
B25: SKU_ID | C25: Description | D25: Category | E25: Days_of_Supply | F25: Lead_Time_Days | G25: Avg_Inventory_Value
B26: =IFERROR(INDEX(Inventory_Planning_Model!$A$9:$A$48,MATCH(1,Inventory_Planning_Model!$X$9:$X$48,0)),"—") -> MM-1033 | C26: =IFERROR(INDEX(Inventory_Planning_Model!$B$9:$B$48,MATCH(1,Inventory_Planning_Model!$X$9:$X$48,0)),"") -> Raw Material Item 04 - Raw Material - Metal Stock | D26: =IFERROR(INDEX(Inventory_Planning_Model!$C$9:$C$48,MATCH(1,Inventory_Planning_Model!$X$9:$X$48,0)),"") -> Raw Material - Metal Stock | E26: =IFERROR(ROUND(INDEX(Inventory_Planning_Model!$P$9:$P$48,MATCH(1,Inventory_Planning_Model!$X$9:$X$48,0)),0),"") -> 71 | F26: =IFERROR(INDEX(Inventory_Planning_Model!$D$9:$D$48,MATCH(1,Inventory_Planning_Model!$X$9:$X$48,0)),"") -> 38 | G26: =IFERROR(ROUND(INDEX(Inventory_Planning_Model!$W$9:$W$48,MATCH(1,Inventory_Planning_Model!$X$9:$X$48,0)),0),"") -> 70522
B27: =IFERROR(INDEX(Inventory_Planning_Model!$A$9:$A$48,MATCH(2,Inventory_Planning_Model!$X$9:$X$48,0)),"—") -> MM-1030 | C27: =IFERROR(INDEX(Inventory_Planning_Model!$B$9:$B$48,MATCH(2,Inventory_Planning_Model!$X$9:$X$48,0)),"") -> Raw Material Item 01 - Raw Material - Metal Stock | D27: =IFERROR(INDEX(Inventory_Planning_Model!$C$9:$C$48,MATCH(2,Inventory_Planning_Model!$X$9:$X$48,0)),"") -> Raw Material - Metal Stock | E27: =IFERROR(ROUND(INDEX(Inventory_Planning_Model!$P$9:$P$48,MATCH(2,Inventory_Planning_Model!$X$9:$X$48,0)),0),"") -> 93 | F27: =IFERROR(INDEX(Inventory_Planning_Model!$D$9:$D$48,MATCH(2,Inventory_Planning_Model!$X$9:$X$48,0)),"") -> 40 | G27: =IFERROR(ROUND(INDEX(Inventory_Planning_Model!$W$9:$W$48,MATCH(2,Inventory_Planning_Model!$X$9:$X$48,0)),0),"") -> 32589
B28: =IFERROR(INDEX(Inventory_Planning_Model!$A$9:$A$48,MATCH(3,Inventory_Planning_Model!$X$9:$X$48,0)),"—") -> MM-1028 | C28: =IFERROR(INDEX(Inventory_Planning_Model!$B$9:$B$48,MATCH(3,Inventory_Planning_Model!$X$9:$X$48,0)),"") -> Pneumatic Components Item 04 - Pneumatic Components | D28: =IFERROR(INDEX(Inventory_Planning_Model!$C$9:$C$48,MATCH(3,Inventory_Planning_Model!$X$9:$X$48,0)),"") -> Pneumatic Components | E28: =IFERROR(ROUND(INDEX(Inventory_Planning_Model!$P$9:$P$48,MATCH(3,Inventory_Planning_Model!$X$9:$X$48,0)),0),"") -> 134 | F28: =IFERROR(INDEX(Inventory_Planning_Model!$D$9:$D$48,MATCH(3,Inventory_Planning_Model!$X$9:$X$48,0)),"") -> 46 | G28: =IFERROR(ROUND(INDEX(Inventory_Planning_Model!$W$9:$W$48,MATCH(3,Inventory_Planning_Model!$X$9:$X$48,0)),0),"") -> 3079
B29: =IFERROR(INDEX(Inventory_Planning_Model!$A$9:$A$48,MATCH(4,Inventory_Planning_Model!$X$9:$X$48,0)),"—") -> MM-1003 | C29: =IFERROR(INDEX(Inventory_Planning_Model!$B$9:$B$48,MATCH(4,Inventory_Planning_Model!$X$9:$X$48,0)),"") -> Fasteners Item 04 - Fasteners & Hardware | D29: =IFERROR(INDEX(Inventory_Planning_Model!$C$9:$C$48,MATCH(4,Inventory_Planning_Model!$X$9:$X$48,0)),"") -> Fasteners & Hardware | E29: =IFERROR(ROUND(INDEX(Inventory_Planning_Model!$P$9:$P$48,MATCH(4,Inventory_Planning_Model!$X$9:$X$48,0)),0),"") -> 351 | F29: =IFERROR(INDEX(Inventory_Planning_Model!$D$9:$D$48,MATCH(4,Inventory_Planning_Model!$X$9:$X$48,0)),"") -> 52 | G29: =IFERROR(ROUND(INDEX(Inventory_Planning_Model!$W$9:$W$48,MATCH(4,Inventory_Planning_Model!$X$9:$X$48,0)),0),"") -> 4879
B30: =IFERROR(INDEX(Inventory_Planning_Model!$A$9:$A$48,MATCH(5,Inventory_Planning_Model!$X$9:$X$48,0)),"—") -> — | C30: =IFERROR(INDEX(Inventory_Planning_Model!$B$9:$B$48,MATCH(5,Inventory_Planning_Model!$X$9:$X$48,0)),"") | D30: =IFERROR(INDEX(Inventory_Planning_Model!$C$9:$C$48,MATCH(5,Inventory_Planning_Model!$X$9:$X$48,0)),"") | E30: =IFERROR(ROUND(INDEX(Inventory_Planning_Model!$P$9:$P$48,MATCH(5,Inventory_Planning_Model!$X$9:$X$48,0)),0),"") | F30: =IFERROR(INDEX(Inventory_Planning_Model!$D$9:$D$48,MATCH(5,Inventory_Planning_Model!$X$9:$X$48,0)),"") | G30: =IFERROR(ROUND(INDEX(Inventory_Planning_Model!$W$9:$W$48,MATCH(5,Inventory_Planning_Model!$X$9:$X$48,0)),0),"")
B31: =IFERROR(INDEX(Inventory_Planning_Model!$A$9:$A$48,MATCH(6,Inventory_Planning_Model!$X$9:$X$48,0)),"—") -> — | C31: =IFERROR(INDEX(Inventory_Planning_Model!$B$9:$B$48,MATCH(6,Inventory_Planning_Model!$X$9:$X$48,0)),"") | D31: =IFERROR(INDEX(Inventory_Planning_Model!$C$9:$C$48,MATCH(6,Inventory_Planning_Model!$X$9:$X$48,0)),"") | E31: =IFERROR(ROUND(INDEX(Inventory_Planning_Model!$P$9:$P$48,MATCH(6,Inventory_Planning_Model!$X$9:$X$48,0)),0),"") | F31: =IFERROR(INDEX(Inventory_Planning_Model!$D$9:$D$48,MATCH(6,Inventory_Planning_Model!$X$9:$X$48,0)),"") | G31: =IFERROR(ROUND(INDEX(Inventory_Planning_Model!$W$9:$W$48,MATCH(6,Inventory_Planning_Model!$X$9:$X$48,0)),0),"")
B32: =IFERROR(INDEX(Inventory_Planning_Model!$A$9:$A$48,MATCH(7,Inventory_Planning_Model!$X$9:$X$48,0)),"—") -> — | C32: =IFERROR(INDEX(Inventory_Planning_Model!$B$9:$B$48,MATCH(7,Inventory_Planning_Model!$X$9:$X$48,0)),"") | D32: =IFERROR(INDEX(Inventory_Planning_Model!$C$9:$C$48,MATCH(7,Inventory_Planning_Model!$X$9:$X$48,0)),"") | E32: =IFERROR(ROUND(INDEX(Inventory_Planning_Model!$P$9:$P$48,MATCH(7,Inventory_Planning_Model!$X$9:$X$48,0)),0),"") | F32: =IFERROR(INDEX(Inventory_Planning_Model!$D$9:$D$48,MATCH(7,Inventory_Planning_Model!$X$9:$X$48,0)),"") | G32: =IFERROR(ROUND(INDEX(Inventory_Planning_Model!$W$9:$W$48,MATCH(7,Inventory_Planning_Model!$X$9:$X$48,0)),0),"")
B33: =IFERROR(INDEX(Inventory_Planning_Model!$A$9:$A$48,MATCH(8,Inventory_Planning_Model!$X$9:$X$48,0)),"—") -> — | C33: =IFERROR(INDEX(Inventory_Planning_Model!$B$9:$B$48,MATCH(8,Inventory_Planning_Model!$X$9:$X$48,0)),"") | D33: =IFERROR(INDEX(Inventory_Planning_Model!$C$9:$C$48,MATCH(8,Inventory_Planning_Model!$X$9:$X$48,0)),"") | E33: =IFERROR(ROUND(INDEX(Inventory_Planning_Model!$P$9:$P$48,MATCH(8,Inventory_Planning_Model!$X$9:$X$48,0)),0),"") | F33: =IFERROR(INDEX(Inventory_Planning_Model!$D$9:$D$48,MATCH(8,Inventory_Planning_Model!$X$9:$X$48,0)),"") | G33: =IFERROR(ROUND(INDEX(Inventory_Planning_Model!$W$9:$W$48,MATCH(8,Inventory_Planning_Model!$X$9:$X$48,0)),0),"")
B36: Source: simulated NetSuite-style export, Meridian Manufacturing Co. | Model built in Excel with live formulas | See README tab for methodology & assumptions.

Sheet README
B2: Meridian Manufacturing Co. — Demand Forecasting & Inventory Balancing Model
B3: Supply Chain Analytics Portfolio — Project 2
B6: What this workbook does
C7: Turns a simulated 12-month NetSuite-style sales/inventory export (40 SKUs) into a live
C8: replenishment planning model: ABC/XYZ classification, safety stock & reorder points, EOQ,
C9: a FORECAST.LINEAR demand baseline with a measured MAPE, and a red/yellow/green inventory
C10: health flag for every SKU.
B12: Tab guide
B13: Assumptions | C13: Every hardcoded input used anywhere in this model, in one place.
B14: Data_Quality_Log | C14: What was messy in the raw export and how it was cleaned before this workbook.
B15: Raw_SKU_Master | C15: 40-SKU catalog: category, supplier, cost, price, UOM, lead time.
B16: Raw_Sales_Weekly | C16: 1,805 rows of cleaned weekly sell-through, one row per SKU per week.
B17: Raw_Inventory_Monthly | C17: 480 rows of month-end on-hand / on-order snapshots.
B18: ABC_XYZ_Classification | C18: Revenue-based ABC tier x demand-variability XYZ tier for every SKU.
B19: Inventory_Planning_Model | C19: Safety stock, reorder point, EOQ, and stockout/overstock status — all live formulas.
B20: Forecast_Detail | C20: Week-by-week forecast-vs-actual for the 6-week holdout, 36 eligible SKUs.
B21: Forecast_MAPE_Summary | C21: Forecast accuracy (MAPE) by SKU, plus the catalog-wide average.
B22: Executive_Summary | C22: The one-page view: KPI cards, ABC/XYZ matrix, and the SKUs that matter most.
B24: Color key
B25: Blue text | C25: Hardcoded input or assumption
B26: Black text | C26: Formula (same sheet)
B27: Green text | C27: Formula linking to another sheet
B28: Red / Yellow / Green fill | C28: Stockout risk / Overstock / Healthy (Inventory_Planning_Model tab)

Sheet Assumptions
B2: Model Assumptions
B3: Every hardcoded number used in a formula elsewhere in this workbook is defined here, once.
B5: Name | C5: Value | D5: Cell | E5: Used for | F5: Rationale
B6: Service_Level_Z | C6: 1.65 | D6: C6 | E6: Safety stock | F6: Z-score for a 95% single-tail service level (industry-standard planning target).
B7: Order_Cost_S | C7: 75 | D7: C7 | E7: EOQ | F7: Assumed fixed cost per purchase order ($): PO processing + receiving labor.
B8: Holding_Cost_Rate | C8: 0.22 | D8: C8 | E8: EOQ | F8: Annual carrying cost as % of unit cost (typical industrial range: 18-30%).
B9: MOQ_Lot_Size | C9: 25 | D9: C9 | E9: Order rounding | F9: Assumed minimum order lot size (units) enforced via ROUNDUP across the catalog.
B10: Forecast_Holdout_Weeks | C10: 6 | D10: C10 | E10: MAPE test | F10: Most recent 6 weeks per SKU held out and forecast from the prior weeks to measure accuracy.
B11: Min_Weeks_For_Forecast | C11: 15 | D11: C11 | E11: MAPE eligibility | F11: SKUs with fewer weeks of history are excluded from statistical forecasting (too new/sparse).
B12: ABC_A_Cutoff | C12: 0.8 | D12: C12 | E12: ABC class | F12: SKUs contributing to the top 80% of cumulative revenue -> Class A.
B13: ABC_B_Cutoff | C13: 0.95 | D13: C13 | E13: ABC class | F13: Next slice, 80-95% cumulative revenue -> Class B. Remainder -> Class C.
B14: XYZ_X_Cutoff | C14: 0.3 | D14: C14 | E14: XYZ class | F14: Coefficient of variation <= 0.30 -> steady demand (X).
B15: XYZ_Y_Cutoff | C15: 0.55 | D15: C15 | E15: XYZ class | F15: CV 0.30-0.55 -> moderate variability (Y). Above 0.55 -> erratic (Z).
B16: Stockout_Multiple | C16: 1 | D16: C16 | E16: Inventory status | F16: Days of supply (incl. pipeline) < 1x lead time -> Stockout Risk.
B17: Overstock_Multiple | C17: 3 | D17: C17 | E17: Inventory status | F17: Days of supply (incl. pipeline) > 3x lead time -> Overstock.
B18: Weeks_Per_Year | C18: 52 | D18: C18 | E18: Annualization | F18: Used to annualize weekly demand into EOQ's D term.

Sheet Data_Quality_Log
B2: Data Quality Log — Raw NetSuite Export
B3: Issues found in the raw export and how each was resolved before building this workbook.
B5: Issue | C5: Where found | D5: Raw example | E5: Resolution
B6: Mixed date formats | C6: Sales export, Order_Date | D6: 01/18/2026, 2026-01-18, 18-Jan-2026, 01/18/26 | E6: Parsed all 4 formats to ISO dates in Python/SQL before loading; 0 unparseable after cleaning.
B7: Duplicate transaction rows | C7: Sales export | D7: 27 exact-duplicate rows (~1.5% of file) | E7: Dropped via SQL DISTINCT on SKU + date + qty + revenue + warehouse.
B8: UOM inconsistency | C8: SKU master & inventory snapshot | D8: EA / Each / each / ea. | PCS / pcs / Pcs | E8: Standardized to 4 canonical codes (EA, PCS, BOX, FT) via a lookup table.
B9: Supplier name casing | C9: SKU master | D9: Midwest Fastener Co. / MIDWEST FASTENER CO. / midwest fastener co. | E9: Standardized to title case.
B10: Missing On_Order_Qty | C10: Inventory snapshot | D10: 46 of 480 rows (9.6%) blank | E10: Treated as 0 (no open PO) with a flag column retained so the gap stays visible, not hidden.
B11: Sparse / new-SKU history | C11: Sales export | D11: 4 SKUs with <15 weeks of recorded sales | E11: Excluded from statistical forecasting (Forecast_MAPE_Summary); flagged for judgmental forecasting instead.

Sheet Raw_SKU_Master
A1: SKU_ID | B1: SKU_Description | C1: Category | D1: Supplier (cleaned) | E1: Unit_Cost | F1: Unit_Price | G1: UOM (raw) | H1: UOM (clean) | I1: Lead_Time_Days | J1: Warehouse
A2: MM-1000 | B2: Fasteners Item 01 - Fasteners & Hardware | C2: Fasteners & Hardware | D2: Midwest Fastener Co. | E2: 3.82 | F2: 6.94 | G2: PCS | H2: PCS | I2: 65 | J2: WH-OHIO
A3: MM-1001 | B3: Fasteners Item 02 - Fasteners & Hardware | C3: Fasteners & Hardware | D3: Midwest Fastener Co. | E3: 3.86 | F3: 6.59 | G3: EA | H3: EA | I3: 43 | J3: WH-NEVADA
A4: MM-1002 | B4: Fasteners Item 03 - Fasteners & Hardware | C4: Fasteners & Hardware | D4: Midwest Fastener Co. | E4: 2.83 | F4: 4.93 | G4: ea. | H4: EA | I4: 60 | J4: WH-NEVADA
A5: MM-1003 | B5: Fasteners Item 04 - Fasteners & Hardware | C5: Fasteners & Hardware | D5: Midwest Fastener Co. | E5: 2.56 | F5: 5.13 | G5: box | H5: BOX | I5: 52 | J5: WH-OHIO
A6: MM-1004 | B6: Fasteners Item 05 - Fasteners & Hardware | C6: Fasteners & Hardware | D6: Midwest Fastener Co. | E6: 3.55 | F6: 6.83 | G6: EA | H6: EA | I6: 49 | J6: WH-OHIO
A7: MM-1005 | B7: Bearings Item 01 - Bearings & Bushings | C7: Bearings & Bushings | D7: Precision Bearing Supply | E7: 3.02 | F7: 4.89 | G7: pcs | H7: PCS | I7: 95 | J7: WH-OHIO
A8: MM-1006 | B8: Bearings Item 02 - Bearings & Bushings | C8: Bearings & Bushings | D8: Precision Bearing Supply | E8: 3.9 | F8: 6.75 | G8: ea. | H8: EA | I8: 126 | J8: WH-TEXAS
A9: MM-1007 | B9: Bearings Item 03 - Bearings & Bushings | C9: Bearings & Bushings | D9: Precision Bearing Supply | E9: 3.36 | F9: 4.96 | G9: pcs | H9: PCS | I9: 128 | J9: WH-TEXAS
A10: MM-1008 | B10: Bearings Item 04 - Bearings & Bushings | C10: Bearings & Bushings | D10: Precision Bearing Supply | E10: 5.13 | F10: 7.78 | G10: pcs | H10: PCS | I10: 164 | J10: WH-OHIO
A11: MM-1009 | B11: Bearings Item 05 - Bearings & Bushings | C11: Bearings & Bushings | D11: Precision Bearing Supply | E11: 5.45 | F11: 8.96 | G11: each | H11: EA | I11: 141 | J11: WH-OHIO
A12: MM-1010 | B12: Electric Motors Item 01 - Electric Motors & Drives | C12: Electric Motors & Drives | D12: Torque Dynamics Llc | E12: 13.08 | F12: 27.85 | G12: ea. | H12: EA | I12: 32 | J12: WH-TEXAS
A13: MM-1011 | B13: Electric Motors Item 02 - Electric Motors & Drives | C13: Electric Motors & Drives | D13: Torque Dynamics Llc | E13: 15.22 | F13: 32.01 | G13: Each | H13: EA | I13: 52 | J13: WH-NEVADA
... A41: MM-1039 | B41: Packaging Materials Item 05 - Packaging Materials | C41: Packaging Materials | D41: Securepack Solutions | E41: 0.96 | F41: 2.38 | G41: Each | H41: EA | I41: 16 | J41: WH-NEVADA

Sheet Raw_Sales_Weekly
A1: SKU_ID | B1: Week_Ending | C1: Qty_Sold | D1: Revenue | E1: Week_Index
A2: MM-1000 | B2: 2025-07-13 | C2: 142 | D2: 961.93 | E2: 1
A3: MM-1000 | B3: 2025-07-20 | C3: 184 | D3: 1242.63 | E3: 2
A4: MM-1000 | B4: 2025-07-27 | C4: 159 | D4: 1076.92 | E4: 3
A5: MM-1000 | B5: 2025-08-03 | C5: 181 | D5: 1286.49 | E5: 4
A6: MM-1000 | B6: 2025-08-10 | C6: 96 | D6: 678.31 | E6: 5
A7: MM-1000 | B7: 2025-08-17 | C7: 157 | D7: 1098.89 | E7: 6
A8: MM-1000 | B8: 2025-08-24 | C8: 133 | D8: 902.78 | E8: 7
A9: MM-1000 | B9: 2025-08-31 | C9: 135 | D9: 937.7 | E9: 8
A10: MM-1000 | B10: 2025-09-07 | C10: 208 | D10: 1440.3 | E10: 9
A11: MM-1000 | B11: 2025-09-14 | C11: 132 | D11: 923.75 | E11: 10
A12: MM-1000 | B12: 2025-09-21 | C12: 152 | D12: 1032.08 | E12: 11
A13: MM-1000 | B13: 2025-09-28 | C13: 64 | D13: 441.95 | E13: 12
... A1806: MM-1039 | B1806: 2026-07-05 | C1806: 115 | D1806: 271.78 | E1806: 52

Sheet Raw_Inventory_Monthly
A1: SKU_ID | B1: Month | C1: On_Hand_Qty | D1: On_Order_Qty | E1: UOM | F1: Warehouse | G1: On_Order_Qty_Filled
A2: MM-1000 | B2: 2025-08 | C2: 331 | D2: 117 | E2: PCS | F2: WH-OHIO | G2: =IF(D2="",0,D2) -> 117
A3: MM-1000 | B3: 2025-09 | C3: 392 | D3: 118 | E3: pcs | F3: WH-OHIO | G3: =IF(D3="",0,D3) -> 118
A4: MM-1000 | B4: 2025-10 | C4: 324 | D4: 19 | E4: pcs | F4: WH-OHIO | G4: =IF(D4="",0,D4) -> 19
A5: MM-1000 | B5: 2025-11 | C5: 380 | D5: 75 | E5: pcs | F5: WH-OHIO | G5: =IF(D5="",0,D5) -> 75
A6: MM-1000 | B6: 2025-12 | C6: 499 | D6: 5 | E6: Pcs | F6: WH-OHIO | G6: =IF(D6="",0,D6) -> 5
A7: MM-1000 | B7: 2026-01 | C7: 471 | D7: 259 | E7: PCS | F7: WH-OHIO | G7: =IF(D7="",0,D7) -> 259
A8: MM-1000 | B8: 2026-02 | C8: 404 | D8: 150 | E8: Pcs | F8: WH-OHIO | G8: =IF(D8="",0,D8) -> 150
A9: MM-1000 | B9: 2026-03 | C9: 595 | D9: 242 | E9: PCS | F9: WH-OHIO | G9: =IF(D9="",0,D9) -> 242
A10: MM-1000 | B10: 2026-04 | C10: 516 | D10: 247 | E10: Pcs | F10: WH-OHIO | G10: =IF(D10="",0,D10) -> 247
A11: MM-1000 | B11: 2026-05 | C11: 351 | D11: 19 | E11: Pcs | F11: WH-OHIO | G11: =IF(D11="",0,D11) -> 19
A12: MM-1000 | B12: 2026-06 | C12: 0 | D12: 149 | E12: pcs | F12: WH-OHIO | G12: =IF(D12="",0,D12) -> 149
A13: MM-1000 | B13: 2026-07 | C13: 400 | D13: 32 | E13: PCS | F13: WH-OHIO | G13: =IF(D13="",0,D13) -> 32
... A15: MM-1001 | B15: 2025-09 | C15: 0 | D15: 240 | E15: ea. | F15: WH-NEVADA | G15: =IF(D15="",0,D15) -> 240
A16: MM-1001 | B16: 2025-10 | C16: 0 | E16: ea. | F16: WH-NEVADA | G16: =IF(D16="",0,D16) -> 0
A17: MM-1001 | B17: 2025-11 | C17: 334 | D17: 115 | E17: EA | F17: WH-NEVADA | G17: =IF(D17="",0,D17) -> 115
A18: MM-1001 | B18: 2025-12 | C18: 0 | D18: 60 | E18: Each | F18: WH-NEVADA | G18: =IF(D18="",0,D18) -> 60
A19: MM-1001 | B19: 2026-01 | C19: 302 | D19: 220 | E19: Each | F19: WH-NEVADA | G19: =IF(D19="",0,D19) -> 220
A20: MM-1001 | B20: 2026-02 | C20: 0 | D20: 49 | E20: EA | F20: WH-NEVADA | G20: =IF(D20="",0,D20) -> 49
A21: MM-1001 | B21: 2026-03 | C21: 0 | D21: 194 | E21: ea. | F21: WH-NEVADA | G21: =IF(D21="",0,D21) -> 194
A22: MM-1001 | B22: 2026-04 | C22: 347 | D22: 11 | E22: EA | F22: WH-NEVADA | G22: =IF(D22="",0,D22) -> 11
A23: MM-1001 | B23: 2026-05 | C23: 473 | E23: each | F23: WH-NEVADA | G23: =IF(D23="",0,D23) -> 0
A24: MM-1001 | B24: 2026-06 | C24: 496 | D24: 211 | E24: EA | F24: WH-NEVADA | G24: =IF(D24="",0,D24) -> 211
A25: MM-1001 | B25: 2026-07 | C25: 486 | D25: 164 | E25: each | F25: WH-NEVADA | G25: =IF(D25="",0,D25) -> 164
A26: MM-1002 | B26: 2025-08 | C26: 384 | D26: 200 | E26: each | F26: WH-NEVADA | G26: =IF(D26="",0,D26) -> 200
A27: MM-1002 | B27: 2025-09 | C27: 426 | D27: 133 | E27: EA | F27: WH-NEVADA | G27: =IF(D27="",0,D27) -> 133
A28: MM-1002 | B28: 2025-10 | C28: 0 | E28: ea. | F28: WH-NEVADA | G28: =IF(D28="",0,D28) -> 0
A29: MM-1002 | B29: 2025-11 | C29: 687 | D29: 240 | E29: each | F29: WH-NEVADA | G29: =IF(D29="",0,D29) -> 240
A30: MM-1002 | B30: 2025-12 | C30: 642 | D30: 128 | E30: ea. | F30: WH-NEVADA | G30: =IF(D30="",0,D30) -> 128
A31: MM-1002 | B31: 2026-01 | C31: 641 | D31: 189 | E31: each | F31: WH-NEVADA | G31: =IF(D31="",0,D31) -> 189
A32: MM-1002 | B32: 2026-02 | C32: 638 | D32: 53 | E32: ea. | F32: WH-NEVADA | G32: =IF(D32="",0,D32) -> 53
A33: MM-1002 | B33: 2026-03 | C33: 0 | D33: 214 | E33: ea. | F33: WH-NEVADA | G33: =IF(D33="",0,D33) -> 214
A34: MM-1002 | B34: 2026-04 | C34: 380 | D34: 154 | E34: Each | F34: WH-NEVADA | G34: =IF(D34="",0,D34) -> 154
A35: MM-1002 | B35: 2026-05 | C35: 667 | D35: 227 | E35: ea. | F35: WH-NEVADA | G35: =IF(D35="",0,D35) -> 227
A36: MM-1002 | B36: 2026-06 | C36: 573 | E36: EA | F36: WH-NEVADA | G36: =IF(D36="",0,D36) -> 0
A37: MM-1002 | B37: 2026-07 | C37: 0 | E37: ea. | F37: WH-NEVADA | G37: =IF(D37="",0,D37) -> 0
A38: MM-1003 | B38: 2025-08 | C38: 1841 | D38: 162 | E38: each | F38: WH-OHIO | G38: =IF(D38="",0,D38) -> 162
A39: MM-1003 | B39: 2025-09 | C39: 1872 | D39: 303 | E39: Each | F39: WH-OHIO | G39: =IF(D39="",0,D39) -> 303
A40: MM-1003 | B40: 2025-10 | C40: 0 | D40: 168 | E40: Each | F40: WH-OHIO | G40: =IF(D40="",0,D40) -> 168
A41: MM-1003 | B41: 2025-11 | C41: 2406 | D41: 158 | E41: ea. | F41: WH-OHIO | G41: =IF(D41="",0,D41) -> 158
A42: MM-1003 | B42: 2025-12 | C42: 2269 | E42: ea. | F42: WH-OHIO | G42: =IF(D42="",0,D42) -> 0
A43: MM-1003 | B43: 2026-01 | C43: 2400 | D43: 260 | E43: ea. | F43: WH-OHIO | G43: =IF(D43="",0,D43) -> 260
A44: MM-1003 | B44: 2026-02 | C44: 1962 | D44: 18 | E44: Each | F44: WH-OHIO | G44: =IF(D44="",0,D44) -> 18
A45: MM-1003 | B45: 2026-03 | C45: 1962 | E45: EA | F45: WH-OHIO | G45: =IF(D45="",0,D45) -> 0
A46: MM-1003 | B46: 2026-04 | C46: 2384 | D46: 286 | E46: each | F46: WH-OHIO | G46: =IF(D46="",0,D46) -> 286
A47: MM-1003 | B47: 2026-05 | C47: 1874 | D47: 21 | E47: Each | F47: WH-OHIO | G47: =IF(D47="",0,D47) -> 21
A48: MM-1003 | B48: 2026-06 | C48: 1917 | D48: 39 | E48: EA | F48: WH-OHIO | G48: =IF(D48="",0,D48) -> 39
A49: MM-1003 | B49: 2026-07 | C49: 1982 | D49: 222 | E49: Each | F49: WH-OHIO | G49: =IF(D49="",0,D49) -> 222
A50: MM-1004 | B50: 2025-08 | C50: 768 | D50: 65 | E50: ea. | F50: WH-OHIO | G50: =IF(D50="",0,D50) -> 65
A51: MM-1004 | B51: 2025-09 | C51: 0 | D51: 18 | E51: Each | F51: WH-OHIO | G51: =IF(D51="",0,D51) -> 18
A52: MM-1004 | B52: 2025-10 | C52: 965 | D52: 172 | E52: ea. | F52: WH-OHIO | G52: =IF(D52="",0,D52) -> 172
A53: MM-1004 | B53: 2025-11 | C53: 642 | D53: 233 | E53: ea. | F53: WH-OHIO | G53: =IF(D53="",0,D53) -> 233
A54: MM-1004 | B54: 2025-12 | C54: 585 | D54: 208 | E54: ea. | F54: WH-OHIO | G54: =IF(D54="",0,D54) -> 208
A55: MM-1004 | B55: 2026-01 | C55: 728 | D55: 42 | E55: Each | F55: WH-OHIO | G55: =IF(D55="",0,D55) -> 42
A56: MM-1004 | B56: 2026-02 | C56: 800 | D56: 256 | E56: each | F56: WH-OHIO | G56: =IF(D56="",0,D56) -> 256
A57: MM-1004 | B57: 2026-03 | C57: 939 | E57: ea. | F57: WH-OHIO | G57: =IF(D57="",0,D57) -> 0
A58: MM-1004 | B58: 2026-04 | C58: 634 | D58: 297 | E58: each | F58: WH-OHIO | G58: =IF(D58="",0,D58) -> 297
A59: MM-1004 | B59: 2026-05 | C59: 669 | D59: 254 | E59: EA | F59: WH-OHIO | G59: =IF(D59="",0,D59) -> 254
A60: MM-1004 | B60: 2026-06 | C60: 877 | D60: 231 | E60: each | F60: WH-OHIO | G60: =IF(D60="",0,D60) -> 231
A61: MM-1004 | B61: 2026-07 | C61: 731 | D61: 267 | E61: Each | F61: WH-OHIO | G61: =IF(D61="",0,D61) -> 267
A62: MM-1005 | B62: 2025-08 | C62: 356 | E62: EA | F62: WH-OHIO | G62: =IF(D62="",0,D62) -> 0
A63: MM-1005 | B63: 2025-09 | C63: 304 | D63: 131 | E63: Each | F63: WH-OHIO | G63: =IF(D63="",0,D63) -> 131
A64: MM-1005 | B64: 2025-10 | C64: 247 | D64: 7 | E64: Each | F64: WH-OHIO | G64: =IF(D64="",0,D64) -> 7
A65: MM-1005 | B65: 2025-11 | C65: 245 | D65: 111 | E65: ea. | F65: WH-OHIO | G65: =IF(D65="",0,D65) -> 111
A66: MM-1005 | B66: 2025-12 | C66: 0 | E66: each | F66: WH-OHIO | G66: =IF(D66="",0,D66) -> 0
A67: MM-1005 | B67: 2026-01 | C67: 274 | D67: 88 | E67: EA | F67: WH-OHIO | G67: =IF(D67="",0,D67) -> 88
A68: MM-1005 | B68: 2026-02 | C68: 287 | D68: 20 | E68: EA | F68: WH-OHIO | G68: =IF(D68="",0,D68) -> 20
A69: MM-1005 | B69: 2026-03 | C69: 222 | D69: 129 | E69: ea. | F69: WH-OHIO | G69: =IF(D69="",0,D69) -> 129
A70: MM-1005 | B70: 2026-04 | C70: 324 | D70: 118 | E70: ea. | F70: WH-OHIO | G70: =IF(D70="",0,D70) -> 118
A71: MM-1005 | B71: 2026-05 | C71: 272 | D71: 6 | E71: Each | F71: WH-OHIO | G71: =IF(D71="",0,D71) -> 6
A72: MM-1005 | B72: 2026-06 | C72: 386 | D72: 65 | E72: Each | F72: WH-OHIO | G72: =IF(D72="",0,D72) -> 65
A73: MM-1005 | B73: 2026-07 | C73: 308 | D73: 3 | E73: EA | F73: WH-OHIO | G73: =IF(D73="",0,D73) -> 3
A74: MM-1006 | B74: 2025-08 | C74: 866 | D74: 107 | E74: ea. | F74: WH-TEXAS | G74: =IF(D74="",0,D74) -> 107
A75: MM-1006 | B75: 2025-09 | C75: 830 | E75: each | F75: WH-TEXAS | G75: =IF(D75="",0,D75) -> 0
A76: MM-1006 | B76: 2025-10 | C76: 750 | D76: 311 | E76: ea. | F76: WH-TEXAS | G76: =IF(D76="",0,D76) -> 311
A77: MM-1006 | B77: 2025-11 | C77: 625 | D77: 212 | E77: ea. | F77: WH-TEXAS | G77: =IF(D77="",0,D77) -> 212
A78: MM-1006 | B78: 2025-12 | C78: 983 | D78: 208 | E78: ea. | F78: WH-TEXAS | G78: =IF(D78="",0,D78) -> 208
A79: MM-1006 | B79: 2026-01 | C79: 0 | D79: 210 | E79: Each | F79: WH-TEXAS | G79: =IF(D79="",0,D79) -> 210
A80: MM-1006 | B80: 2026-02 | C80: 946 | D80: 147 | E80: each | F80: WH-TEXAS | G80: =IF(D80="",0,D80) -> 147
A81: MM-1006 | B81: 2026-03 | C81: 928 | D81: 278 | E81: each | F81: WH-TEXAS | G81: =IF(D81="",0,D81) -> 278
A82: MM-1006 | B82: 2026-04 | C82: 606 | D82: 171 | E82: Each | F82: WH-TEXAS | G82: =IF(D82="",0,D82) -> 171
A83: MM-1006 | B83: 2026-05 | C83: 956 | D83: 34 | E83: EA | F83: WH-TEXAS | G83: =IF(D83="",0,D83) -> 34
A84: MM-1006 | B84: 2026-06 | C84: 780 | D84: 275 | E84: Each | F84: WH-TEXAS | G84: =IF(D84="",0,D84) -> 275
A85: MM-1006 | B85: 2026-07 | C85: 562 | D85: 199 | E85: ea. | F85: WH-TEXAS | G85: =IF(D85="",0,D85) -> 199
A86: MM-1007 | B86: 2025-08 | C86: 206 | D86: 138 | E86: Each | F86: WH-TEXAS | G86: =IF(D86="",0,D86) -> 138
A87: MM-1007 | B87: 2025-09 | C87: 0 | D87: 94 | E87: ea. | F87: WH-TEXAS | G87: =IF(D87="",0,D87) -> 94
... A93: MM-1007 | B93: 2026-03 | C93: 164 | D93: 158 | E93: each | F93: WH-TEXAS | G93: =IF(D93="",0,D93) -> 158
A94: MM-1007 | B94: 2026-04 | C94: 159 | E94: EA | F94: WH-TEXAS | G94: =IF(D94="",0,D94) -> 0
A95: MM-1007 | B95: 2026-05 | C95: 217 | D95: 50 | E95: each | F95: WH-TEXAS | G95: =IF(D95="",0,D95) -> 50
A96: MM-1007 | B96: 2026-06 | C96: 0 | D96: 52 | E96: ea. | F96: WH-TEXAS | G96: =IF(D96="",0,D96) -> 52
A97: MM-1007 | B97: 2026-07 | C97: 0 | D97: 0 | E97: Each | F97: WH-TEXAS | G97: =IF(D97="",0,D97) -> 0
A98: MM-1008 | B98: 2025-08 | C98: 462 | D98: 5 | E98: each | F98: WH-OHIO | G98: =IF(D98="",0,D98) -> 5
A99: MM-1008 | B99: 2025-09 | C99: 515 | D99: 51 | E99: ea. | F99: WH-OHIO | G99: =IF(D99="",0,D99) -> 51
A100: MM-1008 | B100: 2025-10 | C100: 436 | D100: 7 | E100: ea. | F100: WH-OHIO | G100: =IF(D100="",0,D100) -> 7
A101: MM-1008 | B101: 2025-11 | C101: 416 | D101: 164 | E101: ea. | F101: WH-OHIO | G101: =IF(D101="",0,D101) -> 164
A102: MM-1008 | B102: 2025-12 | C102: 481 | D102: 154 | E102: EA | F102: WH-OHIO | G102: =IF(D102="",0,D102) -> 154
A103: MM-1008 | B103: 2026-01 | C103: 0 | D103: 14 | E103: each | F103: WH-OHIO | G103: =IF(D103="",0,D103) -> 14
A104: MM-1008 | B104: 2026-02 | C104: 482 | D104: 126 | E104: each | F104: WH-OHIO | G104: =IF(D104="",0,D104) -> 126
A105: MM-1008 | B105: 2026-03 | C105: 399 | D105: 121 | E105: EA | F105: WH-OHIO | G105: =IF(D105="",0,D105) -> 121
A106: MM-1008 | B106: 2026-04 | C106: 397 | D106: 38 | E106: ea. | F106: WH-OHIO | G106: =IF(D106="",0,D106) -> 38
...

Sheet ABC_XYZ_Classification
B2: ABC (Revenue) x XYZ (Demand Variability) Classification
B3: Sorted by revenue, descending. Every value is a live formula against Raw_Sales_Weekly / Raw_SKU_Master.
A5: SKU_ID | B5: SKU_Description | C5: Category | D5: Total_Revenue | E5: Total_Qty_Sold | F5: Cum_Revenue | G5: Cum_Pct | H5: ABC_Class | I5: Mean_Weekly_Qty | J5: StDev_Weekly_Qty | K5: CV | L5: XYZ_Class | M5: ABC_XYZ
A6: MM-1033 | B6: =INDEX(Raw_SKU_Master!$B$2:$B$41,MATCH(A6,Raw_SKU_Master!$A$2:$A$41,0)) -> Raw Material Item 04 - Raw Material - Metal Stock | C6: =INDEX(Raw_SKU_Master!$C$2:$C$41,MATCH(A6,Raw_SKU_Master!$A$2:$A$41,0)) -> Raw Material - Metal Stock | D6: =SUMIF(Raw_Sales_Weekly!$A$2:$A$1806,A6,Raw_Sales_Weekly!$D$2:$D$1806) -> 544456.12 | E6: =SUMIF(Raw_Sales_Weekly!$A$2:$A$1806,A6,Raw_Sales_Weekly!$C$2:$C$1806) -> 10524 | F6: =SUM($D$6:D6) -> 544456.12 | G6: =F6/SUM($D$6:$D$45) -> 0.17212532 | H6: =IF(G6<=Assumptions!$C$12,"A",IF(G6<=Assumptions!$C$13,"B","C")) -> A | I6: =AVERAGEIF(Raw_Sales_Weekly!$A$2:$A$1806,A6,Raw_Sales_Weekly!$C$2:$C$1806) -> 210.48 | J6: =SQRT(SUMPRODUCT((Raw_Sales_Weekly!$A$2:$A$1806=A6)*(Raw_Sales_Weekly!$C$2:$C$1806-I6)^2)/COUNTIF(Raw_Sales_Weekly!$A$2:$A$1806,A6)) -> 121.64214 | K6: =IFERROR(J6/I6,0) -> 0.5779273 | L6: =IF(K6<=Assumptions!$C$14,"X",IF(K6<=Assumptions!$C$15,"Y","Z")) -> Z | M6: =H6&L6 -> AZ
A7: MM-1032 | B7: =INDEX(Raw_SKU_Master!$B$2:$B$41,MATCH(A7,Raw_SKU_Master!$A$2:$A$41,0)) -> Raw Material Item 03 - Raw Material - Metal Stock | C7: =INDEX(Raw_SKU_Master!$C$2:$C$41,MATCH(A7,Raw_SKU_Master!$A$2:$A$41,0)) -> Raw Material - Metal Stock | D7: =SUMIF(Raw_Sales_Weekly!$A$2:$A$1806,A7,Raw_Sales_Weekly!$D$2:$D$1806) -> 303904.71 | E7: =SUMIF(Raw_Sales_Weekly!$A$2:$A$1806,A7,Raw_Sales_Weekly!$C$2:$C$1806) -> 8252 | F7: =SUM($D$6:D7) -> 848360.83 | G7: =F7/SUM($D$6:$D$45) -> 0.26820229 | H7: =IF(G7<=Assumptions!$C$12,"A",IF(G7<=Assumptions!$C$13,"B","C")) -> A | I7: =AVERAGEIF(Raw_Sales_Weekly!$A$2:$A$1806,A7,Raw_Sales_Weekly!$C$2:$C$1806) -> 161.80392 | J7: =SQRT(SUMPRODUCT((Raw_Sales_Weekly!$A$2:$A$1806=A7)*(Raw_Sales_Weekly!$C$2:$C$1806-I7)^2)/COUNTIF(Raw_Sales_Weekly!$A$2:$A$1806,A7)) -> 93.090093 | K7: =IFERROR(J7/I7,0) -> 0.57532656 | L7: =IF(K7<=Assumptions!$C$14,"X",IF(K7<=Assumptions!$C$15,"Y","Z")) -> Z | M7: =H7&L7 -> AZ
A8: MM-1025 | B8: =INDEX(Raw_SKU_Master!$B$2:$B$41,MATCH(A8,Raw_SKU_Master!$A$2:$A$41,0)) -> Pneumatic Components Item 01 - Pneumatic Components | C8: =INDEX(Raw_SKU_Master!$C$2:$C$41,MATCH(A8,Raw_SKU_Master!$A$2:$A$41,0)) -> Pneumatic Components | D8: =SUMIF(Raw_Sales_Weekly!$A$2:$A$1806,A8,Raw_Sales_Weekly!$D$2:$D$1806) -> 239857.28 | E8: =SUMIF(Raw_Sales_Weekly!$A$2:$A$1806,A8,Raw_Sales_Weekly!$C$2:$C$1806) -> 8260 | F8: =SUM($D$6:D8) -> 1088218.1 | G8: =F8/SUM($D$6:$D$45) -> 0.3440312 | H8: =IF(G8<=Assumptions!$C$12,"A",IF(G8<=Assumptions!$C$13,"B","C")) -> A | I8: =AVERAGEIF(Raw_Sales_Weekly!$A$2:$A$1806,A8,Raw_Sales_Weekly!$C$2:$C$1806) -> 165.2 | J8: =SQRT(SUMPRODUCT((Raw_Sales_Weekly!$A$2:$A$1806=A8)*(Raw_Sales_Weekly!$C$2:$C$1806-I8)^2)/COUNTIF(Raw_Sales_Weekly!$A$2:$A$1806,A8)) -> 80.431089 | K8: =IFERROR(J8/I8,0) -> 0.486871 | L8: =IF(K8<=Assumptions!$C$14,"X",IF(K8<=Assumptions!$C$15,"Y","Z")) -> Y | M8: =H8&L8 -> AY
A9: MM-1030 | B9: =INDEX(Raw_SKU_Master!$B$2:$B$41,MATCH(A9,Raw_SKU_Master!$A$2:$A$41,0)) -> Raw Material Item 01 - Raw Material - Metal Stock | C9: =INDEX(Raw_SKU_Master!$C$2:$C$41,MATCH(A9,Raw_SKU_Master!$A$2:$A$41,0)) -> Raw Material - Metal Stock | D9: =SUMIF(Raw_Sales_Weekly!$A$2:$A$1806,A9,Raw_Sales_Weekly!$D$2:$D$1806) -> 187809.68 | E9: =SUMIF(Raw_Sales_Weekly!$A$2:$A$1806,A9,Raw_Sales_Weekly!$C$2:$C$1806) -> 4081 | F9: =SUM($D$6:D9) -> 1276027.8 | G9: =F9/SUM($D$6:$D$45) -> 0.40340568 | H9: =IF(G9<=Assumptions!$C$12,"A",IF(G9<=Assumptions!$C$13,"B","C")) -> A | I9: =AVERAGEIF(Raw_Sales_Weekly!$A$2:$A$1806,A9,Raw_Sales_Weekly!$C$2:$C$1806) -> 80.019608 | J9: =SQRT(SUMPRODUCT((Raw_Sales_Weekly!$A$2:$A$1806=A9)*(Raw_Sales_Weekly!$C$2:$C$1806-I9)^2)/COUNTIF(Raw_Sales_Weekly!$A$2:$A$1806,A9)) -> 50.206823 | K9: =IFERROR(J9/I9,0) -> 0.62743151 | L9: =IF(K9<=Assumptions!$C$14,"X",IF(K9<=Assumptions!$C$15,"Y","Z")) -> Z | M9: =H9&L9 -> AZ
A10: MM-1014 | B10: =INDEX(Raw_SKU_Master!$B$2:$B$41,MATCH(A10,Raw_SKU_Master!$A$2:$A$41,0)) -> Electric Motors Item 05 - Electric Motors & Drives | C10: =INDEX(Raw_SKU_Master!$C$2:$C$41,MATCH(A10,Raw_SKU_Master!$A$2:$A$41,0)) -> Electric Motors & Drives | D10: =SUMIF(Raw_Sales_Weekly!$A$2:$A$1806,A10,Raw_Sales_Weekly!$D$2:$D$1806) -> 156097.75 | E10: =SUMIF(Raw_Sales_Weekly!$A$2:$A$1806,A10,Raw_Sales_Weekly!$C$2:$C$1806) -> 3722 | F10: =SUM($D$6:D10) -> 1432125.5 | G10: =F10/SUM($D$6:$D$45) -> 0.4527547 | H10: =IF(G10<=Assumptions!$C$12,"A",IF(G10<=Assumptions!$C$13,"B","C")) -> A | I10: =AVERAGEIF(Raw_Sales_Weekly!$A$2:$A$1806,A10,Raw_Sales_Weekly!$C$2:$C$1806) -> 71.576923 | J10: =SQRT(SUMPRODUCT((Raw_Sales_Weekly!$A$2:$A$1806=A10)*(Raw_Sales_Weekly!$C$2:$C$1806-I10)^2)/COUNTIF(Raw_Sales_Weekly!$A$2:$A$1806,A10)) -> 10.508872 | K10: =IFERROR(J10/I10,0) -> 0.14681928 | L10: =IF(K10<=Assumptions!$C$14,"X",IF(K10<=Assumptions!$C$15,"Y","Z")) -> X | M10: =H10&L10 -> AX
A11: MM-1010 | B11: =INDEX(Raw_SKU_Master!$B$2:$B$41,MATCH(A11,Raw_SKU_Master!$A$2:$A$41,0)) -> Electric Motors Item 01 - Electric Motors & Drives | C11: =INDEX(Raw_SKU_Master!$C$2:$C$41,MATCH(A11,Raw_SKU_Master!$A$2:$A$41,0)) -> Electric Motors & Drives | D11: =SUMIF(Raw_Sales_Weekly!$A$2:$A$1806,A11,Raw_Sales_Weekly!$D$2:$D$1806) -> 142199.48 | E11: =SUMIF(Raw_Sales_Weekly!$A$2:$A$1806,A11,Raw_Sales_Weekly!$C$2:$C$1806) -> 5128 | F11: =SUM($D$6:D11) -> 1574325 | G11: =F11/SUM($D$6:$D$45) -> 0.4977099 | H11: =IF(G11<=Assumptions!$C$12,"A",IF(G11<=Assumptions!$C$13,"B","C")) -> A | I11: =AVERAGEIF(Raw_Sales_Weekly!$A$2:$A$1806,A11,Raw_Sales_Weekly!$C$2:$C$1806) -> 98.615385 | J11: =SQRT(SUMPRODUCT((Raw_Sales_Weekly!$A$2:$A$1806=A11)*(Raw_Sales_Weekly!$C$2:$C$1806-I11)^2)/COUNTIF(Raw_Sales_Weekly!$A$2:$A$1806,A11)) -> 13.147322 | K11: =IFERROR(J11/I11,0) -> 0.13331918 | L11: =IF(K11<=Assumptions!$C$14,"X",IF(K11<=Assumptions!$C$15,"Y","Z")) -> X | M11: =H11&L11 -> AX
A12: MM-1011 | B12: =INDEX(Raw_SKU_Master!$B$2:$B$41,MATCH(A12,Raw_SKU_Master!$A$2:$A$41,0)) -> Electric Motors Item 02 - Electric Motors & Drives | C12: =INDEX(Raw_SKU_Master!$C$2:$C$41,MATCH(A12,Raw_SKU_Master!$A$2:$A$41,0)) -> Electric Motors & Drives | D12: =SUMIF(Raw_Sales_Weekly!$A$2:$A$1806,A12,Raw_Sales_Weekly!$D$2:$D$1806) -> 140581.06 | E12: =SUMIF(Raw_Sales_Weekly!$A$2:$A$1806,A12,Raw_Sales_Weekly!$C$2:$C$1806) -> 4406 | F12: =SUM($D$6:D12) -> 1714906.1 | G12: =F12/SUM($D$6:$D$45) -> 0.54215344 | H12: =IF(G12<=Assumptions!$C$12,"A",IF(G12<=Assumptions!$C$13,"B","C")) -> A | I12: =AVERAGEIF(Raw_Sales_Weekly!$A$2:$A$1806,A12,Raw_Sales_Weekly!$C$2:$C$1806) -> 209.80952 | J12: =SQRT(SUMPRODUCT((Raw_Sales_Weekly!$A$2:$A$1806=A12)*(Raw_Sales_Weekly!$C$2:$C$1806-I12)^2)/COUNTIF(Raw_Sales_Weekly!$A$2:$A$1806,A12)) -> 30.562378 | K12: =IFERROR(J12/I12,0) -> 0.14566726 | L12: =IF(K12<=Assumptions!$C$14,"X",IF(K12<=Assumptions!$C$15,"Y","Z")) -> X | M12: =H12&L12 -> AX
A13: MM-1013 | B13: =INDEX(Raw_SKU_Master!$B$2:$B$41,MATCH(A13,Raw_SKU_Master!$A$2:$A$41,0)) -> Electric Motors Item 04 - Electric Motors & Drives | C13: =INDEX(Raw_SKU_Master!$C$2:$C$41,MATCH(A13,Raw_SKU_Master!$A$2:$A$41,0)) -> Electric Motors & Drives | D13: =SUMIF(Raw_Sales_Weekly!$A$2:$A$1806,A13,Raw_Sales_Weekly!$D$2:$D$1806) -> 140269.93 | E13: =SUMIF(Raw_Sales_Weekly!$A$2:$A$1806,A13,Raw_Sales_Weekly!$C$2:$C$1806) -> 5749 | F13: =SUM($D$6:D13) -> 1855176 | G13: =F13/SUM($D$6:$D$45) -> 0.58649863 | H13: =IF(G13<=Assumptions!$C$12,"A",IF(G13<=Assumptions!$C$13,"B","C")) -> A | I13: =AVERAGEIF(Raw_Sales_Weekly!$A$2:$A$1806,A13,Raw_Sales_Weekly!$C$2:$C$1806) -> 110.55769 | J13: =SQRT(SUMPRODUCT((Raw_Sales_Weekly!$A$2:$A$1806=A13)*(Raw_Sales_Weekly!$C$2:$C$1806-I13)^2)/COUNTIF(Raw_Sales_Weekly!$A$2:$A$1806,A13)) -> 15.501133 | K13: =IFERROR(J13/I13,0) -> 0.14020855 | L13: =IF(K13<=Assumptions!$C$14,"X",IF(K13<=Assumptions!$C$15,"Y","Z")) -> X | M13: =H13&L13 -> AX
A14: MM-1015 | B14: =INDEX(Raw_SKU_Master!$B$2:$B$41,MATCH(A14,Raw_SKU_Master!$A$2:$A$41,0)) -> Sensors Item 01 - Sensors & Controls | C14: =INDEX(Raw_SKU_Master!$C$2:$C$41,MATCH(A14,Raw_SKU_Master!$A$2:$A$41,0)) -> Sensors & Controls | D14: =SUMIF(Raw_Sales_Weekly!$A$2:$A$1806,A14,Raw_Sales_Weekly!$D$2:$D$1806) -> 108623.95 | E14: =SUMIF(Raw_Sales_Weekly!$A$2:$A$1806,A14,Raw_Sales_Weekly!$C$2:$C$1806) -> 9605 | F14: =SUM($D$6:D14) -> 1963800 | G14: =F14/SUM($D$6:$D$45) -> 0.6208392 | H14: =IF(G14<=Assumptions!$C$12,"A",IF(G14<=Assumptions!$C$13,"B","C")) -> A | I14: =AVERAGEIF(Raw_Sales_Weekly!$A$2:$A$1806,A14,Raw_Sales_Weekly!$C$2:$C$1806) -> 184.71154 | J14: =SQRT(SUMPRODUCT((Raw_Sales_Weekly!$A$2:$A$1806=A14)*(Raw_Sales_Weekly!$C$2:$C$1806-I14)^2)/COUNTIF(Raw_Sales_Weekly!$A$2:$A$1806,A14)) -> 110.24297 | K14: =IFERROR(J14/I14,0) -> 0.59683858 | L14: =IF(K14<=Assumptions!$C$14,"X",IF(K14<=Assumptions!$C$15,"Y","Z")) -> Z | M14: =H14&L14 -> AZ
A15: MM-1019 | B15: =INDEX(Raw_SKU_Master!$B$2:$B$41,MATCH(A15,Raw_SKU_Master!$A$2:$A$41,0)) -> Sensors Item 05 - Sensors & Controls | C15: =INDEX(Raw_SKU_Master!$C$2:$C$41,MATCH(A15,Raw_SKU_Master!$A$2:$A$41,0)) -> Sensors & Controls | D15: =SUMIF(Raw_Sales_Weekly!$A$2:$A$1806,A15,Raw_Sales_Weekly!$D$2:$D$1806) -> 107028.35 | E15: =SUMIF(Raw_Sales_Weekly!$A$2:$A$1806,A15,Raw_Sales_Weekly!$C$2:$C$1806) -> 11884 | F15: =SUM($D$6:D15) -> 2070828.3 | G15: =F15/SUM($D$6:$D$45) -> 0.65467533 | H15: =IF(G15<=Assumptions!$C$12,"A",IF(G15<=Assumptions!$C$13,"B","C")) -> A | I15: =AVERAGEIF(Raw_Sales_Weekly!$A$2:$A$1806,A15,Raw_Sales_Weekly!$C$2:$C$1806) -> 228.53846 | J15: =SQRT(SUMPRODUCT((Raw_Sales_Weekly!$A$2:$A$1806=A15)*(Raw_Sales_Weekly!$C$2:$C$1806-I15)^2)/COUNTIF(Raw_Sales_Weekly!$A$2:$A$1806,A15)) -> 72.072736 | K15: =IFERROR(J15/I15,0) -> 0.31536371 | L15: =IF(K15<=Assumptions!$C$14,"X",IF(K15<=Assumptions!$C$15,"Y","Z")) -> Y | M15: =H15&L15 -> AY
A16: MM-1034 | B16: =INDEX(Raw_SKU_Master!$B$2:$B$41,MATCH(A16,Raw_SKU_Master!$A$2:$A$41,0)) -> Raw Material Item 05 - Raw Material - Metal Stock | C16: =INDEX(Raw_SKU_Master!$C$2:$C$41,MATCH(A16,Raw_SKU_Master!$A$2:$A$41,0)) -> Raw Material - Metal Stock | D16: =SUMIF(Raw_Sales_Weekly!$A$2:$A$1806,A16,Raw_Sales_Weekly!$D$2:$D$1806) -> 99301.07 | E16: =SUMIF(Raw_Sales_Weekly!$A$2:$A$1806,A16,Raw_Sales_Weekly!$C$2:$C$1806) -> 2368 | F16: =SUM($D$6:D16) -> 2170129.4 | G16: =F16/SUM($D$6:$D$45) -> 0.68606854 | H16: =IF(G16<=Assumptions!$C$12,"A",IF(G16<=Assumptions!$C$13,"B","C")) -> A | I16: =AVERAGEIF(Raw_Sales_Weekly!$A$2:$A$1806,A16,Raw_Sales_Weekly!$C$2:$C$1806) -> 45.538462 | J16: =SQRT(SUMPRODUCT((Raw_Sales_Weekly!$A$2:$A$1806=A16)*(Raw_Sales_Weekly!$C$2:$C$1806-I16)^2)/COUNTIF(Raw_Sales_Weekly!$A$2:$A$1806,A16)) -> 6.3198757 | K16: =IFERROR(J16/I16,0) -> 0.13878105 | L16: =IF(K16<=Assumptions!$C$14,"X",IF(K16<=Assumptions!$C$15,"Y","Z")) -> X | M16: =H16&L16 -> AX
A17: MM-1018 | B17: =INDEX(Raw_SKU_Master!$B$2:$B$41,MATCH(A17,Raw_SKU_Master!$A$2:$A$41,0)) -> Sensors Item 04 - Sensors & Controls | C17: =INDEX(Raw_SKU_Master!$C$2:$C$41,MATCH(A17,Raw_SKU_Master!$A$2:$A$41,0)) -> Sensors & Controls | D17: =SUMIF(Raw_Sales_Weekly!$A$2:$A$1806,A17,Raw_Sales_Weekly!$D$2:$D$1806) -> 91339.24 | E17: =SUMIF(Raw_Sales_Weekly!$A$2:$A$1806,A17,Raw_Sales_Weekly!$C$2:$C$1806) -> 9392 | F17: =SUM($D$6:D17) -> 2261468.6 | G17: =F17/SUM($D$6:$D$45) -> 0.71494469 | H17: =IF(G17<=Assumptions!$C$12,"A",IF(G17<=Assumptions!$C$13,"B","C")) -> A | I17: =AVERAGEIF(Raw_Sales_Weekly!$A$2:$A$1806,A17,Raw_Sales_Weekly!$C$2:$C$1806) -> 180.61538 | J17: =SQRT(SUMPRODUCT((Raw_Sales_Weekly!$A$2:$A$1806=A17)*(Raw_Sales_Weekly!$C$2:$C$1806-I17)^2)/COUNTIF(Raw_Sales_Weekly!$A$2:$A$1806,A17)) -> 55.467299 | K17: =IFERROR(J17/I17,0) -> 0.30710174 | L17: =IF(K17<=Assumptions!$C$14,"X",IF(K17<=Assumptions!$C$15,"Y","Z")) -> Y | M17: =H17&L17 -> AY
... A45: MM-1037 | B45: =INDEX(Raw_SKU_Master!$B$2:$B$41,MATCH(A45,Raw_SKU_Master!$A$2:$A$41,0)) -> Packaging Materials Item 03 - Packaging Materials | C45: =INDEX(Raw_SKU_Master!$C$2:$C$41,MATCH(A45,Raw_SKU_Master!$A$2:$A$41,0)) -> Packaging Materials | D45: =SUMIF(Raw_Sales_Weekly!$A$2:$A$1806,A45,Raw_Sales_Weekly!$D$2:$D$1806) -> 1966.29 | E45: =SUMIF(Raw_Sales_Weekly!$A$2:$A$1806,A45,Raw_Sales_Weekly!$C$2:$C$1806) -> 1169 | F45: =SUM($D$6:D45) -> 3163137.9 | G45: =F45/SUM($D$6:$D$45) -> 1 | H45: =IF(G45<=Assumptions!$C$12,"A",IF(G45<=Assumptions!$C$13,"B","C")) -> C | I45: =AVERAGEIF(Raw_Sales_Weekly!$A$2:$A$1806,A45,Raw_Sales_Weekly!$C$2:$C$1806) -> 89.923077 | J45: =SQRT(SUMPRODUCT((Raw_Sales_Weekly!$A$2:$A$1806=A45)*(Raw_Sales_Weekly!$C$2:$C$1806-I45)^2)/COUNTIF(Raw_Sales_Weekly!$A$2:$A$1806,A45)) -> 7.7604673 | K45: =IFERROR(J45/I45,0) -> 0.086301176 | L45: =IF(K45<=Assumptions!$C$14,"X",IF(K45<=Assumptions!$C$15,"Y","Z")) -> X | M45: =H45&L45 -> CX

Sheet Inventory_Planning_Model
B2: Inventory Planning Model
B3: Safety stock, reorder point, EOQ, and next-period forecast -- every cell is a live formula.
B5: Excess-Risk Days-of-Supply Threshold (75th pctile, floor 60 days): | F5: =MAX(60,PERCENTILE(P9:P48,0.75)) -> 60
A8: SKU_ID | B8: SKU_Description | C8: Category | D8: Lead_Time_Days | E8: Unit_Cost | F8: Avg_Daily_Usage | G8: StDev_Weekly_Qty | H8: Lead_Time_Weeks | I8: Safety_Stock | J8: Reorder_Point | K8: Annual_Demand_Qty | L8: EOQ | M8: EOQ_Rounded_to_MOQ | N8: Avg_On_Hand_Qty | O8: Avg_On_Order_Qty | P8: Days_of_Supply | Q8: Days_of_Supply_Incl_Pipeline | R8: Inventory_Status | S8: Next_Period_Forecast_Qty | T8: XYZ_Class | U8: ABC_Class | V8: Excess_Risk_SKU | W8: Avg_Inventory_Value | X8: Excess_Risk_Rank
A9: MM-1033 | B9: =ABC_XYZ_Classification!B6 -> Raw Material Item 04 - Raw Material - Metal Stock | C9: =ABC_XYZ_Classification!C6 -> Raw Material - Metal Stock | D9: =INDEX(Raw_SKU_Master!$I$2:$I$41,MATCH(A9,Raw_SKU_Master!$A$2:$A$41,0)) -> 38 | E9: =INDEX(Raw_SKU_Master!$E$2:$E$41,MATCH(A9,Raw_SKU_Master!$A$2:$A$41,0)) -> 34.39 | F9: =ABC_XYZ_Classification!E6/(Assumptions!$C$18*7) -> 28.912088 | G9: =ABC_XYZ_Classification!J6 -> 121.64214 | H9: =D9/7 -> 5.4285714 | I9: =ROUNDUP(Assumptions!$C$6*G9*SQRT(H9),0) -> 468 | J9: =ROUNDUP(F9*D9+I9,0) -> 1567 | K9: =ABC_XYZ_Classification!E6 -> 10524 | L9: =ROUND(SQRT((2*K9*Assumptions!$C$7)/(E9*Assumptions!$C$8)),0) -> 457 | M9: =ROUNDUP(L9/Assumptions!$C$9,0)*Assumptions!$C$9 -> 475 | N9: =AVERAGEIF(Raw_Inventory_Monthly!$A$2:$A$481,A9,Raw_Inventory_Monthly!$C$2:$C$481) -> 2050.6667 | O9: =AVERAGEIF(Raw_Inventory_Monthly!$A$2:$A$481,A9,Raw_Inventory_Monthly!$G$2:$G$481) -> 194.5 | P9: =IFERROR(N9/F9,0) -> 70.927657 | Q9: =IFERROR((N9+O9)/F9,0) -> 77.654947 | R9: =IF(Q9<Assumptions!$C$16*D9,"Stockout Risk",IF(Q9>Assumptions!$C$17*D9,"Overstock","Healthy")) -> Healthy | S9: =ROUND(FORECAST(MAX(Raw_Sales_Weekly!$E$1484:$E$1533)+1,Raw_Sales_Weekly!$C$1484:$C$1533,Raw_Sales_Weekly!$E$1484:$E$1533),0) -> 185 | T9: =ABC_XYZ_Classification!L6 -> Z | U9: =ABC_XYZ_Classification!H6 -> A | V9: =IF(AND(P9>$F$5,T9="Z"),"Yes","No") -> Yes | W9: =N9*E9 -> 70522.427 | X9: =IF(V9="Yes",COUNTIF($V$9:V9,"Yes"),"") -> 1
A10: MM-1032 | B10: =ABC_XYZ_Classification!B7 -> Raw Material Item 03 - Raw Material - Metal Stock | C10: =ABC_XYZ_Classification!C7 -> Raw Material - Metal Stock | D10: =INDEX(Raw_SKU_Master!$I$2:$I$41,MATCH(A10,Raw_SKU_Master!$A$2:$A$41,0)) -> 43 | E10: =INDEX(Raw_SKU_Master!$E$2:$E$41,MATCH(A10,Raw_SKU_Master!$A$2:$A$41,0)) -> 25.32 | F10: =ABC_XYZ_Classification!E7/(Assumptions!$C$18*7) -> 22.67033 | G10: =ABC_XYZ_Classification!J7 -> 93.090093 | H10: =D10/7 -> 6.1428571 | I10: =ROUNDUP(Assumptions!$C$6*G10*SQRT(H10),0) -> 381 | J10: =ROUNDUP(F10*D10+I10,0) -> 1356 | K10: =ABC_XYZ_Classification!E7 -> 8252 | L10: =ROUND(SQRT((2*K10*Assumptions!$C$7)/(E10*Assumptions!$C$8)),0) -> 471 | M10: =ROUNDUP(L10/Assumptions!$C$9,0)*Assumptions!$C$9 -> 475 | N10: =AVERAGEIF(Raw_Inventory_Monthly!$A$2:$A$481,A10,Raw_Inventory_Monthly!$C$2:$C$481) -> 474.25 | O10: =AVERAGEIF(Raw_Inventory_Monthly!$A$2:$A$481,A10,Raw_Inventory_Monthly!$G$2:$G$481) -> 185.25 | P10: =IFERROR(N10/F10,0) -> 20.919413 | Q10: =IFERROR((N10+O10)/F10,0) -> 29.090887 | R10: =IF(Q10<Assumptions!$C$16*D10,"Stockout Risk",IF(Q10>Assumptions!$C$17*D10,"Overstock","Healthy")) -> Stockout Risk | S10: =ROUND(FORECAST(MAX(Raw_Sales_Weekly!$E$1433:$E$1483)+1,Raw_Sales_Weekly!$C$1433:$C$1483,Raw_Sales_Weekly!$E$1433:$E$1483),0) -> 152 | T10: =ABC_XYZ_Classification!L7 -> Z | U10: =ABC_XYZ_Classification!H7 -> A | V10: =IF(AND(P10>$F$5,T10="Z"),"Yes","No") -> No | W10: =N10*E10 -> 12008.01 | X10: =IF(V10="Yes",COUNTIF($V$9:V10,"Yes"),"")
A11: MM-1025 | B11: =ABC_XYZ_Classification!B8 -> Pneumatic Components Item 01 - Pneumatic Components | C11: =ABC_XYZ_Classification!C8 -> Pneumatic Components | D11: =INDEX(Raw_SKU_Master!$I$2:$I$41,MATCH(A11,Raw_SKU_Master!$A$2:$A$41,0)) -> 55 | E11: =INDEX(Raw_SKU_Master!$E$2:$E$41,MATCH(A11,Raw_SKU_Master!$A$2:$A$41,0)) -> 14.33 | F11: =ABC_XYZ_Classification!E8/(Assumptions!$C$18*7) -> 22.692308 | G11: =ABC_XYZ_Classification!J8 -> 80.431089 | H11: =D11/7 -> 7.8571429 | I11: =ROUNDUP(Assumptions!$C$6*G11*SQRT(H11),0) -> 372 | J11: =ROUNDUP(F11*D11+I11,0) -> 1621 | K11: =ABC_XYZ_Classification!E8 -> 8260 | L11: =ROUND(SQRT((2*K11*Assumptions!$C$7)/(E11*Assumptions!$C$8)),0) -> 627 | M11: =ROUNDUP(L11/Assumptions!$C$9,0)*Assumptions!$C$9 -> 650 | N11: =AVERAGEIF(Raw_Inventory_Monthly!$A$2:$A$481,A11,Raw_Inventory_Monthly!$C$2:$C$481) -> 1192.5833 | O11: =AVERAGEIF(Raw_Inventory_Monthly!$A$2:$A$481,A11,Raw_Inventory_Monthly!$G$2:$G$481) -> 114 | P11: =IFERROR(N11/F11,0) -> 52.55452 | Q11: =IFERROR((N11+O11)/F11,0) -> 57.578249 | R11: =IF(Q11<Assumptions!$C$16*D11,"Stockout Risk",IF(Q11>Assumptions!$C$17*D11,"Overstock","Healthy")) -> Healthy | S11: =ROUND(FORECAST(MAX(Raw_Sales_Weekly!$E$1152:$E$1201)+1,Raw_Sales_Weekly!$C$1152:$C$1201,Raw_Sales_Weekly!$E$1152:$E$1201),0) -> 136 | T11: =ABC_XYZ_Classification!L8 -> Y | U11: =ABC_XYZ_Classification!H8 -> A | V11: =IF(AND(P11>$F$5,T11="Z"),"Yes","No") -> No | W11: =N11*E11 -> 17089.719 | X11: =IF(V11="Yes",COUNTIF($V$9:V11,"Yes"),"")
A12: MM-1030 | B12: =ABC_XYZ_Classification!B9 -> Raw Material Item 01 - Raw Material - Metal Stock | C12: =ABC_XYZ_Classification!C9 -> Raw Material - Metal Stock | D12: =INDEX(Raw_SKU_Master!$I$2:$I$41,MATCH(A12,Raw_SKU_Master!$A$2:$A$41,0)) -> 40 | E12: =INDEX(Raw_SKU_Master!$E$2:$E$41,MATCH(A12,Raw_SKU_Master!$A$2:$A$41,0)) -> 31.3 | F12: =ABC_XYZ_Classification!E9/(Assumptions!$C$18*7) -> 11.211538 | G12: =ABC_XYZ_Classification!J9 -> 50.206823 | H12: =D12/7 -> 5.7142857 | I12: =ROUNDUP(Assumptions!$C$6*G12*SQRT(H12),0) -> 199 | J12: =ROUNDUP(F12*D12+I12,0) -> 648 | K12: =ABC_XYZ_Classification!E9 -> 4081 | L12: =ROUND(SQRT((2*K12*Assumptions!$C$7)/(E12*Assumptions!$C$8)),0) -> 298 | M12: =ROUNDUP(L12/Assumptions!$C$9,0)*Assumptions!$C$9 -> 300 | N12: =AVERAGEIF(Raw_Inventory_Monthly!$A$2:$A$481,A12,Raw_Inventory_Monthly!$C$2:$C$481) -> 1041.1667 | O12: =AVERAGEIF(Raw_Inventory_Monthly!$A$2:$A$481,A12,Raw_Inventory_Monthly!$G$2:$G$481) -> 75.333333 | P12: =IFERROR(N12/F12,0) -> 92.865638 | Q12: =IFERROR((N12+O12)/F12,0) -> 99.584906 | R12: =IF(Q12<Assumptions!$C$16*D12,"Stockout Risk",IF(Q12>Assumptions!$C$17*D12,"Overstock","Healthy")) -> Healthy | S12: =ROUND(FORECAST(MAX(Raw_Sales_Weekly!$E$1377:$E$1427)+1,Raw_Sales_Weekly!$C$1377:$C$1427,Raw_Sales_Weekly!$E$1377:$E$1427),0) -> 100 | T12: =ABC_XYZ_Classification!L9 -> Z | U12: =ABC_XYZ_Classification!H9 -> A | V12: =IF(AND(P12>$F$5,T12="Z"),"Yes","No") -> Yes | W12: =N12*E12 -> 32588.517 | X12: =IF(V12="Yes",COUNTIF($V$9:V12,"Yes"),"") -> 2
A13: MM-1014 | B13: =ABC_XYZ_Classification!B10 -> Electric Motors Item 05 - Electric Motors & Drives | C13: =ABC_XYZ_Classification!C10 -> Electric Motors & Drives | D13: =INDEX(Raw_SKU_Master!$I$2:$I$41,MATCH(A13,Raw_SKU_Master!$A$2:$A$41,0)) -> 40 | E13: =INDEX(Raw_SKU_Master!$E$2:$E$41,MATCH(A13,Raw_SKU_Master!$A$2:$A$41,0)) -> 20.28 | F13: =ABC_XYZ_Classification!E10/(Assumptions!$C$18*7) -> 10.225275 | G13: =ABC_XYZ_Classification!J10 -> 10.508872 | H13: =D13/7 -> 5.7142857 | I13: =ROUNDUP(Assumptions!$C$6*G13*SQRT(H13),0) -> 42 | J13: =ROUNDUP(F13*D13+I13,0) -> 452 | K13: =ABC_XYZ_Classification!E10 -> 3722 | L13: =ROUND(SQRT((2*K13*Assumptions!$C$7)/(E13*Assumptions!$C$8)),0) -> 354 | M13: =ROUNDUP(L13/Assumptions!$C$9,0)*Assumptions!$C$9 -> 375 | N13: =AVERAGEIF(Raw_Inventory_Monthly!$A$2:$A$481,A13,Raw_Inventory_Monthly!$C$2:$C$481) -> 277.83333 | O13: =AVERAGEIF(Raw_Inventory_Monthly!$A$2:$A$481,A13,Raw_Inventory_Monthly!$G$2:$G$481) -> 75.166667 | P13: =IFERROR(N13/F13,0) -> 27.171234 | Q13: =IFERROR((N13+O13)/F13,0) -> 34.5223 | R13: =IF(Q13<Assumptions!$C$16*D13,"Stockout Risk",IF(Q13>Assumptions!$C$17*D13,"Overstock","Healthy")) -> Stockout Risk | S13: =ROUND(FORECAST(MAX(Raw_Sales_Weekly!$E$615:$E$666)+1,Raw_Sales_Weekly!$C$615:$C$666,Raw_Sales_Weekly!$E$615:$E$666),0) -> 68 | T13: =ABC_XYZ_Classification!L10 -> X | U13: =ABC_XYZ_Classification!H10 -> A | V13: =IF(AND(P13>$F$5,T13="Z"),"Yes","No") -> No | W13: =N13*E13 -> 5634.46 | X13: =IF(V13="Yes",COUNTIF($V$9:V13,"Yes"),"")
A14: MM-1010 | B14: =ABC_XYZ_Classification!B11 -> Electric Motors Item 01 - Electric Motors & Drives | C14: =ABC_XYZ_Classification!C11 -> Electric Motors & Drives | D14: =INDEX(Raw_SKU_Master!$I$2:$I$41,MATCH(A14,Raw_SKU_Master!$A$2:$A$41,0)) -> 32 | E14: =INDEX(Raw_SKU_Master!$E$2:$E$41,MATCH(A14,Raw_SKU_Master!$A$2:$A$41,0)) -> 13.08 | F14: =ABC_XYZ_Classification!E11/(Assumptions!$C$18*7) -> 14.087912 | G14: =ABC_XYZ_Classification!J11 -> 13.147322 | H14: =D14/7 -> 4.5714286 | I14: =ROUNDUP(Assumptions!$C$6*G14*SQRT(H14),0) -> 47 | J14: =ROUNDUP(F14*D14+I14,0) -> 498 | K14: =ABC_XYZ_Classification!E11 -> 5128 | L14: =ROUND(SQRT((2*K14*Assumptions!$C$7)/(E14*Assumptions!$C$8)),0) -> 517 | M14: =ROUNDUP(L14/Assumptions!$C$9,0)*Assumptions!$C$9 -> 525 | N14: =AVERAGEIF(Raw_Inventory_Monthly!$A$2:$A$481,A14,Raw_Inventory_Monthly!$C$2:$C$481) -> 317.08333 | O14: =AVERAGEIF(Raw_Inventory_Monthly!$A$2:$A$481,A14,Raw_Inventory_Monthly!$G$2:$G$481) -> 91.25 | P14: =IFERROR(N14/F14,0) -> 22.507475 | Q14: =IFERROR((N14+O14)/F14,0) -> 28.984659 | R14: =IF(Q14<Assumptions!$C$16*D14,"Stockout Risk",IF(Q14>Assumptions!$C$17*D14,"Overstock","Healthy")) -> Stockout Risk | S14: =ROUND(FORECAST(MAX(Raw_Sales_Weekly!$E$440:$E$491)+1,Raw_Sales_Weekly!$C$440:$C$491,Raw_Sales_Weekly!$E$440:$E$491),0) -> 99 | T14: =ABC_XYZ_Classification!L11 -> X | U14: =ABC_XYZ_Classification!H11 -> A | V14: =IF(AND(P14>$F$5,T14="Z"),"Yes","No") -> No | W14: =N14*E14 -> 4147.45 | X14: =IF(V14="Yes",COUNTIF($V$9:V14,"Yes"),"")
A15: MM-1011 | B15: =ABC_XYZ_Classification!B12 -> Electric Motors Item 02 - Electric Motors & Drives | C15: =ABC_XYZ_Classification!C12 -> Electric Motors & Drives | D15: =INDEX(Raw_SKU_Master!$I$2:$I$41,MATCH(A15,Raw_SKU_Master!$A$2:$A$41,0)) -> 52 | E15: =INDEX(Raw_SKU_Master!$E$2:$E$41,MATCH(A15,Raw_SKU_Master!$A$2:$A$41,0)) -> 15.22 | F15: =ABC_XYZ_Classification!E12/(Assumptions!$C$18*7) -> 12.104396 | G15: =ABC_XYZ_Classification!J12 -> 30.562378 | H15: =D15/7 -> 7.4285714 | I15: =ROUNDUP(Assumptions!$C$6*G15*SQRT(H15),0) -> 138 | J15: =ROUNDUP(F15*D15+I15,0) -> 768 | K15: =ABC_XYZ_Classification!E12 -> 4406 | L15: =ROUND(SQRT((2*K15*Assumptions!$C$7)/(E15*Assumptions!$C$8)),0) -> 444 | M15: =ROUNDUP(L15/Assumptions!$C$9,0)*Assumptions!$C$9 -> 450 | N15: =AVERAGEIF(Raw_Inventory_Monthly!$A$2:$A$481,A15,Raw_Inventory_Monthly!$C$2:$C$481) -> 851.41667 | O15: =AVERAGEIF(Raw_Inventory_Monthly!$A$2:$A$481,A15,Raw_Inventory_Monthly!$G$2:$G$481) -> 157.58333 | P15: =IFERROR(N15/F15,0) -> 70.339461 | Q15: =IFERROR((N15+O15)/F15,0) -> 83.358148 | R15: =IF(Q15<Assumptions!$C$16*D15,"Stockout Risk",IF(Q15>Assumptions!$C$17*D15,"Overstock","Healthy")) -> Healthy | S15: =ROUND(FORECAST(MAX(Raw_Sales_Weekly!$E$492:$E$512)+1,Raw_Sales_Weekly!$C$492:$C$512,Raw_Sales_Weekly!$E$492:$E$512),0) -> 200 | T15: =ABC_XYZ_Classification!L12 -> X | U15: =ABC_XYZ_Classification!H12 -> A | V15: =IF(AND(P15>$F$5,T15="Z"),"Yes","No") -> No | W15: =N15*E15 -> 12958.562 | X15: =IF(V15="Yes",COUNTIF($V$9:V15,"Yes"),"")
A16: MM-1013 | B16: =ABC_XYZ_Classification!B13 -> Electric Motors Item 04 - Electric Motors & Drives | C16: =ABC_XYZ_Classification!C13 -> Electric Motors & Drives | D16: =INDEX(Raw_SKU_Master!$I$2:$I$41,MATCH(A16,Raw_SKU_Master!$A$2:$A$41,0)) -> 44 | E16: =INDEX(Raw_SKU_Master!$E$2:$E$41,MATCH(A16,Raw_SKU_Master!$A$2:$A$41,0)) -> 12.69 | F16: =ABC_XYZ_Classification!E13/(Assumptions!$C$18*7) -> 15.793956 | G16: =ABC_XYZ_Classification!J13 -> 15.501133 | H16: =D16/7 -> 6.2857143 | I16: =ROUNDUP(Assumptions!$C$6*G16*SQRT(H16),0) -> 65 | J16: =ROUNDUP(F16*D16+I16,0) -> 760 | K16: =ABC_XYZ_Classification!E13 -> 5749 | L16: =ROUND(SQRT((2*K16*Assumptions!$C$7)/(E16*Assumptions!$C$8)),0) -> 556 | M16: =ROUNDUP(L16/Assumptions!$C$9,0)*Assumptions!$C$9 -> 575 | N16: =AVERAGEIF(Raw_Inventory_Monthly!$A$2:$A$481,A16,Raw_Inventory_Monthly!$C$2:$C$481) -> 345.33333 | O16: =AVERAGEIF(Raw_Inventory_Monthly!$A$2:$A$481,A16,Raw_Inventory_Monthly!$G$2:$G$481) -> 62.666667 | P16: =IFERROR(N16/F16,0) -> 21.864904 | Q16: =IFERROR((N16+O16)/F16,0) -> 25.832667 | R16: =IF(Q16<Assumptions!$C$16*D16,"Stockout Risk",IF(Q16>Assumptions!$C$17*D16,"Overstock","Healthy")) -> Stockout Risk | S16: =ROUND(FORECAST(MAX(Raw_Sales_Weekly!$E$563:$E$614)+1,Raw_Sales_Weekly!$C$563:$C$614,Raw_Sales_Weekly!$E$563:$E$614),0) -> 108 | T16: =ABC_XYZ_Classification!L13 -> X | U16: =ABC_XYZ_Classification!H13 -> A | V16: =IF(AND(P16>$F$5,T16="Z"),"Yes","No") -> No | W16: =N16*E16 -> 4382.28 | X16: =IF(V16="Yes",COUNTIF($V$9:V16,"Yes"),"")
A17: MM-1015 | B17: =ABC_XYZ_Classification!B14 -> Sensors Item 01 - Sensors & Controls | C17: =ABC_XYZ_Classification!C14 -> Sensors & Controls | D17: =INDEX(Raw_SKU_Master!$I$2:$I$41,MATCH(A17,Raw_SKU_Master!$A$2:$A$41,0)) -> 27 | E17: =INDEX(Raw_SKU_Master!$E$2:$E$41,MATCH(A17,Raw_SKU_Master!$A$2:$A$41,0)) -> 5.56 | F17: =ABC_XYZ_Classification!E14/(Assumptions!$C$18*7) -> 26.387363 | G17: =ABC_XYZ_Classification!J14 -> 110.24297 | H17: =D17/7 -> 3.8571429 | I17: =ROUNDUP(Assumptions!$C$6*G17*SQRT(H17),0) -> 358 | J17: =ROUNDUP(F17*D17+I17,0) -> 1071 | K17: =ABC_XYZ_Classification!E14 -> 9605 | L17: =ROUND(SQRT((2*K17*Assumptions!$C$7)/(E17*Assumptions!$C$8)),0) -> 1085 | M17: =ROUNDUP(L17/Assumptions!$C$9,0)*Assumptions!$C$9 -> 1100 | N17: =AVERAGEIF(Raw_Inventory_Monthly!$A$2:$A$481,A17,Raw_Inventory_Monthly!$C$2:$C$481) -> 1398.8333 | O17: =AVERAGEIF(Raw_Inventory_Monthly!$A$2:$A$481,A17,Raw_Inventory_Monthly!$G$2:$G$481) -> 154.66667 | P17: =IFERROR(N17/F17,0) -> 53.011487 | Q17: =IFERROR((N17+O17)/F17,0) -> 58.872879 | R17: =IF(Q17<Assumptions!$C$16*D17,"Stockout Risk",IF(Q17>Assumptions!$C$17*D17,"Overstock","Healthy")) -> Healthy | S17: =ROUND(FORECAST(MAX(Raw_Sales_Weekly!$E$667:$E$718)+1,Raw_Sales_Weekly!$C$667:$C$718,Raw_Sales_Weekly!$E$667:$E$718),0) -> 146 | T17: =ABC_XYZ_Classification!L14 -> Z | U17: =ABC_XYZ_Classification!H14 -> A | V17: =IF(AND(P17>$F$5,T17="Z"),"Yes","No") -> No | W17: =N17*E17 -> 7777.5133 | X17: =IF(V17="Yes",COUNTIF($V$9:V17,"Yes"),"")
A18: MM-1019 | B18: =ABC_XYZ_Classification!B15 -> Sensors Item 05 - Sensors & Controls | C18: =ABC_XYZ_Classification!C15 -> Sensors & Controls | D18: =INDEX(Raw_SKU_Master!$I$2:$I$41,MATCH(A18,Raw_SKU_Master!$A$2:$A$41,0)) -> 22 | E18: =INDEX(Raw_SKU_Master!$E$2:$E$41,MATCH(A18,Raw_SKU_Master!$A$2:$A$41,0)) -> 3.76 | F18: =ABC_XYZ_Classification!E15/(Assumptions!$C$18*7) -> 32.648352 | G18: =ABC_XYZ_Classification!J15 -> 72.072736 | H18: =D18/7 -> 3.1428571 | I18: =ROUNDUP(Assumptions!$C$6*G18*SQRT(H18),0) -> 211 | J18: =ROUNDUP(F18*D18+I18,0) -> 930 | K18: =ABC_XYZ_Classification!E15 -> 11884 | L18: =ROUND(SQRT((2*K18*Assumptions!$C$7)/(E18*Assumptions!$C$8)),0) -> 1468 | M18: =ROUNDUP(L18/Assumptions!$C$9,0)*Assumptions!$C$9 -> 1475 | N18: =AVERAGEIF(Raw_Inventory_Monthly!$A$2:$A$481,A18,Raw_Inventory_Monthly!$C$2:$C$481) -> 1682.5 | O18: =AVERAGEIF(Raw_Inventory_Monthly!$A$2:$A$481,A18,Raw_Inventory_Monthly!$G$2:$G$481) -> 156.66667 | P18: =IFERROR(N18/F18,0) -> 51.533995 | Q18: =IFERROR((N18+O18)/F18,0) -> 56.332604 | R18: =IF(Q18<Assumptions!$C$16*D18,"Stockout Risk",IF(Q18>Assumptions!$C$17*D18,"Overstock","Healthy")) -> Healthy | S18: =ROUND(FORECAST(MAX(Raw_Sales_Weekly!$E$840:$E$891)+1,Raw_Sales_Weekly!$C$840:$C$891,Raw_Sales_Weekly!$E$840:$E$891),0) -> 271 | T18: =ABC_XYZ_Classification!L15 -> Y | U18: =ABC_XYZ_Classification!H15 -> A | V18: =IF(AND(P18>$F$5,T18="Z"),"Yes","No") -> No | W18: =N18*E18 -> 6326.2 | X18: =IF(V18="Yes",COUNTIF($V$9:V18,"Yes"),"")
A19: MM-1034 | B19: =ABC_XYZ_Classification!B16 -> Raw Material Item 05 - Raw Material - Metal Stock | C19: =ABC_XYZ_Classification!C16 -> Raw Material - Metal Stock | D19: =INDEX(Raw_SKU_Master!$I$2:$I$41,MATCH(A19,Raw_SKU_Master!$A$2:$A$41,0)) -> 57 | E19: =INDEX(Raw_SKU_Master!$E$2:$E$41,MATCH(A19,Raw_SKU_Master!$A$2:$A$41,0)) -> 31.12 | F19: =ABC_XYZ_Classification!E16/(Assumptions!$C$18*7) -> 6.5054945 | G19: =ABC_XYZ_Classification!J16 -> 6.3198757 | H19: =D19/7 -> 8.1428571 | I19: =ROUNDUP(Assumptions!$C$6*G19*SQRT(H19),0) -> 30 | J19: =ROUNDUP(F19*D19+I19,0) -> 401 | K19: =ABC_XYZ_Classification!E16 -> 2368 | L19: =ROUND(SQRT((2*K19*Assumptions!$C$7)/(E19*Assumptions!$C$8)),0) -> 228 | M19: =ROUNDUP(L19/Assumptions!$C$9,0)*Assumptions!$C$9 -> 250 | N19: =AVERAGEIF(Raw_Inventory_Monthly!$A$2:$A$481,A19,Raw_Inventory_Monthly!$C$2:$C$481) -> 61 | O19: =AVERAGEIF(Raw_Inventory_Monthly!$A$2:$A$481,A19,Raw_Inventory_Monthly!$G$2:$G$481) -> 33.5 | P19: =IFERROR(N19/F19,0) -> 9.3766892 | Q19: =IFERROR((N19+O19)/F19,0) -> 14.526182 | R19: =IF(Q19<Assumptions!$C$16*D19,"Stockout Risk",IF(Q19>Assumptions!$C$17*D19,"Overstock","Healthy")) -> Stockout Risk | S19: =ROUND(FORECAST(MAX(Raw_Sales_Weekly!$E$1534:$E$1585)+1,Raw_Sales_Weekly!$C$1534:$C$1585,Raw_Sales_Weekly!$E$1534:$E$1585),0) -> 45 | T19: =ABC_XYZ_Classification!L16 -> X | U19: =ABC_XYZ_Classification!H16 -> A | V19: =IF(AND(P19>$F$5,T19="Z"),"Yes","No") -> No | W19: =N19*E19 -> 1898.32 | X19: =IF(V19="Yes",COUNTIF($V$9:V19,"Yes"),"")
A20: MM-1018 | B20: =ABC_XYZ_Classification!B17 -> Sensors Item 04 - Sensors & Controls | C20: =ABC_XYZ_Classification!C17 -> Sensors & Controls | D20: =INDEX(Raw_SKU_Master!$I$2:$I$41,MATCH(A20,Raw_SKU_Master!$A$2:$A$41,0)) -> 25 | E20: =INDEX(Raw_SKU_Master!$E$2:$E$41,MATCH(A20,Raw_SKU_Master!$A$2:$A$41,0)) -> 4.34 | F20: =ABC_XYZ_Classification!E17/(Assumptions!$C$18*7) -> 25.802198 | G20: =ABC_XYZ_Classification!J17 -> 55.467299 | H20: =D20/7 -> 3.5714286 | I20: =ROUNDUP(Assumptions!$C$6*G20*SQRT(H20),0) -> 173 | J20: =ROUNDUP(F20*D20+I20,0) -> 819 | K20: =ABC_XYZ_Classification!E17 -> 9392 | L20: =ROUND(SQRT((2*K20*Assumptions!$C$7)/(E20*Assumptions!$C$8)),0) -> 1215 | M20: =ROUNDUP(L20/Assumptions!$C$9,0)*Assumptions!$C$9 -> 1225 | N20: =AVERAGEIF(Raw_Inventory_Monthly!$A$2:$A$481,A20,Raw_Inventory_Monthly!$C$2:$C$481) -> 866.16667 | O20: =AVERAGEIF(Raw_Inventory_Monthly!$A$2:$A$481,A20,Raw_Inventory_Monthly!$G$2:$G$481) -> 166.25 | P20: =IFERROR(N20/F20,0) -> 33.569492 | Q20: =IFERROR((N20+O20)/F20,0) -> 40.012741 | R20: =IF(Q20<Assumptions!$C$16*D20,"Stockout Risk",IF(Q20>Assumptions!$C$17*D20,"Overstock","Healthy")) -> Healthy | S20: =ROUND(FORECAST(MAX(Raw_Sales_Weekly!$E$788:$E$839)+1,Raw_Sales_Weekly!$C$788:$C$839,Raw_Sales_Weekly!$E$788:$E$839),0) -> 170 | T20: =ABC_XYZ_Classification!L17 -> Y | U20: =ABC_XYZ_Classification!H17 -> A | V20: =IF(AND(P20>$F$5,T20="Z"),"Yes","No") -> No | W20: =N20*E20 -> 3759.1633 | X20: =IF(V20="Yes",COUNTIF($V$9:V20,"Yes"),"")
A21: MM-1026 | B21: =ABC_XYZ_Classification!B18 -> Pneumatic Components Item 02 - Pneumatic Components | C21: =ABC_XYZ_Classification!C18 -> Pneumatic Components | D21: =INDEX(Raw_SKU_Master!$I$2:$I$41,MATCH(A21,Raw_SKU_Master!$A$2:$A$41,0)) -> 51 | E21: =INDEX(Raw_SKU_Master!$E$2:$E$41,MATCH(A21,Raw_SKU_Master!$A$2:$A$41,0)) -> 12.21 | F21: =ABC_XYZ_Classification!E18/(Assumptions!$C$18*7) -> 9.8653846 | G21: =ABC_XYZ_Classification!J18 -> 24.676689 | H21: =D21/7 -> 7.2857143 | I21: =ROUNDUP(Assumptions!$C$6*G21*SQRT(H21),0) -> 110 | J21: =ROUNDUP(F21*D21+I21,0) -> 614 | K21: =ABC_XYZ_Classification!E18 -> 3591 | L21: =ROUND(SQRT((2*K21*Assumptions!$C$7)/(E21*Assumptions!$C$8)),0) -> 448 | M21: =ROUNDUP(L21/Assumptions!$C$9,0)*Assumptions!$C$9 -> 450 | N21: =AVERAGEIF(Raw_Inventory_Monthly!$A$2:$A$481,A21,Raw_Inventory_Monthly!$C$2:$C$481) -> 430.25 | O21: =AVERAGEIF(Raw_Inventory_Monthly!$A$2:$A$481,A21,Raw_Inventory_Monthly!$G$2:$G$481) -> 61.583333 | P21: =IFERROR(N21/F21,0) -> 43.612086 | Q21: =IFERROR((N21+O21)/F21,0) -> 49.854451 | R21: =IF(Q21<Assumptions!$C$16*D21,"Stockout Risk",IF(Q21>Assumptions!$C$17*D21,"Overstock","Healthy")) -> Stockout Risk | S21: =ROUND(FORECAST(MAX(Raw_Sales_Weekly!$E$1202:$E$1253)+1,Raw_Sales_Weekly!$C$1202:$C$1253,Raw_Sales_Weekly!$E$1202:$E$1253),0) -> 56 | T21: =ABC_XYZ_Classification!L18 -> Y | U21: =ABC_XYZ_Classification!H18 -> A | V21: =IF(AND(P21>$F$5,T21="Z"),"Yes","No") -> No | W21: =N21*E21 -> 5253.3525 | X21: =IF(V21="Yes",COUNTIF($V$9:V21,"Yes"),"")
A22: MM-1009 | B22: =ABC_XYZ_Classification!B19 -> Bearings Item 05 - Bearings & Bushings | C22: =ABC_XYZ_Classification!C19 -> Bearings & Bushings | D22: =INDEX(Raw_SKU_Master!$I$2:$I$41,MATCH(A22,Raw_SKU_Master!$A$2:$A$41,0)) -> 141 | E22: =INDEX(Raw_SKU_Master!$E$2:$E$41,MATCH(A22,Raw_SKU_Master!$A$2:$A$41,0)) -> 5.45 | F22: =ABC_XYZ_Classification!E19/(Assumptions!$C$18*7) -> 25.046703 | G22: =ABC_XYZ_Classification!J19 -> 37.503703 | H22: =D22/7 -> 20.142857 | I22: =ROUNDUP(Assumptions!$C$6*G22*SQRT(H22),0) -> 278 | J22: =ROUNDUP(F22*D22+I22,0) -> 3810 | K22: =ABC_XYZ_Classification!E19 -> 9117 | L22: =ROUND(SQRT((2*K22*Assumptions!$C$7)/(E22*Assumptions!$C$8)),0) -> 1068 | M22: =ROUNDUP(L22/Assumptions!$C$9,0)*Assumptions!$C$9 -> 1075 | N22: =AVERAGEIF(Raw_Inventory_Monthly!$A$2:$A$481,A22,Raw_Inventory_Monthly!$C$2:$C$481) -> 293 | O22: =AVERAGEIF(Raw_Inventory_Monthly!$A$2:$A$481,A22,Raw_Inventory_Monthly!$G$2:$G$481) -> 184.16667 | P22: =IFERROR(N22/F22,0) -> 11.698146 | Q22: =IFERROR((N22+O22)/F22,0) -> 19.051077 | R22: =IF(Q22<Assumptions!$C$16*D22,"Stockout Risk",IF(Q22>Assumptions!$C$17*D22,"Overstock","Healthy")) -> Stockout Risk | S22: =ROUND(FORECAST(MAX(Raw_Sales_Weekly!$E$388:$E$439)+1,Raw_Sales_Weekly!$C$388:$C$439,Raw_Sales_Weekly!$E$388:$E$439),0) -> 151 | T22: =ABC_XYZ_Classification!L19 -> X | U22: =ABC_XYZ_Classification!H19 -> A | V22: =IF(AND(P22>$F$5,T22="Z"),"Yes","No") -> No | W22: =N22*E22 -> 1596.85 | X22: =IF(V22="Yes",COUNTIF($V$9:V22,"Yes"),"")
A23: MM-1012 | B23: =ABC_XYZ_Classification!B20 -> Electric Motors Item 03 - Electric Motors & Drives | C23: =ABC_XYZ_Classification!C20 -> Electric Motors & Drives | D23: =INDEX(Raw_SKU_Master!$I$2:$I$41,MATCH(A23,Raw_SKU_Master!$A$2:$A$41,0)) -> 39 | E23: =INDEX(Raw_SKU_Master!$E$2:$E$41,MATCH(A23,Raw_SKU_Master!$A$2:$A$41,0)) -> 17.6 | F23: =ABC_XYZ_Classification!E20/(Assumptions!$C$18*7) -> 5.8351648 | G23: =ABC_XYZ_Classification!J20 -> 22.763339 | H23: =D23/7 -> 5.5714286 | I23: =ROUNDUP(Assumptions!$C$6*G23*SQRT(H23),0) -> 89 | J23: =ROUNDUP(F23*D23+I23,0) -> 317 | K23: =ABC_XYZ_Classification!E20 -> 2124 | L23: =ROUND(SQRT((2*K23*Assumptions!$C$7)/(E23*Assumptions!$C$8)),0) -> 287 | M23: =ROUNDUP(L23/Assumptions!$C$9,0)*Assumptions!$C$9 -> 300 | N23: =AVERAGEIF(Raw_Inventory_Monthly!$A$2:$A$481,A23,Raw_Inventory_Monthly!$C$2:$C$481) -> 289.66667 | O23: =AVERAGEIF(Raw_Inventory_Monthly!$A$2:$A$481,A23,Raw_Inventory_Monthly!$G$2:$G$481) -> 31.083333 | P23: =IFERROR(N23/F23,0) -> 49.641557 | Q23: =IFERROR((N23+O23)/F23,0) -> 54.968456 | R23: =IF(Q23<Assumptions!$C$16*D23,"Stockout Risk",IF(Q23>Assumptions!$C$17*D23,"Overstock","Healthy")) -> Healthy | S23: =ROUND(FORECAST(MAX(Raw_Sales_Weekly!$E$513:$E$562)+1,Raw_Sales_Weekly!$C$513:$C$562,Raw_Sales_Weekly!$E$513:$E$562),0) -> 31 | T23: =ABC_XYZ_Classification!L20 -> Y | U23: =ABC_XYZ_Classification!H20 -> A | V23: =IF(AND(P23>$F$5,T23="Z"),"Yes","No") -> No | W23: =N23*E23 -> 5098.1333 | X23: =IF(V23="Yes",COUNTIF($V$9:V23,"Yes"),"")
A24: MM-1027 | B24: =ABC_XYZ_Classification!B21 -> Pneumatic Components Item 03 - Pneumatic Components | C24: =ABC_XYZ_Classification!C21 -> Pneumatic Components | D24: =INDEX(Raw_SKU_Master!$I$2:$I$41,MATCH(A24,Raw_SKU_Master!$A$2:$A$41,0)) -> 57 | E24: =INDEX(Raw_SKU_Master!$E$2:$E$41,MATCH(A24,Raw_SKU_Master!$A$2:$A$41,0)) -> 7.11 | F24: =ABC_XYZ_Classification!E21/(Assumptions!$C$18*7) -> 14.82967 | G24: =ABC_XYZ_Classification!J21 -> 63.999501 | H24: =D24/7 -> 8.1428571 | I24: =ROUNDUP(Assumptions!$C$6*G24*SQRT(H24),0) -> 302 | J24: =ROUNDUP(F24*D24+I24,0) -> 1148 | K24: =ABC_XYZ_Classification!E21 -> 5398 | L24: =ROUND(SQRT((2*K24*Assumptions!$C$7)/(E24*Assumptions!$C$8)),0) -> 719 | M24: =ROUNDUP(L24/Assumptions!$C$9,0)*Assumptions!$C$9 -> 725 | N24: =AVERAGEIF(Raw_Inventory_Monthly!$A$2:$A$481,A24,Raw_Inventory_Monthly!$C$2:$C$481) -> 363.91667 | O24: =AVERAGEIF(Raw_Inventory_Monthly!$A$2:$A$481,A24,Raw_Inventory_Monthly!$G$2:$G$481) -> 78.833333 | P24: =IFERROR(N24/F24,0) -> 24.539768 | Q24: =IFERROR((N24+O24)/F24,0) -> 29.855687 | R24: =IF(Q24<Assumptions!$C$16*D24,"Stockout Risk",IF(Q24>Assumptions!$C$17*D24,"Overstock","Healthy")) -> Stockout Risk | S24: =ROUND(FORECAST(MAX(Raw_Sales_Weekly!$E$1254:$E$1304)+1,Raw_Sales_Weekly!$C$1254:$C$1304,Raw_Sales_Weekly!$E$1254:$E$1304),0) -> 117 | T24: =ABC_XYZ_Classification!L21 -> Z | U24: =ABC_XYZ_Classification!H21 -> B | V24: =IF(AND(P24>$F$5,T24="Z"),"Yes","No") -> No | W24: =N24*E24 -> 2587.4475 | X24: =IF(V24="Yes",COUNTIF($V$9:V24,"Yes"),"")
A25: MM-1004 | B25: =ABC_XYZ_Classification!B22 -> Fasteners Item 05 - Fasteners & Hardware | C25: =ABC_XYZ_Classification!C22 -> Fasteners & Hardware | D25: =INDEX(Raw_SKU_Master!$I$2:$I$41,MATCH(A25,Raw_SKU_Master!$A$2:$A$41,0)) -> 49 | E25: =INDEX(Raw_SKU_Master!$E$2:$E$41,MATCH(A25,Raw_SKU_Master!$A$2:$A$41,0)) -> 3.55 | F25: =ABC_XYZ_Classification!E22/(Assumptions!$C$18*7) -> 25.225275 | G25: =ABC_XYZ_Classification!J22 -> 34.409495 | H25: =D25/7 -> 7 | I25: =ROUNDUP(Assumptions!$C$6*G25*SQRT(H25),0) -> 151 | J25: =ROUNDUP(F25*D25+I25,0) -> 1388 | K25: =ABC_XYZ_Classification!E22 -> 9182 | L25: =ROUND(SQRT((2*K25*Assumptions!$C$7)/(E25*Assumptions!$C$8)),0) -> 1328 | M25: =ROUNDUP(L25/Assumptions!$C$9,0)*Assumptions!$C$9 -> 1350 | N25: =AVERAGEIF(Raw_Inventory_Monthly!$A$2:$A$481,A25,Raw_Inventory_Monthly!$C$2:$C$481) -> 694.83333 | O25: =AVERAGEIF(Raw_Inventory_Monthly!$A$2:$A$481,A25,Raw_Inventory_Monthly!$G$2:$G$481) -> 170.25 | P25: =IFERROR(N25/F25,0) -> 27.545125 | Q25: =IFERROR((N25+O25)/F25,0) -> 34.294308 | R25: =IF(Q25<Assumptions!$C$16*D25,"Stockout Risk",IF(Q25>Assumptions!$C$17*D25,"Overstock","Healthy")) -> Stockout Risk | S25: =ROUND(FORECAST(MAX(Raw_Sales_Weekly!$E$170:$E$221)+1,Raw_Sales_Weekly!$C$170:$C$221,Raw_Sales_Weekly!$E$170:$E$221),0) -> 154 | T25: =ABC_XYZ_Classification!L22 -> X | U25: =ABC_XYZ_Classification!H22 -> B | V25: =IF(AND(P25>$F$5,T25="Z"),"Yes","No") -> No | W25: =N25*E25 -> 2466.6583 | X25: =IF(V25="Yes",COUNTIF($V$9:V25,"Yes"),"")
A26: MM-1016 | B26: =ABC_XYZ_Classification!B23 -> Sensors Item 02 - Sensors & Controls | C26: =ABC_XYZ_Classification!C23 -> Sensors & Controls | D26: =INDEX(Raw_SKU_Master!$I$2:$I$41,MATCH(A26,Raw_SKU_Master!$A$2:$A$41,0)) -> 30 | E26: =INDEX(Raw_SKU_Master!$E$2:$E$41,MATCH(A26,Raw_SKU_Master!$A$2:$A$41,0)) -> 4.87 | F26: =ABC_XYZ_Classification!E23/(Assumptions!$C$18*7) -> 13.813187 | G26: =ABC_XYZ_Classification!J23 -> 29.547575 | H26: =D26/7 -> 4.2857143 | I26: =ROUNDUP(Assumptions!$C$6*G26*SQRT(H26),0) -> 101 | J26: =ROUNDUP(F26*D26+I26,0) -> 516 | K26: =ABC_XYZ_Classification!E23 -> 5028 | L26: =ROUND(SQRT((2*K26*Assumptions!$C$7)/(E26*Assumptions!$C$8)),0) -> 839 | M26: =ROUNDUP(L26/Assumptions!$C$9,0)*Assumptions!$C$9 -> 850 | N26: =AVERAGEIF(Raw_Inventory_Monthly!$A$2:$A$481,A26,Raw_Inventory_Monthly!$C$2:$C$481) -> 406.33333 | O26: =AVERAGEIF(Raw_Inventory_Monthly!$A$2:$A$481,A26,Raw_Inventory_Monthly!$G$2:$G$481) -> 74.166667 | P26: =IFERROR(N26/F26,0) -> 29.416335 | Q26: =IFERROR((N26+O26)/F26,0) -> 34.785601 | R26: =IF(Q26<Assumptions!$C$16*D26,"Stockout Risk",IF(Q26>Assumptions!$C$17*D26,"Overstock","Healthy")) -> Healthy | S26: =ROUND(FORECAST(MAX(Raw_Sales_Weekly!$E$719:$E$770)+1,Raw_Sales_Weekly!$C$719:$C$770,Raw_Sales_Weekly!$E$719:$E$770),0) -> 100 | T26: =ABC_XYZ_Classification!L23 -> Y | U26: =ABC_XYZ_Classification!H23 -> B | V26: =IF(AND(P26>$F$5,T26="Z"),"Yes","No") -> No | W26: =N26*E26 -> 1978.8433 | X26: =IF(V26="Yes",COUNTIF($V$9:V26,"Yes"),"")
A27: MM-1001 | B27: =ABC_XYZ_Classification!B24 -> Fasteners Item 02 - Fasteners & Hardware | C27: =ABC_XYZ_Classification!C24 -> Fasteners & Hardware | D27: =INDEX(Raw_SKU_Master!$I$2:$I$41,MATCH(A27,Raw_SKU_Master!$A$2:$A$41,0)) -> 43 | E27: =INDEX(Raw_SKU_Master!$E$2:$E$41,MATCH(A27,Raw_SKU_Master!$A$2:$A$41,0)) -> 3.86 | F27: =ABC_XYZ_Classification!E24/(Assumptions!$C$18*7) -> 22.978022 | G27: =ABC_XYZ_Classification!J24 -> 30.509384 | H27: =D27/7 -> 6.1428571 | I27: =ROUNDUP(Assumptions!$C$6*G27*SQRT(H27),0) -> 125 | J27: =ROUNDUP(F27*D27+I27,0) -> 1114 | K27: =ABC_XYZ_Classification!E24 -> 8364 | L27: =ROUND(SQRT((2*K27*Assumptions!$C$7)/(E27*Assumptions!$C$8)),0) -> 1215 | M27: =ROUNDUP(L27/Assumptions!$C$9,0)*Assumptions!$C$9 -> 1225 | N27: =AVERAGEIF(Raw_Inventory_Monthly!$A$2:$A$481,A27,Raw_Inventory_Monthly!$C$2:$C$481) -> 203.16667 | O27: =AVERAGEIF(Raw_Inventory_Monthly!$A$2:$A$481,A27,Raw_Inventory_Monthly!$G$2:$G$481) -> 126.91667 | P27: =IFERROR(N27/F27,0) -> 8.8417822 | Q27: =IFERROR((N27+O27)/F27,0) -> 14.365176 | R27: =IF(Q27<Assumptions!$C$16*D27,"Stockout Risk",IF(Q27>Assumptions!$C$17*D27,"Overstock","Healthy")) -> Stockout Risk | S27: =ROUND(FORECAST(MAX(Raw_Sales_Weekly!$E$54:$E$105)+1,Raw_Sales_Weekly!$C$54:$C$105,Raw_Sales_Weekly!$E$54:$E$105),0) -> 158 | T27: =ABC_XYZ_Classification!L24 -> X | U27: =ABC_XYZ_Classification!H24 -> B | V27: =IF(AND(P27>$F$5,T27="Z"),"Yes","No") -> No | W27: =N27*E27 -> 784.22333 | X27: =IF(V27="Yes",COUNTIF($V$9:V27,"Yes"),"")
A28: MM-1017 | B28: =ABC_XYZ_Classification!B25 -> Sensors Item 03 - Sensors & Controls | C28: =ABC_XYZ_Classification!C25 -> Sensors & Controls | D28: =INDEX(Raw_SKU_Master!$I$2:$I$41,MATCH(A28,Raw_SKU_Master!$A$2:$A$41,0)) -> 31 | E28: =INDEX(Raw_SKU_Master!$E$2:$E$41,MATCH(A28,Raw_SKU_Master!$A$2:$A$41,0)) -> 8.28 | F28: =ABC_XYZ_Classification!E25/(Assumptions!$C$18*7) -> 8.5851648 | G28: =ABC_XYZ_Classification!J25 -> 65.503691 | H28: =D28/7 -> 4.4285714 | I28: =ROUNDUP(Assumptions!$C$6*G28*SQRT(H28),0) -> 228 | J28: =ROUNDUP(F28*D28+I28,0) -> 495 | K28: =ABC_XYZ_Classification!E25 -> 3125 | L28: =ROUND(SQRT((2*K28*Assumptions!$C$7)/(E28*Assumptions!$C$8)),0) -> 507 | M28: =ROUNDUP(L28/Assumptions!$C$9,0)*Assumptions!$C$9 -> 525 | N28: =AVERAGEIF(Raw_Inventory_Monthly!$A$2:$A$481,A28,Raw_Inventory_Monthly!$C$2:$C$481) -> 1255.8333 | O28: =AVERAGEIF(Raw_Inventory_Monthly!$A$2:$A$481,A28,Raw_Inventory_Monthly!$G$2:$G$481) -> 113.33333 | P28: =IFERROR(N28/F28,0) -> 146.27947 | Q28: =IFERROR((N28+O28)/F28,0) -> 159.48053 | R28: =IF(Q28<Assumptions!$C$16*D28,"Stockout Risk",IF(Q28>Assumptions!$C$17*D28,"Overstock","Healthy")) -> Overstock | S28: =ROUND(FORECAST(MAX(Raw_Sales_Weekly!$E$771:$E$787)+1,Raw_Sales_Weekly!$C$771:$C$787,Raw_Sales_Weekly!$E$771:$E$787),0) -> 156 | T28: =ABC_XYZ_Classification!L25 -> Y | U28: =ABC_XYZ_Classification!H25 -> B | V28: =IF(AND(P28>$F$5,T28="Z"),"Yes","No") -> No | W28: =N28*E28 -> 10398.3 | X28: =IF(V28="Yes",COUNTIF($V$9:V28,"Yes"),"")
A29: MM-1000 | B29: =ABC_XYZ_Classification!B26 -> Fasteners Item 01 - Fasteners & Hardware | C29: =ABC_XYZ_Classification!C26 -> Fasteners & Hardware | D29: =INDEX(Raw_SKU_Master!$I$2:$I$41,MATCH(A29,Raw_SKU_Master!$A$2:$A$41,0)) -> 65 | E29: =INDEX(Raw_SKU_Master!$E$2:$E$41,MATCH(A29,Raw_SKU_Master!$A$2:$A$41,0)) -> 3.82 | F29: =ABC_XYZ_Classification!E26/(Assumptions!$C$18*7) -> 19.228022 | G29: =ABC_XYZ_Classification!J26 -> 34.997395 | H29: =D29/7 -> 9.2857143 | I29: =ROUNDUP(Assumptions!$C$6*G29*SQRT(H29),0) -> 176 | J29: =ROUNDUP(F29*D29+I29,0) -> 1426 | K29: =ABC_XYZ_Classification!E26 -> 6999 | L29: =ROUND(SQRT((2*K29*Assumptions!$C$7)/(E29*Assumptions!$C$8)),0) -> 1118 | M29: =ROUNDUP(L29/Assumptions!$C$9,0)*Assumptions!$C$9 -> 1125 | N29: =AVERAGEIF(Raw_Inventory_Monthly!$A$2:$A$481,A29,Raw_Inventory_Monthly!$C$2:$C$481) -> 388.58333 | O29: =AVERAGEIF(Raw_Inventory_Monthly!$A$2:$A$481,A29,Raw_Inventory_Monthly!$G$2:$G$481) -> 119.33333 | P29: =IFERROR(N29/F29,0) -> 20.20922 | Q29: =IFERROR((N29+O29)/F29,0) -> 26.41544 | R29: =IF(Q29<Assumptions!$C$16*D29,"Stockout Risk",IF(Q29>Assumptions!$C$17*D29,"Overstock","Healthy")) -> Stockout Risk | S29: =ROUND(FORECAST(MAX(Raw_Sales_Weekly!$E$2:$E$53)+1,Raw_Sales_Weekly!$C$2:$C$53,Raw_Sales_Weekly!$E$2:$E$53),0) -> 117 | T29: =ABC_XYZ_Classification!L26 -> X | U29: =ABC_XYZ_Classification!H26 -> B | V29: =IF(AND(P29>$F$5,T29="Z"),"Yes","No") -> No | W29: =N29*E29 -> 1484.3883 | X29: =IF(V29="Yes",COUNTIF($V$9:V29,"Yes"),"")
A30: MM-1029 | B30: =ABC_XYZ_Classification!B27 -> Pneumatic Components Item 05 - Pneumatic Components | C30: =ABC_XYZ_Classification!C27 -> Pneumatic Components | D30: =INDEX(Raw_SKU_Master!$I$2:$I$41,MATCH(A30,Raw_SKU_Master!$A$2:$A$41,0)) -> 19 | E30: =INDEX(Raw_SKU_Master!$E$2:$E$41,MATCH(A30,Raw_SKU_Master!$A$2:$A$41,0)) -> 6.07 | F30: =ABC_XYZ_Classification!E27/(Assumptions!$C$18*7) -> 10.56044 | G30: =ABC_XYZ_Classification!J27 -> 21.523553 | H30: =D30/7 -> 2.7142857 | I30: =ROUNDUP(Assumptions!$C$6*G30*SQRT(H30),0) -> 59 | J30: =ROUNDUP(F30*D30+I30,0) -> 260 | K30: =ABC_XYZ_Classification!E27 -> 3844 | L30: =ROUND(SQRT((2*K30*Assumptions!$C$7)/(E30*Assumptions!$C$8)),0) -> 657 | M30: =ROUNDUP(L30/Assumptions!$C$9,0)*Assumptions!$C$9 -> 675 | N30: =AVERAGEIF(Raw_Inventory_Monthly!$A$2:$A$481,A30,Raw_Inventory_Monthly!$C$2:$C$481) -> 297.58333 | O30: =AVERAGEIF(Raw_Inventory_Monthly!$A$2:$A$481,A30,Raw_Inventory_Monthly!$G$2:$G$481) -> 68 | P30: =IFERROR(N30/F30,0) -> 28.179067 | Q30: =IFERROR((N30+O30)/F30,0) -> 34.618193 | R30: =IF(Q30<Assumptions!$C$16*D30,"Stockout Risk",IF(Q30>Assumptions!$C$17*D30,"Overstock","Healthy")) -> Healthy | S30: =ROUND(FORECAST(MAX(Raw_Sales_Weekly!$E$1325:$E$1376)+1,Raw_Sales_Weekly!$C$1325:$C$1376,Raw_Sales_Weekly!$E$1325:$E$1376),0) -> 85 | T30: =ABC_XYZ_Classification!L27 -> X | U30: =ABC_XYZ_Classification!H27 -> B | V30: =IF(AND(P30>$F$5,T30="Z"),"Yes","No") -> No | W30: =N30*E30 -> 1806.3308 | X30: =IF(V30="Yes",COUNTIF($V$9:V30,"Yes"),"")
A31: MM-1008 | B31: =ABC_XYZ_Classification!B28 -> Bearings Item 04 - Bearings & Bushings | C31: =ABC_XYZ_Classification!C28 -> Bearings & Bushings | D31: =INDEX(Raw_SKU_Master!$I$2:$I$41,MATCH(A31,Raw_SKU_Master!$A$2:$A$41,0)) -> 164 | E31: =INDEX(Raw_SKU_Master!$E$2:$E$41,MATCH(A31,Raw_SKU_Master!$A$2:$A$41,0)) -> 5.13 | F31: =ABC_XYZ_Classification!E28/(Assumptions!$C$18*7) -> 13.373626 | G31: =ABC_XYZ_Classification!J28 -> 33.632147 | H31: =D31/7 -> 23.428571 | I31: =ROUNDUP(Assumptions!$C$6*G31*SQRT(H31),0) -> 269 | J31: =ROUNDUP(F31*D31+I31,0) -> 2463 | K31: =ABC_XYZ_Classification!E28 -> 4868 | L31: =ROUND(SQRT((2*K31*Assumptions!$C$7)/(E31*Assumptions!$C$8)),0) -> 804 | M31: =ROUNDUP(L31/Assumptions!$C$9,0)*Assumptions!$C$9 -> 825 | N31: =AVERAGEIF(Raw_Inventory_Monthly!$A$2:$A$481,A31,Raw_Inventory_Monthly!$C$2:$C$481) -> 414.41667 | O31: =AVERAGEIF(Raw_Inventory_Monthly!$A$2:$A$481,A31,Raw_Inventory_Monthly!$G$2:$G$481) -> 88.25 | P31: =IFERROR(N31/F31,0) -> 30.987606 | Q31: =IFERROR((N31+O31)/F31,0) -> 37.586415 | R31: =IF(Q31<Assumptions!$C$16*D31,"Stockout Risk",IF(Q31>Assumptions!$C$17*D31,"Overstock","Healthy")) -> Stockout Risk | S31: =ROUND(FORECAST(MAX(Raw_Sales_Weekly!$E$336:$E$387)+1,Raw_Sales_Weekly!$C$336:$C$387,Raw_Sales_Weekly!$E$336:$E$387),0) -> 68 | T31: =ABC_XYZ_Classification!L28 -> Y | U31: =ABC_XYZ_Classification!H28 -> B | V31: =IF(AND(P31>$F$5,T31="Z"),"Yes","No") -> No | W31: =N31*E31 -> 2125.9575 | X31: =IF(V31="Yes",COUNTIF($V$9:V31,"Yes"),"")
A32: MM-1002 | B32: =ABC_XYZ_Classification!B29 -> Fasteners Item 03 - Fasteners & Hardware | C32: =ABC_XYZ_Classification!C29 -> Fasteners & Hardware | D32: =INDEX(Raw_SKU_Master!$I$2:$I$41,MATCH(A32,Raw_SKU_Master!$A$2:$A$41,0)) -> 60 | E32: =INDEX(Raw_SKU_Master!$E$2:$E$41,MATCH(A32,Raw_SKU_Master!$A$2:$A$41,0)) -> 2.83 | F32: =ABC_XYZ_Classification!E29/(Assumptions!$C$18*7) -> 17.843407 | G32: =ABC_XYZ_Classification!J29 -> 43.563949 | H32: =D32/7 -> 8.5714286 | I32: =ROUNDUP(Assumptions!$C$6*G32*SQRT(H32),0) -> 211 | J32: =ROUNDUP(F32*D32+I32,0) -> 1282 | K32: =ABC_XYZ_Classification!E29 -> 6495 | L32: =ROUND(SQRT((2*K32*Assumptions!$C$7)/(E32*Assumptions!$C$8)),0) -> 1251 | M32: =ROUNDUP(L32/Assumptions!$C$9,0)*Assumptions!$C$9 -> 1275 | N32: =AVERAGEIF(Raw_Inventory_Monthly!$A$2:$A$481,A32,Raw_Inventory_Monthly!$C$2:$C$481) -> 419.83333 | O32: =AVERAGEIF(Raw_Inventory_Monthly!$A$2:$A$481,A32,Raw_Inventory_Monthly!$G$2:$G$481) -> 128.16667 | P32: =IFERROR(N32/F32,0) -> 23.528766 | Q32: =IFERROR((N32+O32)/F32,0) -> 30.711624 | R32: =IF(Q32<Assumptions!$C$16*D32,"Stockout Risk",IF(Q32>Assumptions!$C$17*D32,"Overstock","Healthy")) -> Stockout Risk | S32: =ROUND(FORECAST(MAX(Raw_Sales_Weekly!$E$106:$E$157)+1,Raw_Sales_Weekly!$C$106:$C$157,Raw_Sales_Weekly!$E$106:$E$157),0) -> 132 | T32: =ABC_XYZ_Classification!L29 -> Y | U32: =ABC_XYZ_Classification!H29 -> B | V32: =IF(AND(P32>$F$5,T32="Z"),"Yes","No") -> No | W32: =N32*E32 -> 1188.1283 | X32: =IF(V32="Yes",COUNTIF($V$9:V32,"Yes"),"")
A33: MM-1007 | B33: =ABC_XYZ_Classification!B30 -> Bearings Item 03 - Bearings & Bushings | C33: =ABC_XYZ_Classification!C30 -> Bearings & Bushings | D33: =INDEX(Raw_SKU_Master!$I$2:$I$41,MATCH(A33,Raw_SKU_Master!$A$2:$A$41,0)) -> 128 | E33: =INDEX(Raw_SKU_Master!$E$2:$E$41,MATCH(A33,Raw_SKU_Master!$A$2:$A$41,0)) -> 3.36 | F33: =ABC_XYZ_Classification!E30/(Assumptions!$C$18*7) -> 12.997253 | G33: =ABC_XYZ_Classification!J30 -> 16.183432 | H33: =D33/7 -> 18.285714 | I33: =ROUNDUP(Assumptions!$C$6*G33*SQRT(H33),0) -> 115 | J33: =ROUNDUP(F33*D33+I33,0) -> 1779 | K33: =ABC_XYZ_Classification!E30 -> 4731 | L33: =ROUND(SQRT((2*K33*Assumptions!$C$7)/(E33*Assumptions!$C$8)),0) -> 980 | M33: =ROUNDUP(L33/Assumptions!$C$9,0)*Assumptions!$C$9 -> 1000 | N33: =AVERAGEIF(Raw_Inventory_Monthly!$A$2:$A$481,A33,Raw_Inventory_Monthly!$C$2:$C$481) -> 135.91667 | O33: =AVERAGEIF(Raw_Inventory_Monthly!$A$2:$A$481,A33,Raw_Inventory_Monthly!$G$2:$G$481) -> 71.333333 | P33: =IFERROR(N33/F33,0) -> 10.457338 | Q33: =IFERROR((N33+O33)/F33,0) -> 15.945677 | R33: =IF(Q33<Assumptions!$C$16*D33,"Stockout Risk",IF(Q33>Assumptions!$C$17*D33,"Overstock","Healthy")) -> Stockout Risk | S33: =ROUND(FORECAST(MAX(Raw_Sales_Weekly!$E$284:$E$335)+1,Raw_Sales_Weekly!$C$284:$C$335,Raw_Sales_Weekly!$E$284:$E$335),0) -> 86 | T33: =ABC_XYZ_Classification!L30 -> X | U33: =ABC_XYZ_Classification!H30 -> B | V33: =IF(AND(P33>$F$5,T33="Z"),"Yes","No") -> No | W33: =N33*E33 -> 456.68 | X33: =IF(V33="Yes",COUNTIF($V$9:V33,"Yes"),"")
A34: MM-1020 | B34: =ABC_XYZ_Classification!B31 -> Seals Item 01 - Seals & Gaskets | C34: =ABC_XYZ_Classification!C31 -> Seals & Gaskets | D34: =INDEX(Raw_SKU_Master!$I$2:$I$41,MATCH(A34,Raw_SKU_Master!$A$2:$A$41,0)) -> 16 | E34: =INDEX(Raw_SKU_Master!$E$2:$E$41,MATCH(A34,Raw_SKU_Master!$A$2:$A$41,0)) -> 2.59 | F34: =ABC_XYZ_Classification!E31/(Assumptions!$C$18*7) -> 13.186813 | G34: =ABC_XYZ_Classification!J31 -> 29.226923 | H34: =D34/7 -> 2.2857143 | I34: =ROUNDUP(Assumptions!$C$6*G34*SQRT(H34),0) -> 73 | J34: =ROUNDUP(F34*D34+I34,0) -> 284 | K34: =ABC_XYZ_Classification!E31 -> 4800 | L34: =ROUND(SQRT((2*K34*Assumptions!$C$7)/(E34*Assumptions!$C$8)),0) -> 1124 | M34: =ROUNDUP(L34/Assumptions!$C$9,0)*Assumptions!$C$9 -> 1125 | N34: =AVERAGEIF(Raw_Inventory_Monthly!$A$2:$A$481,A34,Raw_Inventory_Monthly!$C$2:$C$481) -> 243.83333 | O34: =AVERAGEIF(Raw_Inventory_Monthly!$A$2:$A$481,A34,Raw_Inventory_Monthly!$G$2:$G$481) -> 56.5 | P34: =IFERROR(N34/F34,0) -> 18.490694 | Q34: =IFERROR((N34+O34)/F34,0) -> 22.775278 | R34: =IF(Q34<Assumptions!$C$16*D34,"Stockout Risk",IF(Q34>Assumptions!$C$17*D34,"Overstock","Healthy")) -> Healthy | S34: =ROUND(FORECAST(MAX(Raw_Sales_Weekly!$E$892:$E$943)+1,Raw_Sales_Weekly!$C$892:$C$943,Raw_Sales_Weekly!$E$892:$E$943),0) -> 86 | T34: =ABC_XYZ_Classification!L31 -> Y | U34: =ABC_XYZ_Classification!H31 -> C | V34: =IF(AND(P34>$F$5,T34="Z"),"Yes","No") -> No | W34: =N34*E34 -> 631.52833 | X34: =IF(V34="Yes",COUNTIF($V$9:V34,"Yes"),"")
A35: MM-1005 | B35: =ABC_XYZ_Classification!B32 -> Bearings Item 01 - Bearings & Bushings | C35: =ABC_XYZ_Classification!C32 -> Bearings & Bushings | D35: =INDEX(Raw_SKU_Master!$I$2:$I$41,MATCH(A35,Raw_SKU_Master!$A$2:$A$41,0)) -> 95 | E35: =INDEX(Raw_SKU_Master!$E$2:$E$41,MATCH(A35,Raw_SKU_Master!$A$2:$A$41,0)) -> 3.02 | F35: =ABC_XYZ_Classification!E32/(Assumptions!$C$18*7) -> 10.208791 | G35: =ABC_XYZ_Classification!J32 -> 20.095409 | H35: =D35/7 -> 13.571429 | I35: =ROUNDUP(Assumptions!$C$6*G35*SQRT(H35),0) -> 123 | J35: =ROUNDUP(F35*D35+I35,0) -> 1093 | K35: =ABC_XYZ_Classification!E32 -> 3716 | L35: =ROUND(SQRT((2*K35*Assumptions!$C$7)/(E35*Assumptions!$C$8)),0) -> 916 | M35: =ROUNDUP(L35/Assumptions!$C$9,0)*Assumptions!$C$9 -> 925 | N35: =AVERAGEIF(Raw_Inventory_Monthly!$A$2:$A$481,A35,Raw_Inventory_Monthly!$C$2:$C$481) -> 268.75 | O35: =AVERAGEIF(Raw_Inventory_Monthly!$A$2:$A$481,A35,Raw_Inventory_Monthly!$G$2:$G$481) -> 56.5 | P35: =IFERROR(N35/F35,0) -> 26.32535 | Q35: =IFERROR((N35+O35)/F35,0) -> 31.859795 | R35: =IF(Q35<Assumptions!$C$16*D35,"Stockout Risk",IF(Q35>Assumptions!$C$17*D35,"Overstock","Healthy")) -> Stockout Risk | S35: =ROUND(FORECAST(MAX(Raw_Sales_Weekly!$E$222:$E$273)+1,Raw_Sales_Weekly!$C$222:$C$273,Raw_Sales_Weekly!$E$222:$E$273),0) -> 70 | T35: =ABC_XYZ_Classification!L32 -> X | U35: =ABC_XYZ_Classification!H32 -> C | V35: =IF(AND(P35>$F$5,T35="Z"),"Yes","No") -> No | W35: =N35*E35 -> 811.625 | X35: =IF(V35="Yes",COUNTIF($V$9:V35,"Yes"),"")
A36: MM-1035 | B36: =ABC_XYZ_Classification!B33 -> Packaging Materials Item 01 - Packaging Materials | C36: =ABC_XYZ_Classification!C33 -> Packaging Materials | D36: =INDEX(Raw_SKU_Master!$I$2:$I$41,MATCH(A36,Raw_SKU_Master!$A$2:$A$41,0)) -> 19 | E36: =INDEX(Raw_SKU_Master!$E$2:$E$41,MATCH(A36,Raw_SKU_Master!$A$2:$A$41,0)) -> 0.84 | F36: =ABC_XYZ_Classification!E33/(Assumptions!$C$18*7) -> 24.967033 | G36: =ABC_XYZ_Classification!J33 -> 27.282437 | H36: =D36/7 -> 2.7142857 | I36: =ROUNDUP(Assumptions!$C$6*G36*SQRT(H36),0) -> 75 | J36: =ROUNDUP(F36*D36+I36,0) -> 550 | K36: =ABC_XYZ_Classification!E33 -> 9088 | L36: =ROUND(SQRT((2*K36*Assumptions!$C$7)/(E36*Assumptions!$C$8)),0) -> 2716 | M36: =ROUNDUP(L36/Assumptions!$C$9,0)*Assumptions!$C$9 -> 2725 | N36: =AVERAGEIF(Raw_Inventory_Monthly!$A$2:$A$481,A36,Raw_Inventory_Monthly!$C$2:$C$481) -> 632 | O36: =AVERAGEIF(Raw_Inventory_Monthly!$A$2:$A$481,A36,Raw_Inventory_Monthly!$G$2:$G$481) -> 141.33333 | P36: =IFERROR(N36/F36,0) -> 25.31338 | Q36: =IFERROR((N36+O36)/F36,0) -> 30.974178 | R36: =IF(Q36<Assumptions!$C$16*D36,"Stockout Risk",IF(Q36>Assumptions!$C$17*D36,"Overstock","Healthy")) -> Healthy | S36: =ROUND(FORECAST(MAX(Raw_Sales_Weekly!$E$1586:$E$1637)+1,Raw_Sales_Weekly!$C$1586:$C$1637,Raw_Sales_Weekly!$E$1586:$E$1637),0) -> 158 | T36: =ABC_XYZ_Classification!L33 -> X | U36: =ABC_XYZ_Classification!H33 -> C | V36: =IF(AND(P36>$F$5,T36="Z"),"Yes","No") -> No | W36: =N36*E36 -> 530.88 | X36: =IF(V36="Yes",COUNTIF($V$9:V36,"Yes"),"")
A37: MM-1028 | B37: =ABC_XYZ_Classification!B34 -> Pneumatic Components Item 04 - Pneumatic Components | C37: =ABC_XYZ_Classification!C34 -> Pneumatic Components | D37: =INDEX(Raw_SKU_Master!$I$2:$I$41,MATCH(A37,Raw_SKU_Master!$A$2:$A$41,0)) -> 46 | E37: =INDEX(Raw_SKU_Master!$E$2:$E$41,MATCH(A37,Raw_SKU_Master!$A$2:$A$41,0)) -> 6.69 | F37: =ABC_XYZ_Classification!E34/(Assumptions!$C$18*7) -> 3.4368132 | G37: =ABC_XYZ_Classification!J34 -> 44.761004 | H37: =D37/7 -> 6.5714286 | I37: =ROUNDUP(Assumptions!$C$6*G37*SQRT(H37),0) -> 190 | J37: =ROUNDUP(F37*D37+I37,0) -> 349 | K37: =ABC_XYZ_Classification!E34 -> 1251 | L37: =ROUND(SQRT((2*K37*Assumptions!$C$7)/(E37*Assumptions!$C$8)),0) -> 357 | M37: =ROUNDUP(L37/Assumptions!$C$9,0)*Assumptions!$C$9 -> 375 | N37: =AVERAGEIF(Raw_Inventory_Monthly!$A$2:$A$481,A37,Raw_Inventory_Monthly!$C$2:$C$481) -> 460.25 | O37: =AVERAGEIF(Raw_Inventory_Monthly!$A$2:$A$481,A37,Raw_Inventory_Monthly!$G$2:$G$481) -> 63 | P37: =IFERROR(N37/F37,0) -> 133.91767 | Q37: =IFERROR((N37+O37)/F37,0) -> 152.2486 | R37: =IF(Q37<Assumptions!$C$16*D37,"Stockout Risk",IF(Q37>Assumptions!$C$17*D37,"Overstock","Healthy")) -> Overstock | S37: =ROUND(FORECAST(MAX(Raw_Sales_Weekly!$E$1305:$E$1324)+1,Raw_Sales_Weekly!$C$1305:$C$1324,Raw_Sales_Weekly!$E$1305:$E$1324),0) -> 54 | T37: =ABC_XYZ_Classification!L34 -> Z | U37: =ABC_XYZ_Classification!H34 -> C | V37: =IF(AND(P37>$F$5,T37="Z"),"Yes","No") -> Yes | W37: =N37*E37 -> 3079.0725 | X37: =IF(V37="Yes",COUNTIF($V$9:V37,"Yes"),"") -> 3
A38: MM-1036 | B38: =ABC_XYZ_Classification!B35 -> Packaging Materials Item 02 - Packaging Materials | C38: =ABC_XYZ_Classification!C35 -> Packaging Materials | D38: =INDEX(Raw_SKU_Master!$I$2:$I$41,MATCH(A38,Raw_SKU_Master!$A$2:$A$41,0)) -> 34 | E38: =INDEX(Raw_SKU_Master!$E$2:$E$41,MATCH(A38,Raw_SKU_Master!$A$2:$A$41,0)) -> 1.2 | F38: =ABC_XYZ_Classification!E35/(Assumptions!$C$18*7) -> 12.585165 | G38: =ABC_XYZ_Classification!J35 -> 23.778836 | H38: =D38/7 -> 4.8571429 | I38: =ROUNDUP(Assumptions!$C$6*G38*SQRT(H38),0) -> 87 | J38: =ROUNDUP(F38*D38+I38,0) -> 515 | K38: =ABC_XYZ_Classification!E35 -> 4581 | L38: =ROUND(SQRT((2*K38*Assumptions!$C$7)/(E38*Assumptions!$C$8)),0) -> 1613 | M38: =ROUNDUP(L38/Assumptions!$C$9,0)*Assumptions!$C$9 -> 1625 | N38: =AVERAGEIF(Raw_Inventory_Monthly!$A$2:$A$481,A38,Raw_Inventory_Monthly!$C$2:$C$481) -> 216.41667 | O38: =AVERAGEIF(Raw_Inventory_Monthly!$A$2:$A$481,A38,Raw_Inventory_Monthly!$G$2:$G$481) -> 72 | P38: =IFERROR(N38/F38,0) -> 17.196173 | Q38: =IFERROR((N38+O38)/F38,0) -> 22.917194 | R38: =IF(Q38<Assumptions!$C$16*D38,"Stockout Risk",IF(Q38>Assumptions!$C$17*D38,"Overstock","Healthy")) -> Stockout Risk | S38: =ROUND(FORECAST(MAX(Raw_Sales_Weekly!$E$1638:$E$1689)+1,Raw_Sales_Weekly!$C$1638:$C$1689,Raw_Sales_Weekly!$E$1638:$E$1689),0) -> 72 | T38: =ABC_XYZ_Classification!L35 -> X | U38: =ABC_XYZ_Classification!H35 -> C | V38: =IF(AND(P38>$F$5,T38="Z"),"Yes","No") -> No | W38: =N38*E38 -> 259.7 | X38: =IF(V38="Yes",COUNTIF($V$9:V38,"Yes"),"")
A39: MM-1039 | B39: =ABC_XYZ_Classification!B36 -> Packaging Materials Item 05 - Packaging Materials | C39: =ABC_XYZ_Classification!C36 -> Packaging Materials | D39: =INDEX(Raw_SKU_Master!$I$2:$I$41,MATCH(A39,Raw_SKU_Master!$A$2:$A$41,0)) -> 16 | E39: =INDEX(Raw_SKU_Master!$E$2:$E$41,MATCH(A39,Raw_SKU_Master!$A$2:$A$41,0)) -> 0.96 | F39: =ABC_XYZ_Classification!E36/(Assumptions!$C$18*7) -> 15.384615 | G39: =ABC_XYZ_Classification!J36 -> 14.53317 | H39: =D39/7 -> 2.2857143 | I39: =ROUNDUP(Assumptions!$C$6*G39*SQRT(H39),0) -> 37 | J39: =ROUNDUP(F39*D39+I39,0) -> 284 | K39: =ABC_XYZ_Classification!E36 -> 5600 | L39: =ROUND(SQRT((2*K39*Assumptions!$C$7)/(E39*Assumptions!$C$8)),0) -> 1994 | M39: =ROUNDUP(L39/Assumptions!$C$9,0)*Assumptions!$C$9 -> 2000 | N39: =AVERAGEIF(Raw_Inventory_Monthly!$A$2:$A$481,A39,Raw_Inventory_Monthly!$C$2:$C$481) -> 410.58333 | O39: =AVERAGEIF(Raw_Inventory_Monthly!$A$2:$A$481,A39,Raw_Inventory_Monthly!$G$2:$G$481) -> 97.416667 | P39: =IFERROR(N39/F39,0) -> 26.687917 | Q39: =IFERROR((N39+O39)/F39,0) -> 33.02 | R39: =IF(Q39<Assumptions!$C$16*D39,"Stockout Risk",IF(Q39>Assumptions!$C$17*D39,"Overstock","Healthy")) -> Healthy | S39: =ROUND(FORECAST(MAX(Raw_Sales_Weekly!$E$1755:$E$1806)+1,Raw_Sales_Weekly!$C$1755:$C$1806,Raw_Sales_Weekly!$E$1755:$E$1806),0) -> 114 | T39: =ABC_XYZ_Classification!L36 -> X | U39: =ABC_XYZ_Classification!H36 -> C | V39: =IF(AND(P39>$F$5,T39="Z"),"Yes","No") -> No | W39: =N39*E39 -> 394.16 | X39: =IF(V39="Yes",COUNTIF($V$9:V39,"Yes"),"")
A40: MM-1038 | B40: =ABC_XYZ_Classification!B37 -> Packaging Materials Item 04 - Packaging Materials | C40: =ABC_XYZ_Classification!C37 -> Packaging Materials | D40: =INDEX(Raw_SKU_Master!$I$2:$I$41,MATCH(A40,Raw_SKU_Master!$A$2:$A$41,0)) -> 17 | E40: =INDEX(Raw_SKU_Master!$E$2:$E$41,MATCH(A40,Raw_SKU_Master!$A$2:$A$41,0)) -> 0.53 | F40: =ABC_XYZ_Classification!E37/(Assumptions!$C$18*7) -> 30.063187 | G40: =ABC_XYZ_Classification!J37 -> 36.837697 | H40: =D40/7 -> 2.4285714 | I40: =ROUNDUP(Assumptions!$C$6*G40*SQRT(H40),0) -> 95 | J40: =ROUNDUP(F40*D40+I40,0) -> 607 | K40: =ABC_XYZ_Classification!E37 -> 10943 | L40: =ROUND(SQRT((2*K40*Assumptions!$C$7)/(E40*Assumptions!$C$8)),0) -> 3752 | M40: =ROUNDUP(L40/Assumptions!$C$9,0)*Assumptions!$C$9 -> 3775 | N40: =AVERAGEIF(Raw_Inventory_Monthly!$A$2:$A$481,A40,Raw_Inventory_Monthly!$C$2:$C$481) -> 826.83333 | O40: =AVERAGEIF(Raw_Inventory_Monthly!$A$2:$A$481,A40,Raw_Inventory_Monthly!$G$2:$G$481) -> 180.5 | P40: =IFERROR(N40/F40,0) -> 27.503183 | Q40: =IFERROR((N40+O40)/F40,0) -> 33.507204 | R40: =IF(Q40<Assumptions!$C$16*D40,"Stockout Risk",IF(Q40>Assumptions!$C$17*D40,"Overstock","Healthy")) -> Healthy | S40: =ROUND(FORECAST(MAX(Raw_Sales_Weekly!$E$1703:$E$1754)+1,Raw_Sales_Weekly!$C$1703:$C$1754,Raw_Sales_Weekly!$E$1703:$E$1754),0) -> 233 | T40: =ABC_XYZ_Classification!L37 -> X | U40: =ABC_XYZ_Classification!H37 -> C | V40: =IF(AND(P40>$F$5,T40="Z"),"Yes","No") -> No | W40: =N40*E40 -> 438.22167 | X40: =IF(V40="Yes",COUNTIF($V$9:V40,"Yes"),"")
A41: MM-1022 | B41: =ABC_XYZ_Classification!B38 -> Seals Item 03 - Seals & Gaskets | C41: =ABC_XYZ_Classification!C38 -> Seals & Gaskets | D41: =INDEX(Raw_SKU_Master!$I$2:$I$41,MATCH(A41,Raw_SKU_Master!$A$2:$A$41,0)) -> 50 | E41: =INDEX(Raw_SKU_Master!$E$2:$E$41,MATCH(A41,Raw_SKU_Master!$A$2:$A$41,0)) -> 1.41 | F41: =ABC_XYZ_Classification!E38/(Assumptions!$C$18*7) -> 13.368132 | G41: =ABC_XYZ_Classification!J38 -> 21.024113 | H41: =D41/7 -> 7.1428571 | I41: =ROUNDUP(Assumptions!$C$6*G41*SQRT(H41),0) -> 93 | J41: =ROUNDUP(F41*D41+I41,0) -> 762 | K41: =ABC_XYZ_Classification!E38 -> 4866 | L41: =ROUND(SQRT((2*K41*Assumptions!$C$7)/(E41*Assumptions!$C$8)),0) -> 1534 | M41: =ROUNDUP(L41/Assumptions!$C$9,0)*Assumptions!$C$9 -> 1550 | N41: =AVERAGEIF(Raw_Inventory_Monthly!$A$2:$A$481,A41,Raw_Inventory_Monthly!$C$2:$C$481) -> 181.41667 | O41: =AVERAGEIF(Raw_Inventory_Monthly!$A$2:$A$481,A41,Raw_Inventory_Monthly!$G$2:$G$481) -> 57.416667 | P41: =IFERROR(N41/F41,0) -> 13.570832 | Q41: =IFERROR((N41+O41)/F41,0) -> 17.865872 | R41: =IF(Q41<Assumptions!$C$16*D41,"Stockout Risk",IF(Q41>Assumptions!$C$17*D41,"Overstock","Healthy")) -> Stockout Risk | S41: =ROUND(FORECAST(MAX(Raw_Sales_Weekly!$E$996:$E$1047)+1,Raw_Sales_Weekly!$C$996:$C$1047,Raw_Sales_Weekly!$E$996:$E$1047),0) -> 86 | T41: =ABC_XYZ_Classification!L38 -> X | U41: =ABC_XYZ_Classification!H38 -> C | V41: =IF(AND(P41>$F$5,T41="Z"),"Yes","No") -> No | W41: =N41*E41 -> 255.7975 | X41: =IF(V41="Yes",COUNTIF($V$9:V41,"Yes"),"")
A42: MM-1006 | B42: =ABC_XYZ_Classification!B39 -> Bearings Item 02 - Bearings & Bushings | C42: =ABC_XYZ_Classification!C39 -> Bearings & Bushings | D42: =INDEX(Raw_SKU_Master!$I$2:$I$41,MATCH(A42,Raw_SKU_Master!$A$2:$A$41,0)) -> 126 | E42: =INDEX(Raw_SKU_Master!$E$2:$E$41,MATCH(A42,Raw_SKU_Master!$A$2:$A$41,0)) -> 3.9 | F42: =ABC_XYZ_Classification!E39/(Assumptions!$C$18*7) -> 4.4120879 | G42: =ABC_XYZ_Classification!J39 -> 47.16821 | H42: =D42/7 -> 18 | I42: =ROUNDUP(Assumptions!$C$6*G42*SQRT(H42),0) -> 331 | J42: =ROUNDUP(F42*D42+I42,0) -> 887 | K42: =ABC_XYZ_Classification!E39 -> 1606 | L42: =ROUND(SQRT((2*K42*Assumptions!$C$7)/(E42*Assumptions!$C$8)),0) -> 530 | M42: =ROUNDUP(L42/Assumptions!$C$9,0)*Assumptions!$C$9 -> 550 | N42: =AVERAGEIF(Raw_Inventory_Monthly!$A$2:$A$481,A42,Raw_Inventory_Monthly!$C$2:$C$481) -> 736 | O42: =AVERAGEIF(Raw_Inventory_Monthly!$A$2:$A$481,A42,Raw_Inventory_Monthly!$G$2:$G$481) -> 179.33333 | P42: =IFERROR(N42/F42,0) -> 166.81445 | Q42: =IFERROR((N42+O42)/F42,0) -> 207.46036 | R42: =IF(Q42<Assumptions!$C$16*D42,"Stockout Risk",IF(Q42>Assumptions!$C$17*D42,"Overstock","Healthy")) -> Healthy | S42: =ROUND(FORECAST(MAX(Raw_Sales_Weekly!$E$274:$E$283)+1,Raw_Sales_Weekly!$C$274:$C$283,Raw_Sales_Weekly!$E$274:$E$283),0) -> 177 | T42: =ABC_XYZ_Classification!L39 -> X | U42: =ABC_XYZ_Classification!H39 -> C | V42: =IF(AND(P42>$F$5,T42="Z"),"Yes","No") -> No | W42: =N42*E42 -> 2870.4 | X42: =IF(V42="Yes",COUNTIF($V$9:V42,"Yes"),"")
A43: MM-1003 | B43: =ABC_XYZ_Classification!B40 -> Fasteners Item 04 - Fasteners & Hardware | C43: =ABC_XYZ_Classification!C40 -> Fasteners & Hardware | D43: =INDEX(Raw_SKU_Master!$I$2:$I$41,MATCH(A43,Raw_SKU_Master!$A$2:$A$41,0)) -> 52 | E43: =INDEX(Raw_SKU_Master!$E$2:$E$41,MATCH(A43,Raw_SKU_Master!$A$2:$A$41,0)) -> 2.56 | F43: =ABC_XYZ_Classification!E40/(Assumptions!$C$18*7) -> 5.4285714 | G43: =ABC_XYZ_Classification!J40 -> 116.86341 | H43: =D43/7 -> 7.4285714 | I43: =ROUNDUP(Assumptions!$C$6*G43*SQRT(H43),0) -> 526 | J43: =ROUNDUP(F43*D43+I43,0) -> 809 | K43: =ABC_XYZ_Classification!E40 -> 1976 | L43: =ROUND(SQRT((2*K43*Assumptions!$C$7)/(E43*Assumptions!$C$8)),0) -> 725 | M43: =ROUNDUP(L43/Assumptions!$C$9,0)*Assumptions!$C$9 -> 725 | N43: =AVERAGEIF(Raw_Inventory_Monthly!$A$2:$A$481,A43,Raw_Inventory_Monthly!$C$2:$C$481) -> 1905.75 | O43: =AVERAGEIF(Raw_Inventory_Monthly!$A$2:$A$481,A43,Raw_Inventory_Monthly!$G$2:$G$481) -> 136.41667 | P43: =IFERROR(N43/F43,0) -> 351.05921 | Q43: =IFERROR((N43+O43)/F43,0) -> 376.1886 | R43: =IF(Q43<Assumptions!$C$16*D43,"Stockout Risk",IF(Q43>Assumptions!$C$17*D43,"Overstock","Healthy")) -> Overstock | S43: =ROUND(FORECAST(MAX(Raw_Sales_Weekly!$E$158:$E$169)+1,Raw_Sales_Weekly!$C$158:$C$169,Raw_Sales_Weekly!$E$158:$E$169),0) -> 77 | T43: =ABC_XYZ_Classification!L40 -> Z | U43: =ABC_XYZ_Classification!H40 -> C | V43: =IF(AND(P43>$F$5,T43="Z"),"Yes","No") -> Yes | W43: =N43*E43 -> 4878.72 | X43: =IF(V43="Yes",COUNTIF($V$9:V43,"Yes"),"") -> 4
A44: MM-1024 | B44: =ABC_XYZ_Classification!B41 -> Seals Item 05 - Seals & Gaskets | C44: =ABC_XYZ_Classification!C41 -> Seals & Gaskets | D44: =INDEX(Raw_SKU_Master!$I$2:$I$41,MATCH(A44,Raw_SKU_Master!$A$2:$A$41,0)) -> 34 | E44: =INDEX(Raw_SKU_Master!$E$2:$E$41,MATCH(A44,Raw_SKU_Master!$A$2:$A$41,0)) -> 1.42 | F44: =ABC_XYZ_Classification!E41/(Assumptions!$C$18*7) -> 10.489011 | G44: =ABC_XYZ_Classification!J41 -> 23.718174 | H44: =D44/7 -> 4.8571429 | I44: =ROUNDUP(Assumptions!$C$6*G44*SQRT(H44),0) -> 87 | J44: =ROUNDUP(F44*D44+I44,0) -> 444 | K44: =ABC_XYZ_Classification!E41 -> 3818 | L44: =ROUND(SQRT((2*K44*Assumptions!$C$7)/(E44*Assumptions!$C$8)),0) -> 1354 | M44: =ROUNDUP(L44/Assumptions!$C$9,0)*Assumptions!$C$9 -> 1375 | N44: =AVERAGEIF(Raw_Inventory_Monthly!$A$2:$A$481,A44,Raw_Inventory_Monthly!$C$2:$C$481) -> 262.33333 | O44: =AVERAGEIF(Raw_Inventory_Monthly!$A$2:$A$481,A44,Raw_Inventory_Monthly!$G$2:$G$481) -> 75.75 | P44: =IFERROR(N44/F44,0) -> 25.010302 | Q44: =IFERROR((N44+O44)/F44,0) -> 32.232146 | R44: =IF(Q44<Assumptions!$C$16*D44,"Stockout Risk",IF(Q44>Assumptions!$C$17*D44,"Overstock","Healthy")) -> Stockout Risk | S44: =ROUND(FORECAST(MAX(Raw_Sales_Weekly!$E$1100:$E$1151)+1,Raw_Sales_Weekly!$C$1100:$C$1151,Raw_Sales_Weekly!$E$1100:$E$1151),0) -> 52 | T44: =ABC_XYZ_Classification!L41 -> Y | U44: =ABC_XYZ_Classification!H41 -> C | V44: =IF(AND(P44>$F$5,T44="Z"),"Yes","No") -> No | W44: =N44*E44 -> 372.51333 | X44: =IF(V44="Yes",COUNTIF($V$9:V44,"Yes"),"")
A45: MM-1031 | B45: =ABC_XYZ_Classification!B42 -> Raw Material Item 02 - Raw Material - Metal Stock | C45: =ABC_XYZ_Classification!C42 -> Raw Material - Metal Stock | D45: =INDEX(Raw_SKU_Master!$I$2:$I$41,MATCH(A45,Raw_SKU_Master!$A$2:$A$41,0)) -> 68 | E45: =INDEX(Raw_SKU_Master!$E$2:$E$41,MATCH(A45,Raw_SKU_Master!$A$2:$A$41,0)) -> 19.22 | F45: =ABC_XYZ_Classification!E42/(Assumptions!$C$18*7) -> 0.79945055 | G45: =ABC_XYZ_Classification!J42 -> 7.5206383 | H45: =D45/7 -> 9.7142857 | I45: =ROUNDUP(Assumptions!$C$6*G45*SQRT(H45),0) -> 39 | J45: =ROUNDUP(F45*D45+I45,0) -> 94 | K45: =ABC_XYZ_Classification!E42 -> 291 | L45: =ROUND(SQRT((2*K45*Assumptions!$C$7)/(E45*Assumptions!$C$8)),0) -> 102 | M45: =ROUNDUP(L45/Assumptions!$C$9,0)*Assumptions!$C$9 -> 125 | N45: =AVERAGEIF(Raw_Inventory_Monthly!$A$2:$A$481,A45,Raw_Inventory_Monthly!$C$2:$C$481) -> 121.08333 | O45: =AVERAGEIF(Raw_Inventory_Monthly!$A$2:$A$481,A45,Raw_Inventory_Monthly!$G$2:$G$481) -> 72.25 | P45: =IFERROR(N45/F45,0) -> 151.45819 | Q45: =IFERROR((N45+O45)/F45,0) -> 241.83276 | R45: =IF(Q45<Assumptions!$C$16*D45,"Stockout Risk",IF(Q45>Assumptions!$C$17*D45,"Overstock","Healthy")) -> Overstock | S45: =ROUND(FORECAST(MAX(Raw_Sales_Weekly!$E$1428:$E$1432)+1,Raw_Sales_Weekly!$C$1428:$C$1432,Raw_Sales_Weekly!$E$1428:$E$1432),0) -> 52 | T45: =ABC_XYZ_Classification!L42 -> X | U45: =ABC_XYZ_Classification!H42 -> C | V45: =IF(AND(P45>$F$5,T45="Z"),"Yes","No") -> No | W45: =N45*E45 -> 2327.2217 | X45: =IF(V45="Yes",COUNTIF($V$9:V45,"Yes"),"")
A46: MM-1023 | B46: =ABC_XYZ_Classification!B43 -> Seals Item 04 - Seals & Gaskets | C46: =ABC_XYZ_Classification!C43 -> Seals & Gaskets | D46: =INDEX(Raw_SKU_Master!$I$2:$I$41,MATCH(A46,Raw_SKU_Master!$A$2:$A$41,0)) -> 53 | E46: =INDEX(Raw_SKU_Master!$E$2:$E$41,MATCH(A46,Raw_SKU_Master!$A$2:$A$41,0)) -> 0.97 | F46: =ABC_XYZ_Classification!E43/(Assumptions!$C$18*7) -> 12.049451 | G46: =ABC_XYZ_Classification!J43 -> 15.722209 | H46: =D46/7 -> 7.5714286 | I46: =ROUNDUP(Assumptions!$C$6*G46*SQRT(H46),0) -> 72 | J46: =ROUNDUP(F46*D46+I46,0) -> 711 | K46: =ABC_XYZ_Classification!E43 -> 4386 | L46: =ROUND(SQRT((2*K46*Assumptions!$C$7)/(E46*Assumptions!$C$8)),0) -> 1756 | M46: =ROUNDUP(L46/Assumptions!$C$9,0)*Assumptions!$C$9 -> 1775 | N46: =AVERAGEIF(Raw_Inventory_Monthly!$A$2:$A$481,A46,Raw_Inventory_Monthly!$C$2:$C$481) -> 315.58333 | O46: =AVERAGEIF(Raw_Inventory_Monthly!$A$2:$A$481,A46,Raw_Inventory_Monthly!$G$2:$G$481) -> 93 | P46: =IFERROR(N46/F46,0) -> 26.190682 | Q46: =IFERROR((N46+O46)/F46,0) -> 33.908877 | R46: =IF(Q46<Assumptions!$C$16*D46,"Stockout Risk",IF(Q46>Assumptions!$C$17*D46,"Overstock","Healthy")) -> Stockout Risk | S46: =ROUND(FORECAST(MAX(Raw_Sales_Weekly!$E$1048:$E$1099)+1,Raw_Sales_Weekly!$C$1048:$C$1099,Raw_Sales_Weekly!$E$1048:$E$1099),0) -> 89 | T46: =ABC_XYZ_Classification!L43 -> X | U46: =ABC_XYZ_Classification!H43 -> C | V46: =IF(AND(P46>$F$5,T46="Z"),"Yes","No") -> No | W46: =N46*E46 -> 306.11583 | X46: =IF(V46="Yes",COUNTIF($V$9:V46,"Yes"),"")
A47: MM-1021 | B47: =ABC_XYZ_Classification!B44 -> Seals Item 02 - Seals & Gaskets | C47: =ABC_XYZ_Classification!C44 -> Seals & Gaskets | D47: =INDEX(Raw_SKU_Master!$I$2:$I$41,MATCH(A47,Raw_SKU_Master!$A$2:$A$41,0)) -> 36 | E47: =INDEX(Raw_SKU_Master!$E$2:$E$41,MATCH(A47,Raw_SKU_Master!$A$2:$A$41,0)) -> 0.94 | F47: =ABC_XYZ_Classification!E44/(Assumptions!$C$18*7) -> 9.5659341 | G47: =ABC_XYZ_Classification!J44 -> 14.462101 | H47: =D47/7 -> 5.1428571 | I47: =ROUNDUP(Assumptions!$C$6*G47*SQRT(H47),0) -> 55 | J47: =ROUNDUP(F47*D47+I47,0) -> 400 | K47: =ABC_XYZ_Classification!E44 -> 3482 | L47: =ROUND(SQRT((2*K47*Assumptions!$C$7)/(E47*Assumptions!$C$8)),0) -> 1589 | M47: =ROUNDUP(L47/Assumptions!$C$9,0)*Assumptions!$C$9 -> 1600 | N47: =AVERAGEIF(Raw_Inventory_Monthly!$A$2:$A$481,A47,Raw_Inventory_Monthly!$C$2:$C$481) -> 236.16667 | O47: =AVERAGEIF(Raw_Inventory_Monthly!$A$2:$A$481,A47,Raw_Inventory_Monthly!$G$2:$G$481) -> 58.666667 | P47: =IFERROR(N47/F47,0) -> 24.688302 | Q47: =IFERROR((N47+O47)/F47,0) -> 30.821176 | R47: =IF(Q47<Assumptions!$C$16*D47,"Stockout Risk",IF(Q47>Assumptions!$C$17*D47,"Overstock","Healthy")) -> Stockout Risk | S47: =ROUND(FORECAST(MAX(Raw_Sales_Weekly!$E$944:$E$995)+1,Raw_Sales_Weekly!$C$944:$C$995,Raw_Sales_Weekly!$E$944:$E$995),0) -> 73 | T47: =ABC_XYZ_Classification!L44 -> X | U47: =ABC_XYZ_Classification!H44 -> C | V47: =IF(AND(P47>$F$5,T47="Z"),"Yes","No") -> No | W47: =N47*E47 -> 221.99667 | X47: =IF(V47="Yes",COUNTIF($V$9:V47,"Yes"),"")
A48: MM-1037 | B48: =ABC_XYZ_Classification!B45 -> Packaging Materials Item 03 - Packaging Materials | C48: =ABC_XYZ_Classification!C45 -> Packaging Materials | D48: =INDEX(Raw_SKU_Master!$I$2:$I$41,MATCH(A48,Raw_SKU_Master!$A$2:$A$41,0)) -> 23 | E48: =INDEX(Raw_SKU_Master!$E$2:$E$41,MATCH(A48,Raw_SKU_Master!$A$2:$A$41,0)) -> 0.78 | F48: =ABC_XYZ_Classification!E45/(Assumptions!$C$18*7) -> 3.2115385 | G48: =ABC_XYZ_Classification!J45 -> 7.7604673 | H48: =D48/7 -> 3.2857143 | I48: =ROUNDUP(Assumptions!$C$6*G48*SQRT(H48),0) -> 24 | J48: =ROUNDUP(F48*D48+I48,0) -> 98 | K48: =ABC_XYZ_Classification!E45 -> 1169 | L48: =ROUND(SQRT((2*K48*Assumptions!$C$7)/(E48*Assumptions!$C$8)),0) -> 1011 | M48: =ROUNDUP(L48/Assumptions!$C$9,0)*Assumptions!$C$9 -> 1025 | N48: =AVERAGEIF(Raw_Inventory_Monthly!$A$2:$A$481,A48,Raw_Inventory_Monthly!$C$2:$C$481) -> 190 | O48: =AVERAGEIF(Raw_Inventory_Monthly!$A$2:$A$481,A48,Raw_Inventory_Monthly!$G$2:$G$481) -> 56.166667 | P48: =IFERROR(N48/F48,0) -> 59.161677 | Q48: =IFERROR((N48+O48)/F48,0) -> 76.650699 | R48: =IF(Q48<Assumptions!$C$16*D48,"Stockout Risk",IF(Q48>Assumptions!$C$17*D48,"Overstock","Healthy")) -> Overstock | S48: =ROUND(FORECAST(MAX(Raw_Sales_Weekly!$E$1690:$E$1702)+1,Raw_Sales_Weekly!$C$1690:$C$1702,Raw_Sales_Weekly!$E$1690:$E$1702),0) -> 91 | T48: =ABC_XYZ_Classification!L45 -> X | U48: =ABC_XYZ_Classification!H45 -> C | V48: =IF(AND(P48>$F$5,T48="Z"),"Yes","No") -> No | W48: =N48*E48 -> 148.2 | X48: =IF(V48="Yes",COUNTIF($V$9:V48,"Yes"),"")

Sheet Forecast_Detail
B2: Forecast Holdout Detail
B3: Most recent 6 weeks per SKU held out; each is forecast from FORECAST() over that SKU's prior weeks only (no leakage), then compared to what actually happened.
A5: SKU_ID | B5: Week_Index | C5: Actual_Qty | D5: Forecast_Qty | E5: APE | F5: Abs_Error
A6: MM-1033 | B6: =Raw_Sales_Weekly!E1528 -> 45 | C6: =Raw_Sales_Weekly!C1528 -> 123 | D6: =ROUND(FORECAST(B6,Raw_Sales_Weekly!$C$1484:$C$1527,Raw_Sales_Weekly!$E$1484:$E$1527),0) -> 176 | E6: =IFERROR(ABS((D6-C6)/C6),"") -> 0.43089431 | F6: =ABS(D6-C6) -> 53
A7: MM-1033 | B7: =Raw_Sales_Weekly!E1529 -> 46 | C7: =Raw_Sales_Weekly!C1529 -> 147 | D7: =ROUND(FORECAST(B7,Raw_Sales_Weekly!$C$1484:$C$1527,Raw_Sales_Weekly!$E$1484:$E$1527),0) -> 174 | E7: =IFERROR(ABS((D7-C7)/C7),"") -> 0.18367347 | F7: =ABS(D7-C7) -> 27
A8: MM-1033 | B8: =Raw_Sales_Weekly!E1530 -> 47 | C8: =Raw_Sales_Weekly!C1530 -> 235 | D8: =ROUND(FORECAST(B8,Raw_Sales_Weekly!$C$1484:$C$1527,Raw_Sales_Weekly!$E$1484:$E$1527),0) -> 172 | E8: =IFERROR(ABS((D8-C8)/C8),"") -> 0.26808511 | F8: =ABS(D8-C8) -> 63
A9: MM-1033 | B9: =Raw_Sales_Weekly!E1531 -> 48 | C9: =Raw_Sales_Weekly!C1531 -> 286 | D9: =ROUND(FORECAST(B9,Raw_Sales_Weekly!$C$1484:$C$1527,Raw_Sales_Weekly!$E$1484:$E$1527),0) -> 171 | E9: =IFERROR(ABS((D9-C9)/C9),"") -> 0.4020979 | F9: =ABS(D9-C9) -> 115
A10: MM-1033 | B10: =Raw_Sales_Weekly!E1532 -> 49 | C10: =Raw_Sales_Weekly!C1532 -> 275 | D10: =ROUND(FORECAST(B10,Raw_Sales_Weekly!$C$1484:$C$1527,Raw_Sales_Weekly!$E$1484:$E$1527),0) -> 169 | E10: =IFERROR(ABS((D10-C10)/C10),"") -> 0.38545455 | F10: =ABS(D10-C10) -> 106
A11: MM-1033 | B11: =Raw_Sales_Weekly!E1533 -> 50 | C11: =Raw_Sales_Weekly!C1533 -> 199 | D11: =ROUND(FORECAST(B11,Raw_Sales_Weekly!$C$1484:$C$1527,Raw_Sales_Weekly!$E$1484:$E$1527),0) -> 168 | E11: =IFERROR(ABS((D11-C11)/C11),"") -> 0.15577889 | F11: =ABS(D11-C11) -> 31
A12: MM-1032 | B12: =Raw_Sales_Weekly!E1478 -> 46 | C12: =Raw_Sales_Weekly!C1478 -> 140 | D12: =ROUND(FORECAST(B12,Raw_Sales_Weekly!$C$1433:$C$1477,Raw_Sales_Weekly!$E$1433:$E$1477),0) -> 164 | E12: =IFERROR(ABS((D12-C12)/C12),"") -> 0.17142857 | F12: =ABS(D12-C12) -> 24
A13: MM-1032 | B13: =Raw_Sales_Weekly!E1479 -> 47 | C13: =Raw_Sales_Weekly!C1479 -> 168 | D13: =ROUND(FORECAST(B13,Raw_Sales_Weekly!$C$1433:$C$1477,Raw_Sales_Weekly!$E$1433:$E$1477),0) -> 163 | E13: =IFERROR(ABS((D13-C13)/C13),"") -> 0.029761905 | F13: =ABS(D13-C13) -> 5
A14: MM-1032 | B14: =Raw_Sales_Weekly!E1480 -> 48 | C14: =Raw_Sales_Weekly!C1480 -> 120 | D14: =ROUND(FORECAST(B14,Raw_Sales_Weekly!$C$1433:$C$1477,Raw_Sales_Weekly!$E$1433:$E$1477),0) -> 163 | E14: =IFERROR(ABS((D14-C14)/C14),"") -> 0.35833333 | F14: =ABS(D14-C14) -> 43
A15: MM-1032 | B15: =Raw_Sales_Weekly!E1481 -> 49 | C15: =Raw_Sales_Weekly!C1481 -> 6 | D15: =ROUND(FORECAST(B15,Raw_Sales_Weekly!$C$1433:$C$1477,Raw_Sales_Weekly!$E$1433:$E$1477),0) -> 163 | E15: =IFERROR(ABS((D15-C15)/C15),"") -> 26.166667 | F15: =ABS(D15-C15) -> 157
A16: MM-1032 | B16: =Raw_Sales_Weekly!E1482 -> 50 | C16: =Raw_Sales_Weekly!C1482 -> 157 | D16: =ROUND(FORECAST(B16,Raw_Sales_Weekly!$C$1433:$C$1477,Raw_Sales_Weekly!$E$1433:$E$1477),0) -> 163 | E16: =IFERROR(ABS((D16-C16)/C16),"") -> 0.038216561 | F16: =ABS(D16-C16) -> 6
A17: MM-1032 | B17: =Raw_Sales_Weekly!E1483 -> 51 | C17: =Raw_Sales_Weekly!C1483 -> 234 | D17: =ROUND(FORECAST(B17,Raw_Sales_Weekly!$C$1433:$C$1477,Raw_Sales_Weekly!$E$1433:$E$1477),0) -> 163 | E17: =IFERROR(ABS((D17-C17)/C17),"") -> 0.3034188 | F17: =ABS(D17-C17) -> 71
A18: MM-1025 | B18: =Raw_Sales_Weekly!E1196 -> 45 | C18: =Raw_Sales_Weekly!C1196 -> 212 | D18: =ROUND(FORECAST(B18,Raw_Sales_Weekly!$C$1152:$C$1195,Raw_Sales_Weekly!$E$1152:$E$1195),0) -> 138 | E18: =IFERROR(ABS((D18-C18)/C18),"") -> 0.3490566 | F18: =ABS(D18-C18) -> 74
A19: MM-1025 | B19: =Raw_Sales_Weekly!E1197 -> 46 | C19: =Raw_Sales_Weekly!C1197 -> 0 | D19: =ROUND(FORECAST(B19,Raw_Sales_Weekly!$C$1152:$C$1195,Raw_Sales_Weekly!$E$1152:$E$1195),0) -> 137 | E19: =IFERROR(ABS((D19-C19)/C19),"") | F19: =ABS(D19-C19) -> 137
A20: MM-1025 | B20: =Raw_Sales_Weekly!E1198 -> 47 | C20: =Raw_Sales_Weekly!C1198 -> 88 | D20: =ROUND(FORECAST(B20,Raw_Sales_Weekly!$C$1152:$C$1195,Raw_Sales_Weekly!$E$1152:$E$1195),0) -> 135 | E20: =IFERROR(ABS((D20-C20)/C20),"") -> 0.53409091 | F20: =ABS(D20-C20) -> 47
A21: MM-1025 | B21: =Raw_Sales_Weekly!E1199 -> 48 | C21: =Raw_Sales_Weekly!C1199 -> 216 | D21: =ROUND(FORECAST(B21,Raw_Sales_Weekly!$C$1152:$C$1195,Raw_Sales_Weekly!$E$1152:$E$1195),0) -> 134 | E21: =IFERROR(ABS((D21-C21)/C21),"") -> 0.37962963 | F21: =ABS(D21-C21) -> 82
A22: MM-1025 | B22: =Raw_Sales_Weekly!E1200 -> 49 | C22: =Raw_Sales_Weekly!C1200 -> 235 | D22: =ROUND(FORECAST(B22,Raw_Sales_Weekly!$C$1152:$C$1195,Raw_Sales_Weekly!$E$1152:$E$1195),0) -> 133 | E22: =IFERROR(ABS((D22-C22)/C22),"") -> 0.43404255 | F22: =ABS(D22-C22) -> 102
A23: MM-1025 | B23: =Raw_Sales_Weekly!E1201 -> 50 | C23: =Raw_Sales_Weekly!C1201 -> 125 | D23: =ROUND(FORECAST(B23,Raw_Sales_Weekly!$C$1152:$C$1195,Raw_Sales_Weekly!$E$1152:$E$1195),0) -> 131 | E23: =IFERROR(ABS((D23-C23)/C23),"") -> 0.048 | F23: =ABS(D23-C23) -> 6
A24: MM-1030 | B24: =Raw_Sales_Weekly!E1422 -> 46 | C24: =Raw_Sales_Weekly!C1422 -> 82 | D24: =ROUND(FORECAST(B24,Raw_Sales_Weekly!$C$1377:$C$1421,Raw_Sales_Weekly!$E$1377:$E$1421),0) -> 107 | E24: =IFERROR(ABS((D24-C24)/C24),"") -> 0.30487805 | F24: =ABS(D24-C24) -> 25
A25: MM-1030 | B25: =Raw_Sales_Weekly!E1423 -> 47 | C25: =Raw_Sales_Weekly!C1423 -> 93 | D25: =ROUND(FORECAST(B25,Raw_Sales_Weekly!$C$1377:$C$1421,Raw_Sales_Weekly!$E$1377:$E$1421),0) -> 108 | E25: =IFERROR(ABS((D25-C25)/C25),"") -> 0.16129032 | F25: =ABS(D25-C25) -> 15
A26: MM-1030 | B26: =Raw_Sales_Weekly!E1424 -> 48 | C26: =Raw_Sales_Weekly!C1424 -> 33 | D26: =ROUND(FORECAST(B26,Raw_Sales_Weekly!$C$1377:$C$1421,Raw_Sales_Weekly!$E$1377:$E$1421),0) -> 109 | E26: =IFERROR(ABS((D26-C26)/C26),"") -> 2.3030303 | F26: =ABS(D26-C26) -> 76
A27: MM-1030 | B27: =Raw_Sales_Weekly!E1425 -> 49 | C27: =Raw_Sales_Weekly!C1425 -> 119 | D27: =ROUND(FORECAST(B27,Raw_Sales_Weekly!$C$1377:$C$1421,Raw_Sales_Weekly!$E$1377:$E$1421),0) -> 110 | E27: =IFERROR(ABS((D27-C27)/C27),"") -> 0.075630252 | F27: =ABS(D27-C27) -> 9
A28: MM-1030 | B28: =Raw_Sales_Weekly!E1426 -> 50 | C28: =Raw_Sales_Weekly!C1426 -> 139 | D28: =ROUND(FORECAST(B28,Raw_Sales_Weekly!$C$1377:$C$1421,Raw_Sales_Weekly!$E$1377:$E$1421),0) -> 111 | E28: =IFERROR(ABS((D28-C28)/C28),"") -> 0.20143885 | F28: =ABS(D28-C28) -> 28
A29: MM-1030 | B29: =Raw_Sales_Weekly!E1427 -> 51 | C29: =Raw_Sales_Weekly!C1427 -> 7 | D29: =ROUND(FORECAST(B29,Raw_Sales_Weekly!$C$1377:$C$1421,Raw_Sales_Weekly!$E$1377:$E$1421),0) -> 112 | E29: =IFERROR(ABS((D29-C29)/C29),"") -> 15 | F29: =ABS(D29-C29) -> 105
A30: MM-1014 | B30: =Raw_Sales_Weekly!E661 -> 47 | C30: =Raw_Sales_Weekly!C661 -> 56 | D30: =ROUND(FORECAST(B30,Raw_Sales_Weekly!$C$615:$C$660,Raw_Sales_Weekly!$E$615:$E$660),0) -> 70 | E30: =IFERROR(ABS((D30-C30)/C30),"") -> 0.25 | F30: =ABS(D30-C30) -> 14
A31: MM-1014 | B31: =Raw_Sales_Weekly!E662 -> 48 | C31: =Raw_Sales_Weekly!C662 -> 67 | D31: =ROUND(FORECAST(B31,Raw_Sales_Weekly!$C$615:$C$660,Raw_Sales_Weekly!$E$615:$E$660),0) -> 70 | E31: =IFERROR(ABS((D31-C31)/C31),"") -> 0.044776119 | F31: =ABS(D31-C31) -> 3
A32: MM-1014 | B32: =Raw_Sales_Weekly!E663 -> 49 | C32: =Raw_Sales_Weekly!C663 -> 67 | D32: =ROUND(FORECAST(B32,Raw_Sales_Weekly!$C$615:$C$660,Raw_Sales_Weekly!$E$615:$E$660),0) -> 70 | E32: =IFERROR(ABS((D32-C32)/C32),"") -> 0.044776119 | F32: =ABS(D32-C32) -> 3
A33: MM-1014 | B33: =Raw_Sales_Weekly!E664 -> 50 | C33: =Raw_Sales_Weekly!C664 -> 65 | D33: =ROUND(FORECAST(B33,Raw_Sales_Weekly!$C$615:$C$660,Raw_Sales_Weekly!$E$615:$E$660),0) -> 70 | E33: =IFERROR(ABS((D33-C33)/C33),"") -> 0.076923077 | F33: =ABS(D33-C33) -> 5
A34: MM-1014 | B34: =Raw_Sales_Weekly!E665 -> 51 | C34: =Raw_Sales_Weekly!C665 -> 74 | D34: =ROUND(FORECAST(B34,Raw_Sales_Weekly!$C$615:$C$660,Raw_Sales_Weekly!$E$615:$E$660),0) -> 69 | E34: =IFERROR(ABS((D34-C34)/C34),"") -> 0.067567568 | F34: =ABS(D34-C34) -> 5
A35: MM-1014 | B35: =Raw_Sales_Weekly!E666 -> 52 | C35: =Raw_Sales_Weekly!C666 -> 69 | D35: =ROUND(FORECAST(B35,Raw_Sales_Weekly!$C$615:$C$660,Raw_Sales_Weekly!$E$615:$E$660),0) -> 69 | E35: =IFERROR(ABS((D35-C35)/C35),"") -> 0 | F35: =ABS(D35-C35) -> 0
A36: MM-1010 | B36: =Raw_Sales_Weekly!E486 -> 47 | C36: =Raw_Sales_Weekly!C486 -> 96 | D36: =ROUND(FORECAST(B36,Raw_Sales_Weekly!$C$440:$C$485,Raw_Sales_Weekly!$E$440:$E$485),0) -> 100 | E36: =IFERROR(ABS((D36-C36)/C36),"") -> 0.041666667 | F36: =ABS(D36-C36) -> 4
A37: MM-1010 | B37: =Raw_Sales_Weekly!E487 -> 48 | C37: =Raw_Sales_Weekly!C487 -> 93 | D37: =ROUND(FORECAST(B37,Raw_Sales_Weekly!$C$440:$C$485,Raw_Sales_Weekly!$E$440:$E$485),0) -> 100 | E37: =IFERROR(ABS((D37-C37)/C37),"") -> 0.075268817 | F37: =ABS(D37-C37) -> 7
A38: MM-1010 | B38: =Raw_Sales_Weekly!E488 -> 49 | C38: =Raw_Sales_Weekly!C488 -> 112 | D38: =ROUND(FORECAST(B38,Raw_Sales_Weekly!$C$440:$C$485,Raw_Sales_Weekly!$E$440:$E$485),0) -> 101 | E38: =IFERROR(ABS((D38-C38)/C38),"") -> 0.098214286 | F38: =ABS(D38-C38) -> 11
A39: MM-1010 | B39: =Raw_Sales_Weekly!E489 -> 50 | C39: =Raw_Sales_Weekly!C489 -> 94 | D39: =ROUND(FORECAST(B39,Raw_Sales_Weekly!$C$440:$C$485,Raw_Sales_Weekly!$E$440:$E$485),0) -> 101 | E39: =IFERROR(ABS((D39-C39)/C39),"") -> 0.074468085 | F39: =ABS(D39-C39) -> 7
A40: MM-1010 | B40: =Raw_Sales_Weekly!E490 -> 51 | C40: =Raw_Sales_Weekly!C490 -> 73 | D40: =ROUND(FORECAST(B40,Raw_Sales_Weekly!$C$440:$C$485,Raw_Sales_Weekly!$E$440:$E$485),0) -> 101 | E40: =IFERROR(ABS((D40-C40)/C40),"") -> 0.38356164 | F40: =ABS(D40-C40) -> 28
A41: MM-1010 | B41: =Raw_Sales_Weekly!E491 -> 52 | C41: =Raw_Sales_Weekly!C491 -> 111 | D41: =ROUND(FORECAST(B41,Raw_Sales_Weekly!$C$440:$C$485,Raw_Sales_Weekly!$E$440:$E$485),0) -> 101 | E41: =IFERROR(ABS((D41-C41)/C41),"") -> 0.09009009 | F41: =ABS(D41-C41) -> 10
A42: MM-1011 | B42: =Raw_Sales_Weekly!E507 -> 16 | C42: =Raw_Sales_Weekly!C507 -> 223 | D42: =ROUND(FORECAST(B42,Raw_Sales_Weekly!$C$492:$C$506,Raw_Sales_Weekly!$E$492:$E$506),0) -> 205 | E42: =IFERROR(ABS((D42-C42)/C42),"") -> 0.080717489 | F42: =ABS(D42-C42) -> 18
A43: MM-1011 | B43: =Raw_Sales_Weekly!E508 -> 17 | C43: =Raw_Sales_Weekly!C508 -> 184 | D43: =ROUND(FORECAST(B43,Raw_Sales_Weekly!$C$492:$C$506,Raw_Sales_Weekly!$E$492:$E$506),0) -> 204 | E43: =IFERROR(ABS((D43-C43)/C43),"") -> 0.10869565 | F43: =ABS(D43-C43) -> 20
A44: MM-1011 | B44: =Raw_Sales_Weekly!E509 -> 18 | C44: =Raw_Sales_Weekly!C509 -> 164 | D44: =ROUND(FORECAST(B44,Raw_Sales_Weekly!$C$492:$C$506,Raw_Sales_Weekly!$E$492:$E$506),0) -> 203 | E44: =IFERROR(ABS((D44-C44)/C44),"") -> 0.23780488 | F44: =ABS(D44-C44) -> 39
A45: MM-1011 | B45: =Raw_Sales_Weekly!E510 -> 19 | C45: =Raw_Sales_Weekly!C510 -> 231 | D45: =ROUND(FORECAST(B45,Raw_Sales_Weekly!$C$492:$C$506,Raw_Sales_Weekly!$E$492:$E$506),0) -> 202 | E45: =IFERROR(ABS((D45-C45)/C45),"") -> 0.12554113 | F45: =ABS(D45-C45) -> 29
A46: MM-1011 | B46: =Raw_Sales_Weekly!E511 -> 20 | C46: =Raw_Sales_Weekly!C511 -> 173 | D46: =ROUND(FORECAST(B46,Raw_Sales_Weekly!$C$492:$C$506,Raw_Sales_Weekly!$E$492:$E$506),0) -> 201 | E46: =IFERROR(ABS((D46-C46)/C46),"") -> 0.16184971 | F46: =ABS(D46-C46) -> 28
A47: MM-1011 | B47: =Raw_Sales_Weekly!E512 -> 21 | C47: =Raw_Sales_Weekly!C512 -> 240 | D47: =ROUND(FORECAST(B47,Raw_Sales_Weekly!$C$492:$C$506,Raw_Sales_Weekly!$E$492:$E$506),0) -> 200 | E47: =IFERROR(ABS((D47-C47)/C47),"") -> 0.16666667 | F47: =ABS(D47-C47) -> 40
A48: MM-1013 | B48: =Raw_Sales_Weekly!E609 -> 47 | C48: =Raw_Sales_Weekly!C609 -> 113 | D48: =ROUND(FORECAST(B48,Raw_Sales_Weekly!$C$563:$C$608,Raw_Sales_Weekly!$E$563:$E$608),0) -> 110 | E48: =IFERROR(ABS((D48-C48)/C48),"") -> 0.026548673 | F48: =ABS(D48-C48) -> 3
A49: MM-1013 | B49: =Raw_Sales_Weekly!E610 -> 48 | C49: =Raw_Sales_Weekly!C610 -> 93 | D49: =ROUND(FORECAST(B49,Raw_Sales_Weekly!$C$563:$C$608,Raw_Sales_Weekly!$E$563:$E$608),0) -> 110 | E49: =IFERROR(ABS((D49-C49)/C49),"") -> 0.1827957 | F49: =ABS(D49-C49) -> 17
A50: MM-1013 | B50: =Raw_Sales_Weekly!E611 -> 49 | C50: =Raw_Sales_Weekly!C611 -> 103 | D50: =ROUND(FORECAST(B50,Raw_Sales_Weekly!$C$563:$C$608,Raw_Sales_Weekly!$E$563:$E$608),0) -> 110 | E50: =IFERROR(ABS((D50-C50)/C50),"") -> 0.067961165 | F50: =ABS(D50-C50) -> 7
A51: MM-1013 | B51: =Raw_Sales_Weekly!E612 -> 50 | C51: =Raw_Sales_Weekly!C612 -> 111 | D51: =ROUND(FORECAST(B51,Raw_Sales_Weekly!$C$563:$C$608,Raw_Sales_Weekly!$E$563:$E$608),0) -> 110 | E51: =IFERROR(ABS((D51-C51)/C51),"") -> 0.009009009 | F51: =ABS(D51-C51) -> 1
A52: MM-1013 | B52: =Raw_Sales_Weekly!E613 -> 51 | C52: =Raw_Sales_Weekly!C613 -> 129 | D52: =ROUND(FORECAST(B52,Raw_Sales_Weekly!$C$563:$C$608,Raw_Sales_Weekly!$E$563:$E$608),0) -> 110 | E52: =IFERROR(ABS((D52-C52)/C52),"") -> 0.14728682 | F52: =ABS(D52-C52) -> 19
A53: MM-1013 | B53: =Raw_Sales_Weekly!E614 -> 52 | C53: =Raw_Sales_Weekly!C614 -> 89 | D53: =ROUND(FORECAST(B53,Raw_Sales_Weekly!$C$563:$C$608,Raw_Sales_Weekly!$E$563:$E$608),0) -> 110 | E53: =IFERROR(ABS((D53-C53)/C53),"") -> 0.23595506 | F53: =ABS(D53-C53) -> 21
A54: MM-1015 | B54: =Raw_Sales_Weekly!E713 -> 47 | C54: =Raw_Sales_Weekly!C713 -> 93 | D54: =ROUND(FORECAST(B54,Raw_Sales_Weekly!$C$667:$C$712,Raw_Sales_Weekly!$E$667:$E$712),0) -> 150 | E54: =IFERROR(ABS((D54-C54)/C54),"") -> 0.61290323 | F54: =ABS(D54-C54) -> 57
A55: MM-1015 | B55: =Raw_Sales_Weekly!E714 -> 48 | C55: =Raw_Sales_Weekly!C714 -> 285 | D55: =ROUND(FORECAST(B55,Raw_Sales_Weekly!$C$667:$C$712,Raw_Sales_Weekly!$E$667:$E$712),0) -> 148 | E55: =IFERROR(ABS((D55-C55)/C55),"") -> 0.48070175 | F55: =ABS(D55-C55) -> 137
A56: MM-1015 | B56: =Raw_Sales_Weekly!E715 -> 49 | C56: =Raw_Sales_Weekly!C715 -> 364 | D56: =ROUND(FORECAST(B56,Raw_Sales_Weekly!$C$667:$C$712,Raw_Sales_Weekly!$E$667:$E$712),0) -> 147 | E56: =IFERROR(ABS((D56-C56)/C56),"") -> 0.59615385 | F56: =ABS(D56-C56) -> 217
A57: MM-1015 | B57: =Raw_Sales_Weekly!E716 -> 50 | C57: =Raw_Sales_Weekly!C716 -> 60 | D57: =ROUND(FORECAST(B57,Raw_Sales_Weekly!$C$667:$C$712,Raw_Sales_Weekly!$E$667:$E$712),0) -> 145 | E57: =IFERROR(ABS((D57-C57)/C57),"") -> 1.4166667 | F57: =ABS(D57-C57) -> 85
A58: MM-1015 | B58: =Raw_Sales_Weekly!E717 -> 51 | C58: =Raw_Sales_Weekly!C717 -> 45 | D58: =ROUND(FORECAST(B58,Raw_Sales_Weekly!$C$667:$C$712,Raw_Sales_Weekly!$E$667:$E$712),0) -> 143 | E58: =IFERROR(ABS((D58-C58)/C58),"") -> 2.1777778 | F58: =ABS(D58-C58) -> 98
A59: MM-1015 | B59: =Raw_Sales_Weekly!E718 -> 52 | C59: =Raw_Sales_Weekly!C718 -> 120 | D59: =ROUND(FORECAST(B59,Raw_Sales_Weekly!$C$667:$C$712,Raw_Sales_Weekly!$E$667:$E$712),0) -> 142 | E59: =IFERROR(ABS((D59-C59)/C59),"") -> 0.18333333 | F59: =ABS(D59-C59) -> 22
A60: MM-1019 | B60: =Raw_Sales_Weekly!E886 -> 47 | C60: =Raw_Sales_Weekly!C886 -> 276 | D60: =ROUND(FORECAST(B60,Raw_Sales_Weekly!$C$840:$C$885,Raw_Sales_Weekly!$E$840:$E$885),0) -> 266 | E60: =IFERROR(ABS((D60-C60)/C60),"") -> 0.036231884 | F60: =ABS(D60-C60) -> 10
A61: MM-1019 | B61: =Raw_Sales_Weekly!E887 -> 48 | C61: =Raw_Sales_Weekly!C887 -> 248 | D61: =ROUND(FORECAST(B61,Raw_Sales_Weekly!$C$840:$C$885,Raw_Sales_Weekly!$E$840:$E$885),0) -> 267 | E61: =IFERROR(ABS((D61-C61)/C61),"") -> 0.076612903 | F61: =ABS(D61-C61) -> 19
A62: MM-1019 | B62: =Raw_Sales_Weekly!E888 -> 49 | C62: =Raw_Sales_Weekly!C888 -> 264 | D62: =ROUND(FORECAST(B62,Raw_Sales_Weekly!$C$840:$C$885,Raw_Sales_Weekly!$E$840:$E$885),0) -> 269 | E62: =IFERROR(ABS((D62-C62)/C62),"") -> 0.018939394 | F62: =ABS(D62-C62) -> 5
A63: MM-1019 | B63: =Raw_Sales_Weekly!E889 -> 50 | C63: =Raw_Sales_Weekly!C889 -> 296 | D63: =ROUND(FORECAST(B63,Raw_Sales_Weekly!$C$840:$C$885,Raw_Sales_Weekly!$E$840:$E$885),0) -> 271 | E63: =IFERROR(ABS((D63-C63)/C63),"") -> 0.084459459 | F63: =ABS(D63-C63) -> 25
A64: MM-1019 | B64: =Raw_Sales_Weekly!E890 -> 51 | C64: =Raw_Sales_Weekly!C890 -> 197 | D64: =ROUND(FORECAST(B64,Raw_Sales_Weekly!$C$840:$C$885,Raw_Sales_Weekly!$E$840:$E$885),0) -> 273 | E64: =IFERROR(ABS((D64-C64)/C64),"") -> 0.3857868 | F64: =ABS(D64-C64) -> 76
A65: MM-1019 | B65: =Raw_Sales_Weekly!E891 -> 52 | C65: =Raw_Sales_Weekly!C891 -> 266 | D65: =ROUND(FORECAST(B65,Raw_Sales_Weekly!$C$840:$C$885,Raw_Sales_Weekly!$E$840:$E$885),0) -> 274 | E65: =IFERROR(ABS((D65-C65)/C65),"") -> 0.030075188 | F65: =ABS(D65-C65) -> 8
A66: MM-1034 | B66: =Raw_Sales_Weekly!E1580 -> 47 | C66: =Raw_Sales_Weekly!C1580 -> 41 | D66: =ROUND(FORECAST(B66,Raw_Sales_Weekly!$C$1534:$C$1579,Raw_Sales_Weekly!$E$1534:$E$1579),0) -> 44 | E66: =IFERROR(ABS((D66-C66)/C66),"") -> 0.073170732 | F66: =ABS(D66-C66) -> 3
A67: MM-1034 | B67: =Raw_Sales_Weekly!E1581 -> 48 | C67: =Raw_Sales_Weekly!C1581 -> 52 | D67: =ROUND(FORECAST(B67,Raw_Sales_Weekly!$C$1534:$C$1579,Raw_Sales_Weekly!$E$1534:$E$1579),0) -> 44 | E67: =IFERROR(ABS((D67-C67)/C67),"") -> 0.15384615 | F67: =ABS(D67-C67) -> 8
A68: MM-1034 | B68: =Raw_Sales_Weekly!E1582 -> 49 | C68: =Raw_Sales_Weekly!C1582 -> 43 | D68: =ROUND(FORECAST(B68,Raw_Sales_Weekly!$C$1534:$C$1579,Raw_Sales_Weekly!$E$1534:$E$1579),0) -> 44 | E68: =IFERROR(ABS((D68-C68)/C68),"") -> 0.023255814 | F68: =ABS(D68-C68) -> 1
A69: MM-1034 | B69: =Raw_Sales_Weekly!E1583 -> 50 | C69: =Raw_Sales_Weekly!C1583 -> 40 | D69: =ROUND(FORECAST(B69,Raw_Sales_Weekly!$C$1534:$C$1579,Raw_Sales_Weekly!$E$1534:$E$1579),0) -> 44 | E69: =IFERROR(ABS((D69-C69)/C69),"") -> 0.1 | F69: =ABS(D69-C69) -> 4
A70: MM-1034 | B70: =Raw_Sales_Weekly!E1584 -> 51 | C70: =Raw_Sales_Weekly!C1584 -> 52 | D70: =ROUND(FORECAST(B70,Raw_Sales_Weekly!$C$1534:$C$1579,Raw_Sales_Weekly!$E$1534:$E$1579),0) -> 44 | E70: =IFERROR(ABS((D70-C70)/C70),"") -> 0.15384615 | F70: =ABS(D70-C70) -> 8
A71: MM-1034 | B71: =Raw_Sales_Weekly!E1585 -> 52 | C71: =Raw_Sales_Weekly!C1585 -> 48 | D71: =ROUND(FORECAST(B71,Raw_Sales_Weekly!$C$1534:$C$1579,Raw_Sales_Weekly!$E$1534:$E$1579),0) -> 44 | E71: =IFERROR(ABS((D71-C71)/C71),"") -> 0.083333333 | F71: =ABS(D71-C71) -> 4
A72: MM-1018 | B72: =Raw_Sales_Weekly!E834 -> 47 | C72: =Raw_Sales_Weekly!C834 -> 146 | D72: =ROUND(FORECAST(B72,Raw_Sales_Weekly!$C$788:$C$833,Raw_Sales_Weekly!$E$788:$E$833),0) -> 179 | E72: =IFERROR(ABS((D72-C72)/C72),"") -> 0.2260274 | F72: =ABS(D72-C72) -> 33
A73: MM-1018 | B73: =Raw_Sales_Weekly!E835 -> 48 | C73: =Raw_Sales_Weekly!C835 -> 207 | D73: =ROUND(FORECAST(B73,Raw_Sales_Weekly!$C$788:$C$833,Raw_Sales_Weekly!$E$788:$E$833),0) -> 178 | E73: =IFERROR(ABS((D73-C73)/C73),"") -> 0.14009662 | F73: =ABS(D73-C73) -> 29
A74: MM-1018 | B74: =Raw_Sales_Weekly!E836 -> 49 | C74: =Raw_Sales_Weekly!C836 -> 97 | D74: =ROUND(FORECAST(B74,Raw_Sales_Weekly!$C$788:$C$833,Raw_Sales_Weekly!$E$788:$E$833),0) -> 178 | E74: =IFERROR(ABS((D74-C74)/C74),"") -> 0.83505155 | F74: =ABS(D74-C74) -> 81
A75: MM-1018 | B75: =Raw_Sales_Weekly!E837 -> 50 | C75: =Raw_Sales_Weekly!C837 -> 196 | D75: =ROUND(FORECAST(B75,Raw_Sales_Weekly!$C$788:$C$833,Raw_Sales_Weekly!$E$788:$E$833),0) -> 178 | E75: =IFERROR(ABS((D75-C75)/C75),"") -> 0.091836735 | F75: =ABS(D75-C75) -> 18
A76: MM-1018 | B76: =Raw_Sales_Weekly!E838 -> 51 | C76: =Raw_Sales_Weekly!C838 -> 179 | D76: =ROUND(FORECAST(B76,Raw_Sales_Weekly!$C$788:$C$833,Raw_Sales_Weekly!$E$788:$E$833),0) -> 178 | E76: =IFERROR(ABS((D76-C76)/C76),"") -> 0.0055865922 | F76: =ABS(D76-C76) -> 1
A77: MM-1018 | B77: =Raw_Sales_Weekly!E839 -> 52 | C77: =Raw_Sales_Weekly!C839 -> 145 | D77: =ROUND(FORECAST(B77,Raw_Sales_Weekly!$C$788:$C$833,Raw_Sales_Weekly!$E$788:$E$833),0) -> 178 | E77: =IFERROR(ABS((D77-C77)/C77),"") -> 0.22758621 | F77: =ABS(D77-C77) -> 33
A78: MM-1026 | B78: =Raw_Sales_Weekly!E1248 -> 47 | C78: =Raw_Sales_Weekly!C1248 -> 58 | D78: =ROUND(FORECAST(B78,Raw_Sales_Weekly!$C$1202:$C$1247,Raw_Sales_Weekly!$E$1202:$E$1247),0) -> 69 | E78: =IFERROR(ABS((D78-C78)/C78),"") -> 0.18965517 | F78: =ABS(D78-C78) -> 11
A79: MM-1026 | B79: =Raw_Sales_Weekly!E1249 -> 48 | C79: =Raw_Sales_Weekly!C1249 -> 40 | D79: =ROUND(FORECAST(B79,Raw_Sales_Weekly!$C$1202:$C$1247,Raw_Sales_Weekly!$E$1202:$E$1247),0) -> 68 | E79: =IFERROR(ABS((D79-C79)/C79),"") -> 0.7 | F79: =ABS(D79-C79) -> 28
A80: MM-1026 | B80: =Raw_Sales_Weekly!E1250 -> 49 | C80: =Raw_Sales_Weekly!C1250 -> 22 | D80: =ROUND(FORECAST(B80,Raw_Sales_Weekly!$C$1202:$C$1247,Raw_Sales_Weekly!$E$1202:$E$1247),0) -> 68 | E80: =IFERROR(ABS((D80-C80)/C80),"") -> 2.0909091 | F80: =ABS(D80-C80) -> 46
A81: MM-1026 | B81: =Raw_Sales_Weekly!E1251 -> 50 | C81: =Raw_Sales_Weekly!C1251 -> 17 | D81: =ROUND(FORECAST(B81,Raw_Sales_Weekly!$C$1202:$C$1247,Raw_Sales_Weekly!$E$1202:$E$1247),0) -> 68 | E81: =IFERROR(ABS((D81-C81)/C81),"") -> 3 | F81: =ABS(D81-C81) -> 51
A82: MM-1026 | B82: =Raw_Sales_Weekly!E1252 -> 51 | C82: =Raw_Sales_Weekly!C1252 -> 47 | D82: =ROUND(FORECAST(B82,Raw_Sales_Weekly!$C$1202:$C$1247,Raw_Sales_Weekly!$E$1202:$E$1247),0) -> 68 | E82: =IFERROR(ABS((D82-C82)/C82),"") -> 0.44680851 | F82: =ABS(D82-C82) -> 21
A83: MM-1026 | B83: =Raw_Sales_Weekly!E1253 -> 52 | C83: =Raw_Sales_Weekly!C1253 -> 65 | D83: =ROUND(FORECAST(B83,Raw_Sales_Weekly!$C$1202:$C$1247,Raw_Sales_Weekly!$E$1202:$E$1247),0) -> 68 | E83: =IFERROR(ABS((D83-C83)/C83),"") -> 0.046153846 | F83: =ABS(D83-C83) -> 3
A84: MM-1009 | B84: =Raw_Sales_Weekly!E434 -> 47 | C84: =Raw_Sales_Weekly!C434 -> 122 | D84: =ROUND(FORECAST(B84,Raw_Sales_Weekly!$C$388:$C$433,Raw_Sales_Weekly!$E$388:$E$433),0) -> 167 | E84: =IFERROR(ABS((D84-C84)/C84),"") -> 0.36885246 | F84: =ABS(D84-C84) -> 45
A85: MM-1009 | B85: =Raw_Sales_Weekly!E435 -> 48 | C85: =Raw_Sales_Weekly!C435 -> 169 | D85: =ROUND(FORECAST(B85,Raw_Sales_Weekly!$C$388:$C$433,Raw_Sales_Weekly!$E$388:$E$433),0) -> 166 | E85: =IFERROR(ABS((D85-C85)/C85),"") -> 0.017751479 | F85: =ABS(D85-C85) -> 3
A86: MM-1009 | B86: =Raw_Sales_Weekly!E436 -> 49 | C86: =Raw_Sales_Weekly!C436 -> 138 | D86: =ROUND(FORECAST(B86,Raw_Sales_Weekly!$C$388:$C$433,Raw_Sales_Weekly!$E$388:$E$433),0) -> 166 | E86: =IFERROR(ABS((D86-C86)/C86),"") -> 0.20289855 | F86: =ABS(D86-C86) -> 28
A87: MM-1009 | B87: =Raw_Sales_Weekly!E437 -> 50 | C87: =Raw_Sales_Weekly!C437 -> 117 | D87: =ROUND(FORECAST(B87,Raw_Sales_Weekly!$C$388:$C$433,Raw_Sales_Weekly!$E$388:$E$433),0) -> 165 | E87: =IFERROR(ABS((D87-C87)/C87),"") -> 0.41025641 | F87: =ABS(D87-C87) -> 48
A88: MM-1009 | B88: =Raw_Sales_Weekly!E438 -> 51 | C88: =Raw_Sales_Weekly!C438 -> 141 | D88: =ROUND(FORECAST(B88,Raw_Sales_Weekly!$C$388:$C$433,Raw_Sales_Weekly!$E$388:$E$433),0) -> 165 | E88: =IFERROR(ABS((D88-C88)/C88),"") -> 0.17021277 | F88: =ABS(D88-C88) -> 24
A89: MM-1009 | B89: =Raw_Sales_Weekly!E439 -> 52 | C89: =Raw_Sales_Weekly!C439 -> 138 | D89: =ROUND(FORECAST(B89,Raw_Sales_Weekly!$C$388:$C$433,Raw_Sales_Weekly!$E$388:$E$433),0) -> 164 | E89: =IFERROR(ABS((D89-C89)/C89),"") -> 0.1884058 | F89: =ABS(D89-C89) -> 26
A90: MM-1012 | B90: =Raw_Sales_Weekly!E557 -> 45 | C90: =Raw_Sales_Weekly!C557 -> 46 | D90: =ROUND(FORECAST(B90,Raw_Sales_Weekly!$C$513:$C$556,Raw_Sales_Weekly!$E$513:$E$556),0) -> 41 | E90: =IFERROR(ABS((D90-C90)/C90),"") -> 0.10869565 | F90: =ABS(D90-C90) -> 5
A91: MM-1012 | B91: =Raw_Sales_Weekly!E558 -> 46 | C91: =Raw_Sales_Weekly!C558 -> 43 | D91: =ROUND(FORECAST(B91,Raw_Sales_Weekly!$C$513:$C$556,Raw_Sales_Weekly!$E$513:$E$556),0) -> 41 | E91: =IFERROR(ABS((D91-C91)/C91),"") -> 0.046511628 | F91: =ABS(D91-C91) -> 2
A92: MM-1012 | B92: =Raw_Sales_Weekly!E559 -> 47 | C92: =Raw_Sales_Weekly!C559 -> 12 | D92: =ROUND(FORECAST(B92,Raw_Sales_Weekly!$C$513:$C$556,Raw_Sales_Weekly!$E$513:$E$556),0) -> 40 | E92: =IFERROR(ABS((D92-C92)/C92),"") -> 2.3333333 | F92: =ABS(D92-C92) -> 28
A93: MM-1012 | B93: =Raw_Sales_Weekly!E560 -> 48 | C93: =Raw_Sales_Weekly!C560 -> 0 | D93: =ROUND(FORECAST(B93,Raw_Sales_Weekly!$C$513:$C$556,Raw_Sales_Weekly!$E$513:$E$556),0) -> 40 | E93: =IFERROR(ABS((D93-C93)/C93),"") | F93: =ABS(D93-C93) -> 40
A94: MM-1012 | B94: =Raw_Sales_Weekly!E561 -> 49 | C94: =Raw_Sales_Weekly!C561 -> 24 | D94: =ROUND(FORECAST(B94,Raw_Sales_Weekly!$C$513:$C$556,Raw_Sales_Weekly!$E$513:$E$556),0) -> 40 | E94: =IFERROR(ABS((D94-C94)/C94),"") -> 0.66666667 | F94: =ABS(D94-C94) -> 16
A95: MM-1012 | B95: =Raw_Sales_Weekly!E562 -> 50 | C95: =Raw_Sales_Weekly!C562 -> 7 | D95: =ROUND(FORECAST(B95,Raw_Sales_Weekly!$C$513:$C$556,Raw_Sales_Weekly!$E$513:$E$556),0) -> 40 | E95: =IFERROR(ABS((D95-C95)/C95),"") -> 4.7142857 | F95: =ABS(D95-C95) -> 33
A96: MM-1027 | B96: =Raw_Sales_Weekly!E1299 -> 46 | C96: =Raw_Sales_Weekly!C1299 -> 77 | D96: =ROUND(FORECAST(B96,Raw_Sales_Weekly!$C$1254:$C$1298,Raw_Sales_Weekly!$E$1254:$E$1298),0) -> 109 | E96: =IFERROR(ABS((D96-C96)/C96),"") -> 0.41558442 | F96: =ABS(D96-C96) -> 32
A97: MM-1027 | B97: =Raw_Sales_Weekly!E1300 -> 47 | C97: =Raw_Sales_Weekly!C1300 -> 73 | D97: =ROUND(FORECAST(B97,Raw_Sales_Weekly!$C$1254:$C$1298,Raw_Sales_Weekly!$E$1254:$E$1298),0) -> 109 | E97: =IFERROR(ABS((D97-C97)/C97),"") -> 0.49315068 | F97: =ABS(D97-C97) -> 36
A98: MM-1027 | B98: =Raw_Sales_Weekly!E1301 -> 48 | C98: =Raw_Sales_Weekly!C1301 -> 12 | D98: =ROUND(FORECAST(B98,Raw_Sales_Weekly!$C$1254:$C$1298,Raw_Sales_Weekly!$E$1254:$E$1298),0) -> 109 | E98: =IFERROR(ABS((D98-C98)/C98),"") -> 8.0833333 | F98: =ABS(D98-C98) -> 97
A99: MM-1027 | B99: =Raw_Sales_Weekly!E1302 -> 49 | C99: =Raw_Sales_Weekly!C1302 -> 176 | D99: =ROUND(FORECAST(B99,Raw_Sales_Weekly!$C$1254:$C$1298,Raw_Sales_Weekly!$E$1254:$E$1298),0) -> 110 | E99: =IFERROR(ABS((D99-C99)/C99),"") -> 0.375 | F99: =ABS(D99-C99) -> 66
A100: MM-1027 | B100: =Raw_Sales_Weekly!E1303 -> 50 | C100: =Raw_Sales_Weekly!C1303 -> 196 | D100: =ROUND(FORECAST(B100,Raw_Sales_Weekly!$C$1254:$C$1298,Raw_Sales_Weekly!$E$1254:$E$1298),0) -> 110 | E100: =IFERROR(ABS((D100-C100)/C100),"") -> 0.43877551 | F100: =ABS(D100-C100) -> 86
A101: MM-1027 | B101: =Raw_Sales_Weekly!E1304 -> 51 | C101: =Raw_Sales_Weekly!C1304 -> 195 | D101: =ROUND(FORECAST(B101,Raw_Sales_Weekly!$C$1254:$C$1298,Raw_Sales_Weekly!$E$1254:$E$1298),0) -> 110 | E101: =IFERROR(ABS((D101-C101)/C101),"") -> 0.43589744 | F101: =ABS(D101-C101) -> 85
A102: MM-1004 | B102: =Raw_Sales_Weekly!E216 -> 47 | C102: =Raw_Sales_Weekly!C216 -> 144 | D102: =ROUND(FORECAST(B102,Raw_Sales_Weekly!$C$170:$C$215,Raw_Sales_Weekly!$E$170:$E$215),0) -> 167 | E102: =IFERROR(ABS((D102-C102)/C102),"") -> 0.15972222 | F102: =ABS(D102-C102) -> 23
...

Sheet Forecast_MAPE_Summary
B2: Forecast Accuracy Summary (MAPE)
B3: MAPE = mean absolute percentage error across each SKU's 6-week holdout. Lower is better.
B5: Catalog-wide MAPE (all holdout weeks, all eligible SKUs): | F5: =AVERAGE(Forecast_Detail!E6:E221) -> 0.60511
B6: Catalog-wide WAPE (volume-weighted, robust to near-zero weeks): | F6: =SUM(Forecast_Detail!F6:F221)/SUM(Forecast_Detail!C6:C221) -> 0.28053708
B7: Note: naive MAPE is inflated by a handful of holdout weeks with very low actual demand (a single-digit actual turns a small unit error into a triple-digit % error). WAPE weights every week by its volume and is the more representative accuracy figure for this catalog.
A8: SKU_ID | B8: SKU_Description | C8: Weeks_of_History | D8: Eligible_for_Forecast | E8: MAPE | F8: WAPE | G8: Accuracy_Tier
A9: MM-1033 | B9: =ABC_XYZ_Classification!B6 -> Raw Material Item 04 - Raw Material - Metal Stock | C9: 50 | D9: Yes | E9: =AVERAGEIF(Forecast_Detail!$A$6:$A$221,A9,Forecast_Detail!$E$6:$E$221) -> 0.3043307 | F9: =SUMIF(Forecast_Detail!$A$6:$A$221,A9,Forecast_Detail!$F$6:$F$221)/SUMIF(Forecast_Detail!$A$6:$A$221,A9,Forecast_Detail!$C$6:$C$221) -> 0.31225296 | G9: =IF(F9<=0.15,"Good",IF(F9<=0.3,"Fair","Poor")) -> Poor
A10: MM-1032 | B10: =ABC_XYZ_Classification!B7 -> Raw Material Item 03 - Raw Material - Metal Stock | C10: 51 | D10: Yes | E10: =AVERAGEIF(Forecast_Detail!$A$6:$A$221,A10,Forecast_Detail!$E$6:$E$221) -> 4.5113043 | F10: =SUMIF(Forecast_Detail!$A$6:$A$221,A10,Forecast_Detail!$F$6:$F$221)/SUMIF(Forecast_Detail!$A$6:$A$221,A10,Forecast_Detail!$C$6:$C$221) -> 0.37090909 | G10: =IF(F10<=0.15,"Good",IF(F10<=0.3,"Fair","Poor")) -> Poor
A11: MM-1025 | B11: =ABC_XYZ_Classification!B8 -> Pneumatic Components Item 01 - Pneumatic Components | C11: 50 | D11: Yes | E11: =AVERAGEIF(Forecast_Detail!$A$6:$A$221,A11,Forecast_Detail!$E$6:$E$221) -> 0.34896394 | F11: =SUMIF(Forecast_Detail!$A$6:$A$221,A11,Forecast_Detail!$F$6:$F$221)/SUMIF(Forecast_Detail!$A$6:$A$221,A11,Forecast_Detail!$C$6:$C$221) -> 0.51141553 | G11: =IF(F11<=0.15,"Good",IF(F11<=0.3,"Fair","Poor")) -> Poor
A12: MM-1030 | B12: =ABC_XYZ_Classification!B9 -> Raw Material Item 01 - Raw Material - Metal Stock | C12: 51 | D12: Yes | E12: =AVERAGEIF(Forecast_Detail!$A$6:$A$221,A12,Forecast_Detail!$E$6:$E$221) -> 3.0077113 | F12: =SUMIF(Forecast_Detail!$A$6:$A$221,A12,Forecast_Detail!$F$6:$F$221)/SUMIF(Forecast_Detail!$A$6:$A$221,A12,Forecast_Detail!$C$6:$C$221) -> 0.54545455 | G12: =IF(F12<=0.15,"Good",IF(F12<=0.3,"Fair","Poor")) -> Poor
A13: MM-1014 | B13: =ABC_XYZ_Classification!B10 -> Electric Motors Item 05 - Electric Motors & Drives | C13: 52 | D13: Yes | E13: =AVERAGEIF(Forecast_Detail!$A$6:$A$221,A13,Forecast_Detail!$E$6:$E$221) -> 0.080673814 | F13: =SUMIF(Forecast_Detail!$A$6:$A$221,A13,Forecast_Detail!$F$6:$F$221)/SUMIF(Forecast_Detail!$A$6:$A$221,A13,Forecast_Detail!$C$6:$C$221) -> 0.075376884 | G13: =IF(F13<=0.15,"Good",IF(F13<=0.3,"Fair","Poor")) -> Good
A14: MM-1010 | B14: =ABC_XYZ_Classification!B11 -> Electric Motors Item 01 - Electric Motors & Drives | C14: 52 | D14: Yes | E14: =AVERAGEIF(Forecast_Detail!$A$6:$A$221,A14,Forecast_Detail!$E$6:$E$221) -> 0.1272116 | F14: =SUMIF(Forecast_Detail!$A$6:$A$221,A14,Forecast_Detail!$F$6:$F$221)/SUMIF(Forecast_Detail!$A$6:$A$221,A14,Forecast_Detail!$C$6:$C$221) -> 0.11571675 | G14: =IF(F14<=0.15,"Good",IF(F14<=0.3,"Fair","Poor")) -> Good
A15: MM-1011 | B15: =ABC_XYZ_Classification!B12 -> Electric Motors Item 02 - Electric Motors & Drives | C15: 21 | D15: Yes | E15: =AVERAGEIF(Forecast_Detail!$A$6:$A$221,A15,Forecast_Detail!$E$6:$E$221) -> 0.14687925 | F15: =SUMIF(Forecast_Detail!$A$6:$A$221,A15,Forecast_Detail!$F$6:$F$221)/SUMIF(Forecast_Detail!$A$6:$A$221,A15,Forecast_Detail!$C$6:$C$221) -> 0.14320988 | G15: =IF(F15<=0.15,"Good",IF(F15<=0.3,"Fair","Poor")) -> Good
A16: MM-1013 | B16: =ABC_XYZ_Classification!B13 -> Electric Motors Item 04 - Electric Motors & Drives | C16: 52 | D16: Yes | E16: =AVERAGEIF(Forecast_Detail!$A$6:$A$221,A16,Forecast_Detail!$E$6:$E$221) -> 0.11159274 | F16: =SUMIF(Forecast_Detail!$A$6:$A$221,A16,Forecast_Detail!$F$6:$F$221)/SUMIF(Forecast_Detail!$A$6:$A$221,A16,Forecast_Detail!$C$6:$C$221) -> 0.10658307 | G16: =IF(F16<=0.15,"Good",IF(F16<=0.3,"Fair","Poor")) -> Good
A17: MM-1015 | B17: =ABC_XYZ_Classification!B14 -> Sensors Item 01 - Sensors & Controls | C17: 52 | D17: Yes | E17: =AVERAGEIF(Forecast_Detail!$A$6:$A$221,A17,Forecast_Detail!$E$6:$E$221) -> 0.9112561 | F17: =SUMIF(Forecast_Detail!$A$6:$A$221,A17,Forecast_Detail!$F$6:$F$221)/SUMIF(Forecast_Detail!$A$6:$A$221,A17,Forecast_Detail!$C$6:$C$221) -> 0.63702172 | G17: =IF(F17<=0.15,"Good",IF(F17<=0.3,"Fair","Poor")) -> Poor
A18: MM-1019 | B18: =ABC_XYZ_Classification!B15 -> Sensors Item 05 - Sensors & Controls | C18: 52 | D18: Yes | E18: =AVERAGEIF(Forecast_Detail!$A$6:$A$221,A18,Forecast_Detail!$E$6:$E$221) -> 0.10535094 | F18: =SUMIF(Forecast_Detail!$A$6:$A$221,A18,Forecast_Detail!$F$6:$F$221)/SUMIF(Forecast_Detail!$A$6:$A$221,A18,Forecast_Detail!$C$6:$C$221) -> 0.092436975 | G18: =IF(F18<=0.15,"Good",IF(F18<=0.3,"Fair","Poor")) -> Good
A19: MM-1034 | B19: =ABC_XYZ_Classification!B16 -> Raw Material Item 05 - Raw Material - Metal Stock | C19: 52 | D19: Yes | E19: =AVERAGEIF(Forecast_Detail!$A$6:$A$221,A19,Forecast_Detail!$E$6:$E$221) -> 0.097908698 | F19: =SUMIF(Forecast_Detail!$A$6:$A$221,A19,Forecast_Detail!$F$6:$F$221)/SUMIF(Forecast_Detail!$A$6:$A$221,A19,Forecast_Detail!$C$6:$C$221) -> 0.10144928 | G19: =IF(F19<=0.15,"Good",IF(F19<=0.3,"Fair","Poor")) -> Good
A20: MM-1018 | B20: =ABC_XYZ_Classification!B17 -> Sensors Item 04 - Sensors & Controls | C20: 52 | D20: Yes | E20: =AVERAGEIF(Forecast_Detail!$A$6:$A$221,A20,Forecast_Detail!$E$6:$E$221) -> 0.25436418 | F20: =SUMIF(Forecast_Detail!$A$6:$A$221,A20,Forecast_Detail!$F$6:$F$221)/SUMIF(Forecast_Detail!$A$6:$A$221,A20,Forecast_Detail!$C$6:$C$221) -> 0.20103093 | G20: =IF(F20<=0.15,"Good",IF(F20<=0.3,"Fair","Poor")) -> Fair
... A41: MM-1022 | B41: =ABC_XYZ_Classification!B38 -> Seals Item 03 - Seals & Gaskets | C41: 52 | D41: Yes | E41: =AVERAGEIF(Forecast_Detail!$A$6:$A$221,A41,Forecast_Detail!$E$6:$E$221) -> 0.10162244 | F41: =SUMIF(Forecast_Detail!$A$6:$A$221,A41,Forecast_Detail!$F$6:$F$221)/SUMIF(Forecast_Detail!$A$6:$A$221,A41,Forecast_Detail!$C$6:$C$221) -> 0.1003861 | G41: =IF(F41<=0.15,"Good",IF(F41<=0.3,"Fair","Poor")) -> Good
A42: MM-1006 | B42: =ABC_XYZ_Classification!B39 -> Bearings Item 02 - Bearings & Bushings | C42: 10 | D42: No | E42: N/A | F42: N/A | G42: Insufficient history
A43: MM-1003 | B43: =ABC_XYZ_Classification!B40 -> Fasteners Item 04 - Fasteners & Hardware | C43: 12 | D43: No | E43: N/A | F43: N/A | G43: Insufficient history
A44: MM-1024 | B44: =ABC_XYZ_Classification!B41 -> Seals Item 05 - Seals & Gaskets | C44: 52 | D44: Yes | E44: =AVERAGEIF(Forecast_Detail!$A$6:$A$221,A44,Forecast_Detail!$E$6:$E$221) -> 0.57627571 | F44: =SUMIF(Forecast_Detail!$A$6:$A$221,A44,Forecast_Detail!$F$6:$F$221)/SUMIF(Forecast_Detail!$A$6:$A$221,A44,Forecast_Detail!$C$6:$C$221) -> 0.43445693 | G44: =IF(F44<=0.15,"Good",IF(F44<=0.3,"Fair","Poor")) -> Poor
A45: MM-1031 | B45: =ABC_XYZ_Classification!B42 -> Raw Material Item 02 - Raw Material - Metal Stock | C45: 5 | D45: No | E45: N/A | F45: N/A | G45: Insufficient history
A46: MM-1023 | B46: =ABC_XYZ_Classification!B43 -> Seals Item 04 - Seals & Gaskets | C46: 52 | D46: Yes | E46: =AVERAGEIF(Forecast_Detail!$A$6:$A$221,A46,Forecast_Detail!$E$6:$E$221) -> 0.21788767 | F46: =SUMIF(Forecast_Detail!$A$6:$A$221,A46,Forecast_Detail!$F$6:$F$221)/SUMIF(Forecast_Detail!$A$6:$A$221,A46,Forecast_Detail!$C$6:$C$221) -> 0.20127119 | G46: =IF(F46<=0.15,"Good",IF(F46<=0.3,"Fair","Poor")) -> Fair
A47: MM-1021 | B47: =ABC_XYZ_Classification!B44 -> Seals Item 02 - Seals & Gaskets | C47: 52 | D47: Yes | E47: =AVERAGEIF(Forecast_Detail!$A$6:$A$221,A47,Forecast_Detail!$E$6:$E$221) -> 0.19603779 | F47: =SUMIF(Forecast_Detail!$A$6:$A$221,A47,Forecast_Detail!$F$6:$F$221)/SUMIF(Forecast_Detail!$A$6:$A$221,A47,Forecast_Detail!$C$6:$C$221) -> 0.17359413 | G47: =IF(F47<=0.15,"Good",IF(F47<=0.3,"Fair","Poor")) -> Fair
A48: MM-1037 | B48: =ABC_XYZ_Classification!B45 -> Packaging Materials Item 03 - Packaging Materials | C48: 13 | D48: No | E48: N/A | F48: N/A | G48: Insufficient history
